Workbook

Sheet Table of Contents
A1: File | B1: Electronics Manufacturing Venture | E1: Red | F1: Borders
A2: Author(s) | B2: Krishnamurthy Bindumadhavan, Sri Krishna P | E2: Blue | F2: Input cells
A3: Tab | B3: Table of contents | E3: Green | F3: Cells linked to another sheet
A4: Created | B4: 46033 | E4: Black | F4: Cells containing a calculation on the same sheet
C6: Worksheets
C7: Table of Contents | E7: Input Cells | F7: Description
C8: Assumptions | E8: Yes | F8: All relevant assumptions
C9: Net Income Analysis | E9: No | F9: NI trend and related analysis
C10: Revenue Analysis | E10: No | F10: Revenue trend and related analysis
C11: Expense Analysis | E11: No | F11: Expense trend and related analysis
C12: Casflow Analysis | E12: No | F12: Cashflow trend and waterfall
C13: Income Statement | E13: No | F13: Income Statement
C14: Balance Sheet | E14: No | F14: Balance Sheet
C15: Casflow Statement | E15: No | F15: Statement of Cashflows
C16: Valuation | E16: Yes | F16: NPV and IRR calculations
C17: Loan Repayment Schedule | E17: No | F17: Loan Repayment Schedule
C18: Depreciation Schedule | E18: No | F18: Depreciation Schedule
... C20: Existing Practice Valuation | E20: Yes | F20: Valuation for purchase of existing practice
A1048543: sri rama jayam
A1048544: sri rama jayam
A1048545: sri rama jayam

Sheet Bill of materials
A1: Optimised UAV Bill of Materials — PX4 + ROS 2 + Jetson Orin Nano + Livox Mid-360
A2: Target AUW: 3.2–3.4 kg | Reliability-first | Internationally proven components | Prices in INR (June 2026)
A3: Category | B3: Recommended Component | C3: Manufacturer | D3: Model | E3: Qty | F3: Verified Unit Price (₹) | G3: Total Cost (₹) | H3: Weight (g) | I3: Source | J3: Reason | K3: Alternative Replaced
A4: Frame | B4: Tarot TL65B44 X6 CF 650mm Frame | C4: Tarot | D4: TL65B44 650mm X6 | E4: 1 | F4: 8500 | G4: 8500 | H4: 415 | I4: Banggood/AliExpress ~$95 ≈ ₹8,500 | J4: CF, proven airframe, lighter | K4: Skynexus S-1 CF 650mm (~₹16,999)
A5: Flight Controller | B5: Holybro Pixhawk 6C (FC only) | C5: Holybro | D5: Pixhawk 6C Standard Set | E5: 1 | F5: 28500 | G5: 28500 | H5: 38 | I5: holybro.com $339 ≈ ₹28,500 | J5: PX4 native, globally proven | K5: Agam Autopilot V6X-RT (~₹42,000)
A6: GPS | B6: Holybro M10-100 GPS | C6: Holybro | D6: M10-100 u-blox M10 | E6: 1 | F6: 6200 | G6: 6200 | H6: 18 | I6: holybro.com ~$74 ≈ ₹6,200 | J6: u-blox M10, CAN/UART, cheaper | K6: Agam GNSS01 CAN (~₹16,000)
A7: Telemetry | B7: Holybro SiK Telemetry Radio V3 915MHz | C7: Holybro / RFDesign | D7: SiK V3 915MHz 500mW | E7: 1 | F7: 7800 | G7: 7800 | H7: 16 | I7: holybro.com ~$88 ≈ ₹7,800 | J7: 500mW, MAVLink native, FHSS | K7: Generic SiK V3 433MHz (~₹9,566)
A8: RC System | B8: RadioMaster TX16S MkII + RP3 ELRS Rx | C8: RadioMaster | D8: TX16S MkII ELRS + RP3 | E8: 1 | F8: 18500 | G8: 18500 | H8: 952 | I8: UAVGarage India ~₹17,999+₹500 | J8: ELRS, 250Hz, globally standard | K8: Same — price verified
A9: Motors | B9: T-Motor MN3110-17 700KV ×4 | C9: T-Motor | D9: MN3110-17 700KV | E9: 4 | F9: 5200 | G9: 20800 | H9: 110 | I9: tmotor.com ~$62/pc ≈ ₹5,200 | J9: Aerospace grade, long lifespan | K9: Mechtex KV700 (~₹3,200/pc, B2B only)
A10: ESCs | B10: Holybro Kotleta20 DShot ESC ×4 | C10: Holybro | D10: Kotleta20 20A DShot600 | E10: 4 | F10: 3800 | G10: 15200 | H10: 13 | I10: holybro.com ~$45/pc ≈ ₹3,800 | J10: DShot600, PX4 native, CAN | K10: Bharath IBESC 40A (~₹2,500, B2B)
A11: Propellers | B11: T-Motor 11×3.7 CF Props (2 pairs) | C11: T-Motor | D11: T11×3.7 CF CW+CCW | E11: 2 | F11: 2900 | G11: 5800 | H11: 14 | I11: tmotor.com ~$34/pair ≈ ₹2,900 | J11: Balanced, low vibration, CF | K11: Bharath 11×4.7 CF (~₹450/pc, B2B)
A12: Battery | B12: Tattu 6S 8000mAh 25C LiPo | C12: Tattu (Gens Ace) | D12: 6S 22.2V 8000mAh 25C XT60 | E12: 1 | F12: 14716 | G12: 14716 | H12: 800 | I12: RC Mumbai ₹14,716 / UAVGarage ₹13,201 excl. tax | J12: Higher capacity, longer flight time | K12: Tattu R-Line 6S 8000mAh 95C
A13: Power Distribution | B13: Matek FCHUB-12S PDB 5V/12V BEC | C13: Matek Systems | D13: FCHUB-12S | E13: 1 | F13: 2100 | G13: 2100 | H13: 22 | I13: robu.in ~₹2,100 | J13: Public retail, integrated BEC | K13: Flameback 12S PDB (~₹4,600, B2B)
A14: Companion Computer | B14: NVIDIA Jetson Orin Nano 8GB Module | C14: NVIDIA | D14: Jetson Orin Nano 8GB SOM | E14: 1 | F14: 29650 | G14: 29650 | H14: 50 | I14: ThinkRobotics ₹29,650 (verified) | J14: Core requirement, keep as-is | K14: Same — project requirement
A15: LiDAR | B15: Livox Mid-360 3D LiDAR | C15: Livox (DJI) | D15: Mid-360 | E15: 1 | F15: 85000 | G15: 85000 | H15: 265 | I15: Hexaero India ~₹85,000 | J15: Core SLAM requirement, keep | K15: Same — project requirement
... A21: Miscellaneous | B21: Arm/Disarm Safety Switch | C21: Holybro / Generic | D21: PX4 Safety Switch | E21: 1 | F21: 350 | G21: 350 | H21: 12 | I21: robu.in ~₹350 | J21: PX4 mandatory, others removed | K21: Safety+LED+Cooling bundle (~₹2,000)
A23: 💰 TOTAL COMPONENT COST | F23: 260165 | G23: INR — components only, excl. shipping & taxes
A24: ⚖ TOTAL COMPONENT WEIGHT | F24: 3475 | G24: grams — multiplied by quantity
A25: 🕐 ESTIMATED FLIGHT TIME | F25: ~18–22 min | G25: 6S 8000mAh @ ~250W avg cruise draw
A26: 🛸 ESTIMATED TAKEOFF WEIGHT (AUW) | F26: ~3,250 g | G26: Incl. 800g battery + 265g LiDAR + structure
A27: Edge & Fog Node — Rough BOM Estimates (USD)
A28: Note: Directional estimates only, not vendor-verified like the Bill of Materials tab in the main financial model. Get 2-3 real vendor quotes before finalizing. All prices in USD. | F28: =F23/Assumptions!D32 -> 2726.5248
A30: EDGE NODE (ruggedized on-site laptop, per unit)
A31: Category | B31: Component / Spec | C31: Est. Price | D31: Note
A32: Base unit | B32: Rugged laptop base (CPU, RAM, chassis) — Dell Latitude Rugged / Panasonic Toughbook class, i7, 32GB RAM, MIL-STD-810 | C32: 2200 | D32: Base rugged shell + CPU/RAM
A33: GPU | B33: Discrete GPU upgrade (Nvidia T500 / RTX A1000-class or RTX 4060 mobile) for real-time CV inference | C33: 500 | D33: Sized for inference, not training
A34: Storage | B34: 1-2TB NVMe SSD (buffer for raw imagery before fog sync) | C34: 150
A35: Connectivity | B35: 5G/LTE module or dongle for field sites | C35: 150
A36: Enclosure | B36: Rugged carry case + vehicle/field mounts | C36: 200
A37: Power | B37: Portable battery pack / field UPS | C37: 150
A38: Peripherals | B38: Rugged mouse, cables, spare battery | C38: 150
A39: EDGE NODE TOTAL (per unit) | C39: 3500
A41: FOG NODE (one server per worksite)
A42: Category | B42: Component / Spec | C42: Est. Price | D42: Note
A43: Server base | B43: 1U/2U rackmount chassis + single Xeon/EPYC CPU, industrial-grade | C43: 2500
A44: GPU | B44: Single Nvidia RTX A4000/A5000-class (16-24GB VRAM) | C44: 2200 | D44: Sized for site-wide aggregation, not training
A45: RAM | B45: 64-128GB ECC | C45: 500
A46: Storage | B46: 4-8TB NVMe/RAID array | C46: 800 | D46: Buffer before cloud sync
A47: Power | B47: UPS / power backup | C47: 500 | D47: Important for industrial sites w/ unreliable power
A48: Networking | B48: Managed switch + site Wi-Fi access point | C48: 400 | D48: Connects edge nodes on-site
A49: Enclosure | B49: Dust/heat-rated cabinet | C49: 800 | D49: If not in a controlled server room
A50: Uplink | B50: Cellular/satellite modem for cloud sync | C50: 500 | D50: If no fixed internet on-site
A51: Installation | B51: Cabling, mounting, initial config labor | C51: 750 | D51: Midpoint of $500-1,000 range
A52: FOG NODE TOTAL (per unit) | C52: 8950
A54: SUMMARY
A55: Edge node — per unit | C55: 3500
A56: Fog node — per unit | C56: 8950
A57: Combined (1 Edge + 1 Fog) | C57: 12450
A59: FAR EDGE — ROVER (per unit)
A60: Wider uncertainty than Edge/Fog/Drone: industrial UGV chassis pricing is almost entirely quote-only, not publicly listed.
A61: Category | B61: Component / Spec | C61: Est. Price | D61: Note
A62: Chassis + drivetrain | B62: Tracked or 4-wheel skid-steer UGV base, ~30-50kg payload, IP-rated, motors/tracks/controllers bundled | C62: 3000 | D62: Biggest line item & biggest unknown — get real quotes
A63: Battery | B63: 24V/48V LiFePO4 or Li-ion pack, sized for multi-hour confined-space/underground runs | C63: 600
A64: Motion controller | B64: ROS-compatible controller, wheel encoders, IMU | C64: 500
A65: Companion computer | B65: NVIDIA Jetson Orin Nano (same class as drone) | C65: 310
A66: LiDAR | B66: Livox Mid-360-class, for confined-space/underground navigation & mapping | C66: 890
A67: RGB camera | B67: Defect-detection imaging (same class as drone) | C67: 70
A68: Thermal camera | B68: For underground/low-visibility defect detection | C68: 300 | D68: Not needed on drone BOM; rover-specific
A69: Lighting | B69: LED floodlights for dark/underground environments | C69: 150
A70: Comms | B70: RF telemetry + Wi-Fi mesh/repeater | C70: 350 | D70: Tunnels/confined spaces often break line-of-sight RF
A71: GPS | B71: For outdoor site segments | C71: 170
A72: Storage | B72: NVMe SSD buffer | C72: 75
A73: Wiring/mounts/enclosure | B73: Vibration dampening, cable routing, weatherproofing | C73: 300
A74: Misc | B74: E-stop, safety switch, cooling | C74: 200
A75: ROVER TOTAL (per unit) | C75: 6915

Sheet Assumptions
C7: No of business days | D7: =12*(30 - 8) - 10 -> 254
C8: Units per day (initial) | F8: Operating Costs
C9: Growth rate (annual) | D9: 0.06 | F9: Rent | G9: =5000*12 -> 60000 | I9: Headcount increase(annual)
C10: International sales premium | D10: 0.15 | F10: Utilities | G10: =1000*12 -> 12000 | I10: Staff growth rate | J10: 0.11
C11: Annual CPI | D11: 0.03 | F11: Telephone/ Internet | G11: =100*12 -> 1200 | I11: Engineers growth rate | J11: 0.1
C12: Tax rate | D12: 0.35 | F12: Courier/ postage | G12: =1000*12 -> 12000
C13: % of new customers also taking subscription | D13: 0.85 | F13: Marketing & Advertising | G13: =500*12 -> 6000 | I13: CPI Table | J13: Year | U13: Software subscription churn rate | V13: Rate | X13: Country | Y13: Tax rate | AB13: Operating Cost table | AC13: India | AD13: USA | AE13: Europe | AF13: Australia | AG13: Canada | AH13: South America | AI13: Mexico | AJ13: Africa | AK13: Middle East | AL13: Far East | AN13: Certain other Cost table | AO13: India | AP13: USA | AQ13: Europe | AR13: Australia | AS13: Canada | AT13: South America | AU13: Mexico | AV13: Africa | AW13: Middle East | AX13: Far East
C14: Interest Rate | D14: 0.15 | F14: Insurance | G14: =500*12 -> 6000 | J14: 1 | K14: 2 | L14: 3 | M14: 4 | N14: 5 | O14: 6 | P14: 7 | Q14: 8 | R14: 9 | S14: 10
C15: Loan Term | D15: 10 | E15: Years | F15: IT Support | G15: 1000 | I15: India | J15: 0.046 | K15: 0.046 | L15: 0.046 | M15: 0.046 | N15: 0.046 | O15: 0.046 | P15: 0.046 | Q15: 0.046 | R15: 0.046 | S15: 0.046 | U15: India | V15: 0.15 | X15: India | Y15: 0.3 | AB15: Rent | AC15: 6000 | AD15: 0 | AE15: 0 | AF15: 0 | AG15: 0 | AH15: 0 | AI15: 0 | AJ15: 0 | AK15: 0 | AL15: 0 | AN15: Achitect/Designer Fees | AO15: 5000 | AP15: 5000 | AQ15: 5000 | AR15: 5000 | AS15: 5000 | AT15: 5000 | AU15: 5000 | AV15: 5000 | AW15: 5000 | AX15: 5000
C16: Depreciable life | D16: 10 | E16: Years | F16: Legal/ Accountancy | G16: 1000 | I16: USA | J16: 0.02 | K16: 0.02 | L16: 0.02 | M16: 0.02 | N16: 0.02 | O16: 0.02 | P16: 0.02 | Q16: 0.02 | R16: 0.02 | S16: 0.02 | U16: USA | V16: 0.12 | X16: USA | Y16: 0.37 | AB16: Utilities | AC16: 12000 | AD16: 0 | AE16: 0 | AF16: 0 | AG16: 0 | AH16: 0 | AI16: 0 | AJ16: 0 | AK16: 0 | AL16: 0 | AN16: Rental Deposit (lease) | AO16: 15000 | AP16: 15000 | AQ16: 15000 | AR16: 15000 | AS16: 15000 | AT16: 15000 | AU16: 15000 | AV16: 15000 | AW16: 15000 | AX16: 15000
F17: Software Systems | G17: =500*12 -> 6000 | I17: Australia | J17: 0.04 | K17: 0.04 | L17: 0.04 | M17: 0.04 | N17: 0.04 | O17: 0.04 | P17: 0.04 | Q17: 0.04 | R17: 0.04 | S17: 0.04 | U17: Australia | V17: 0.14 | X17: Australia | Y17: 0.33 | Z17: (avg) | AB17: Telephone/ Internet | AC17: 1200 | AD17: 0 | AE17: 0 | AF17: 0 | AG17: 0 | AH17: 0 | AI17: 0 | AJ17: 0 | AK17: 0 | AL17: 0 | AN17: Utilities Deposit | AO17: 1000 | AP17: 1000 | AQ17: 1000 | AR17: 1000 | AS17: 1000 | AT17: 1000 | AU17: 1000 | AV17: 1000 | AW17: 1000 | AX17: 1000
C18: Startup Costs | F18: Salaries & Benefits cost - Staff | G18: =G28*G29*G30 -> 31200 | I18: Canada | J18: 0.032 | K18: 0.032 | L18: 0.032 | M18: 0.032 | N18: 0.032 | O18: 0.032 | P18: 0.032 | Q18: 0.032 | R18: 0.032 | S18: 0.032 | U18: Canada | V18: 0.12 | X18: Canada | Y18: 0.26 | Z18: (avg) | AB18: Courier/ postage per unit | AC18: 12 | AD18: 100 | AE18: 100 | AF18: 85 | AG18: 100 | AH18: 110 | AI18: 110 | AJ18: 75 | AK18: 45 | AL18: 45 | AN18: Marketing & Advertising (Launch) | AO18: 5000 | AP18: 5000 | AQ18: 5000 | AR18: 5000 | AS18: 5000 | AT18: 5000 | AU18: 5000 | AV18: 5000 | AW18: 5000 | AX18: 5000
C19: Equipment | D19: 120000 | F19: Salaries & Benefits cost - Engineers | G19: 120000 | I19: Europe | J19: 0.0315 | K19: 0.0315 | L19: 0.0315 | M19: 0.0315 | N19: 0.0315 | O19: 0.0315 | P19: 0.0315 | Q19: 0.0315 | R19: 0.0315 | S19: 0.0315 | U19: Europe | V19: 0.13 | X19: Europe | Y19: 0.19 | AB19: Marketing & Advertising (%) | AC19: 0.22 | AD19: 0.22 | AE19: 0.22 | AF19: 0.22 | AG19: 0.22 | AH19: 0.22 | AI19: 0.22 | AJ19: 0.22 | AK19: 0.22 | AL19: 0.22 | AN19: Legal | AO19: 1000 | AP19: 1000 | AQ19: 1000 | AR19: 1000 | AS19: 1000 | AT19: 1000 | AU19: 1000 | AV19: 1000 | AW19: 1000 | AX19: 1000
C20: Factory Fit-out | D20: 75000 | F20: Security | G20: =100*12 -> 1200 | I20: South America | J20: 0.1 | K20: 0.1 | L20: 0.1 | M20: 0.1 | N20: 0.1 | O20: 0.1 | P20: 0.1 | Q20: 0.1 | R20: 0.1 | S20: 0.1 | U20: South America | V20: 0.11 | X20: South America | Y20: 0.2838 | AB20: Insurance | AC20: 6000 | AD20: 0 | AE20: 0 | AF20: 0 | AG20: 0 | AH20: 0 | AI20: 0 | AJ20: 0 | AK20: 0 | AL20: 0 | AN20: Training | AO20: 3000 | AP20: 3000 | AQ20: 3000 | AR20: 3000 | AS20: 3000 | AT20: 3000 | AU20: 3000 | AV20: 3000 | AW20: 3000 | AX20: 3000
C21: Security Equipment | D21: 5000 | F21: Subscriptions/ Memberships | G21: 1000 | I21: Middle East | J21: 0.023 | K21: 0.023 | L21: 0.023 | M21: 0.023 | N21: 0.023 | O21: 0.023 | P21: 0.023 | Q21: 0.023 | R21: 0.023 | S21: 0.023 | U21: Middle East | V21: 0.13 | X21: Middle East | Y21: 0.15 | AB21: IT Support | AC21: 1000 | AD21: 1000 | AE21: 1000 | AF21: 1000 | AG21: 1000 | AH21: 1000 | AI21: 1000 | AJ21: 1000 | AK21: 1000 | AL21: 1000 | AN21: Miscellaneous / Contingency | AO21: 5000 | AP21: 5000 | AQ21: 5000 | AR21: 5000 | AS21: 5000 | AT21: 5000 | AU21: 5000 | AV21: 5000 | AW21: 5000 | AX21: 5000
C22: IT Installation | D22: 5000 | F22: Miscellaneous / Contingency | G22: 5000 | I22: Far East | J22: 0.021 | K22: 0.021 | L22: 0.021 | M22: 0.021 | N22: 0.021 | O22: 0.021 | P22: 0.021 | Q22: 0.021 | R22: 0.021 | S22: 0.021 | U22: Far East | V22: 0.15 | X22: Far East | Y22: 0.23 | AB22: Legal/ Accountancy | AC22: 1000 | AD22: 1000 | AE22: 1000 | AF22: 1000 | AG22: 1000 | AH22: 1000 | AI22: 1000 | AJ22: 1000 | AK22: 1000 | AL22: 1000 | AN22: Repair/ Maintenance | AO22: 5000 | AP22: 5000 | AQ22: 5000 | AR22: 5000 | AS22: 5000 | AT22: 5000 | AU22: 5000 | AV22: 5000 | AW22: 5000 | AX22: 5000
C23: Software | D23: 5000 | I23: Africa | J23: 0.05 | K23: 0.05 | L23: 0.05 | M23: 0.05 | N23: 0.05 | O23: 0.05 | P23: 0.05 | Q23: 0.05 | R23: 0.05 | S23: 0.05 | U23: Africa | V23: 0.1 | X23: Africa | Y23: 0.27 | AB23: Software Systems (base) | AC23: 600 | AD23: 600 | AE23: 6000 | AF23: 6000 | AG23: 6000 | AH23: 6000 | AI23: 6000 | AJ23: 6000 | AK23: 6000 | AL23: 6000 | AN23: Licenses / Permits | AO23: 500 | AP23: 500 | AQ23: 500 | AR23: 500 | AS23: 500 | AT23: 500 | AU23: 500 | AV23: 500 | AW23: 500 | AX23: 500
F24: Costs Occuring Once a Year | I24: Mexico | J24: 0.045 | K24: 0.045 | L24: 0.045 | M24: 0.045 | N24: 0.045 | O24: 0.045 | P24: 0.045 | Q24: 0.045 | R24: 0.045 | S24: 0.045 | U24: Mexico | V24: 0.17 | X24: Mexico | Y24: 0.3 | AB24: Cost per extra user | AC24: 5 | AD24: 5 | AE24: 5 | AF24: 5 | AG24: 5 | AH24: 5 | AI24: 5 | AJ24: 5 | AK24: 5 | AL24: 5
C25: Achitect/Designer Fees | D25: 5000 | F25: Repair/ Maintenance | G25: 5000 | AB25: Salaries & Benefits cost - Staff | AC25: 31200 | AD25: 0 | AE25: 0 | AF25: 0 | AG25: 0 | AH25: 0 | AI25: 0 | AJ25: 0 | AK25: 0 | AL25: 0
C26: Rental Deposit (Lease) | D26: =G9/12*3 -> 15000 | F26: Licenses / Permits | G26: 500 | AB26: Salaries & Benefits cost - Engineers | AC26: 120000 | AD26: 0 | AE26: 0 | AF26: 0 | AG26: 0 | AH26: 0 | AI26: 0 | AJ26: 0 | AK26: 0 | AL26: 0
C27: Utilities Deposit | D27: 1000 | F27: Days inventory outstanding | G27: 75 | AB27: Security | AC27: 1200 | AD27: 1200 | AE27: 1200 | AF27: 1200 | AG27: 1200 | AH27: 1200 | AI27: 1200 | AJ27: 1200 | AK27: 1200 | AL27: 1200
C28: Marketing & Advertising (Launch) | D28: 5000 | F28: Staff compensation per hour | G28: 15 | AB28: Subscriptions/ Memberships | AC28: 1000 | AD28: 1000 | AE28: 1000 | AF28: 1000 | AG28: 1000 | AH28: 1000 | AI28: 1000 | AJ28: 1000 | AK28: 1000 | AL28: 1000
C29: Legal | D29: 1000 | F29: Hours worked per week (per FTE) | G29: 40 | AB29: Miscellaneous / Contingency | AC29: 5000 | AD29: 5000 | AE29: 5000 | AF29: 5000 | AG29: 5000 | AH29: 5000 | AI29: 5000 | AJ29: 5000 | AK29: 5000 | AL29: 5000
C30: Training | D30: 3000 | F30: # of weeks in a year | G30: 52
C31: Miscellaneous / Contingency | D31: 5000 | F31: Days sales outstanding | G31: 50
C32: Exchange rate (Dollar to Rupee) | D32: 95.42 | F32: Days payable outstanding | G32: 55
C33: Product Type | D33: % Patients opting | E33: Cash Fee | F33: Insurance Fee | G33: % Cash | H33: % Insurance | I33: Fee per test
C34: Eye Test | D34: 1 | E34: 120 | F34: =2/3*E34 -> 80 | G34: 0.8 | H34: =1-G34 -> 0.2 | I34: =SUMPRODUCT(E34:F34,G34:H34) -> 112
C35: Diabetes | D35: 0.2 | E35: 200 | F35: =2/3*E35 -> 133.33333 | G35: 0.8 | H35: =1-G35 -> 0.2 | I35: =SUMPRODUCT(E35:F35,G35:H35) -> 186.66667
C36: Hypertension | D36: 0.2 | E36: 200 | F36: =2/3*E36 -> 133.33333 | G36: 0.8 | H36: =1-G36 -> 0.2 | I36: =SUMPRODUCT(E36:F36,G36:H36) -> 186.66667
C37: Glaucoma | D37: 0.1 | E37: 300 | F37: =2/3*E37 -> 200 | G37: 0.8 | H37: =1-G37 -> 0.2 | I37: =SUMPRODUCT(E37:F37,G37:H37) -> 280
C38: Dry Eye | D38: 0.3 | E38: 120 | F38: =2/3*E38 -> 80 | G38: 0.8 | H38: =1-G38 -> 0.2 | I38: =SUMPRODUCT(E38:F38,G38:H38) -> 112
C39: Macular Degeneration | D39: 0.05 | E39: 300 | F39: =2/3*E39 -> 200 | G39: 0.8 | H39: =1-G39 -> 0.2 | I39: =SUMPRODUCT(E39:F39,G39:H39) -> 280
F43: Selling year
C44: Product | D44: Units per Year (Yr1) | E44: Annual Growth rate | F44: India | G44: USA | H44: Europe | I44: Australia | J44: Canada | K44: South America | L44: Mexico | M44: Africa | N44: Middle East | O44: Far East | P44: Selling Price | Q44: COGS | R44: Discounts | S44: Inventory
C45: Far Edge (Drone) | D45: =1540 -> 1540 | E45: 0.15 | F45: 1 | G45: 4 | H45: 4 | I45: 4 | J45: 4 | K45: 4 | L45: 4 | M45: 4 | N45: 4 | O45: 4 | P45: 5000 | Q45: 0.35 | R45: 0 | S45: =T45 -> 269500 | T45: =Q45*P45*D45/10 -> 269500 | W45: =SUM(S45:S49) -> 933600
C46: Far edge (Rover) | D46: 1000 | E46: 0.15 | F46: 1 | G46: 4 | H46: 4 | I46: 4 | J46: 4 | K46: 4 | L46: 4 | M46: 4 | N46: 4 | O46: 4 | P46: 7000 | Q46: 0.35 | R46: 0 | S46: =T46 -> 245000 | T46: =Q46*P46*D46/10 -> 245000
C47: Edge | D47: 1270 | E47: 0.15 | F47: 1 | G47: 4 | H47: 4 | I47: 4 | J47: 4 | K47: 4 | L47: 4 | M47: 4 | N47: 4 | O47: 4 | P47: 4000 | Q47: 0.35 | R47: 0 | S47: =T47 -> 177800 | T47: =Q47*P47*D47/10 -> 177800
C48: FOG | D48: 635 | E48: 0.1 | F48: 2 | G48: 5 | H48: 5 | I48: 5 | J48: 5 | K48: 5 | L48: 5 | M48: 5 | N48: 5 | O48: 5 | P48: 9500 | Q48: 0.4 | R48: 0 | S48: =T48 -> 241300 | T48: =Q48*P48*D48/10 -> 241300
C49: Enterprise | D49: 318 | E49: 0.1 | F49: 3 | G49: 6 | H49: 6 | I49: 6 | J49: 6 | K49: 6 | L49: 6 | M49: 6 | N49: 6 | O49: 6 | P49: 10000 | Q49: 0.4 | R49: 0 | S49: =0 -> 0
C50: Software Stacks (one time) | D50: 1900 | E50: 0.1 | F50: 1 | G50: 4 | H50: 4 | I50: 4 | J50: 4 | K50: 4 | L50: 4 | M50: 4 | N50: 4 | O50: 4 | P50: 1900 | Q50: 0.35 | R50: 0 | S50: =T49 -> 0
C51: Software Stacks (subscription)(new customers/year) | D51: 400 | E51: 0.1 | F51: 2 | G51: 5 | H51: 5 | I51: 5 | J51: 5 | K51: 5 | L51: 5 | M51: 5 | N51: 5 | O51: 5 | P51: 500 | Q51: 0.35 | R51: 0 | S51: =T50 -> 0
C52: System Integration | D52: 300 | E52: 0.1 | F52: 2 | G52: 5 | H52: 5 | I52: 5 | J52: 5 | K52: 5 | L52: 5 | M52: 5 | N52: 5 | O52: 5 | P52: 500 | Q52: 0.35 | R52: 0 | S52: =T51 -> 0
C53: Licensing | D53: 1500 | E53: 0.1 | F53: 2 | G53: 5 | H53: 5 | I53: 5 | J53: 5 | K53: 5 | L53: 5 | M53: 5 | N53: 5 | O53: 5 | P53: 300 | Q53: 0.35 | R53: 0 | S53: =T52 -> 0
C54: Maintenance | D54: 700 | E54: 0.1 | F54: 2 | G54: 5 | H54: 5 | I54: 5 | J54: 5 | K54: 5 | L54: 5 | M54: 5 | N54: 5 | O54: 5 | P54: 700 | Q54: 0.35 | R54: 0 | S54: =T53 -> 0

Sheet Revenue
C1: INDIA | D1: USA | E1: AUSTRALIA | F1: CANADA | G1: EUROPE | H1: SOUTH AMERICA | I1: MEXICO | J1: AFRICA | K1: MIDDLE EAST | L1: FAR EAST
B3: CPI | C3: =Assumptions!J15 -> 0.046 | D3: =Assumptions!K15 -> 0.046 | E3: =Assumptions!L15 -> 0.046 | F3: =Assumptions!M15 -> 0.046 | G3: =Assumptions!N15 -> 0.046 | H3: =Assumptions!O15 -> 0.046 | I3: =Assumptions!P15 -> 0.046 | J3: =Assumptions!Q15 -> 0.046 | ... L3: =Assumptions!S15 -> 0.046 | AB3: CPI | AC3: =Assumptions!J17 -> 0.04 | AD3: =Assumptions!K17 -> 0.04 | AE3: =Assumptions!L17 -> 0.04 | AF3: =Assumptions!M17 -> 0.04 | AG3: =Assumptions!N17 -> 0.04 | AH3: =Assumptions!O17 -> 0.04 | AI3: =Assumptions!P17 -> 0.04 | AJ3: =Assumptions!Q17 -> 0.04 | ... AL3: =Assumptions!S17 -> 0.04
C6: Year | Q6: Year | AC6: Year | AQ6: Year
B7: SELLING PRICE | C7: 1 | D7: 2 | E7: 3 | F7: 4 | G7: 5 | H7: 6 | I7: 7 | J7: 8 | K7: 9 | L7: 10 | P7: UNITS SOLD | Q7: 1 | R7: 2 | S7: 3 | T7: 4 | U7: 5 | V7: 6 | W7: 7 | X7: 8 | Y7: 9 | Z7: 10 | AB7: SELLING PRICE | AC7: 1 | AD7: 2 | AE7: 3 | AF7: 4 | AG7: 5 | AH7: 6 | AI7: 7 | AJ7: 8 | AK7: 9 | AL7: 10 | AP7: UNITS SOLD | AQ7: 1 | AR7: 2 | AS7: 3 | AT7: 4 | AU7: 5 | AV7: 6 | AW7: 7 | AX7: 8 | AY7: 9 | AZ7: 10
B8: Drone | C8: =IF(C7=Assumptions!$F$45, Assumptions!$P$45, 0) -> 5000 | D8: =IF(D7>Assumptions!$F$45, C8*(1+C3), IF(D7=Assumptions!$F$45, Assumptions!$P$45, 0)) -> 5230 | E8: =IF(E7>Assumptions!$F$45, D8*(1+D3), IF(E7=Assumptions!$F$45, Assumptions!$P$45, 0)) -> 5470.58 | F8: =IF(F7>Assumptions!$F$45, E8*(1+E3), IF(F7=Assumptions!$F$45, Assumptions!$P$45, 0)) -> 5722.2267 | G8: =IF(G7>Assumptions!$F$45, F8*(1+F3), IF(G7=Assumptions!$F$45, Assumptions!$P$45, 0)) -> 5985.4491 | H8: =IF(H7>Assumptions!$F$45, G8*(1+G3), IF(H7=Assumptions!$F$45, Assumptions!$P$45, 0)) -> 6260.7798 | I8: =IF(I7>Assumptions!$F$45, H8*(1+H3), IF(I7=Assumptions!$F$45, Assumptions!$P$45, 0)) -> 6548.7756 | J8: =IF(J7>Assumptions!$F$45, I8*(1+I3), IF(J7=Assumptions!$F$45, Assumptions!$P$45, 0)) -> 6850.0193 | K8: =IF(K7>Assumptions!$F$45, J8*(1+J3), IF(K7=Assumptions!$F$45, Assumptions!$P$45, 0)) -> 7165.1202 | L8: =IF(L7>Assumptions!$F$45, K8*(1+K3), IF(L7=Assumptions!$F$45, Assumptions!$P$45, 0)) -> 7494.7157 | P8: Drone | Q8: =IF(Q7=Assumptions!$F$45, Assumptions!$D$45, 0) -> 1540 | R8: =IF(R7>Assumptions!$F$45, Q8*(1+C22), IF(R7=Assumptions!$F$45, Assumptions!$D$45, 0)) -> 1617 | S8: =IF(S7>Assumptions!$F$45, R8*(1+D22), IF(S7=Assumptions!$F$45, Assumptions!$D$45, 0)) -> 1702.0654 | T8: =IF(T7>Assumptions!$F$45, S8*(1+E22), IF(T7=Assumptions!$F$45, Assumptions!$D$45, 0)) -> 1797.0459 | U8: =IF(U7>Assumptions!$F$45, T8*(1+F22), IF(U7=Assumptions!$F$45, Assumptions!$D$45, 0)) -> 1902.2922 | V8: =IF(V7>Assumptions!$F$45, U8*(1+G22), IF(V7=Assumptions!$F$45, Assumptions!$D$45, 0)) -> 2018.623 | W8: =IF(W7>Assumptions!$F$45, V8*(1+H22), IF(W7=Assumptions!$F$45, Assumptions!$D$45, 0)) -> 2150.0655 | X8: =IF(X7>Assumptions!$F$45, W8*(1+I22), IF(X7=Assumptions!$F$45, Assumptions!$D$45, 0)) -> 2297.7602 | Y8: =IF(Y7>Assumptions!$F$45, X8*(1+J22), IF(Y7=Assumptions!$F$45, Assumptions!$D$45, 0)) -> 2464.5299 | Z8: =IF(Z7>Assumptions!$F$45, Y8*(1+K22), IF(Z7=Assumptions!$F$45, Assumptions!$D$45, 0)) -> 2653.2324 | AB8: Drone | AC8: =IF(AC$67=Assumptions!$I$45, Assumptions!$P$45, 0) -> 0 | AD8: =IF(AD7>Assumptions!$I$45, AC8*(1+AC3), IF(AD7=Assumptions!$I$45, Assumptions!$P$45, 0)) -> 0 | AE8: =IF(AE7>Assumptions!$I$45, AD8*(1+AD3), IF(AE7=Assumptions!$I$45, Assumptions!$P$45, 0)) -> 0 | AF8: =IF(AF7>Assumptions!$I$45, AE8*(1+AE3), IF(AF7=Assumptions!$I$45, Assumptions!$P$45, 0)) -> 5000 | AG8: =IF(AG7>Assumptions!$I$45, AF8*(1+AF3), IF(AG7=Assumptions!$I$45, Assumptions!$P$45, 0)) -> 5200 | AH8: =IF(AH7>Assumptions!$I$45, AG8*(1+AG3), IF(AH7=Assumptions!$I$45, Assumptions!$P$45, 0)) -> 5408 | AI8: =IF(AI7>Assumptions!$I$45, AH8*(1+AH3), IF(AI7=Assumptions!$I$45, Assumptions!$P$45, 0)) -> 5624.32 | AJ8: =IF(AJ7>Assumptions!$I$45, AI8*(1+AI3), IF(AJ7=Assumptions!$I$45, Assumptions!$P$45, 0)) -> 5849.2928 | AK8: =IF(AK7>Assumptions!$I$45, AJ8*(1+AJ3), IF(AK7=Assumptions!$I$45, Assumptions!$P$45, 0)) -> 6083.2645 | AL8: =IF(AL7>Assumptions!$I$45, AK8*(1+AK3), IF(AL7=Assumptions!$I$45, Assumptions!$P$45, 0)) -> 6326.5951 | AP8: Drone | AQ8: =IF(AQ7=Assumptions!$I$45, Assumptions!$D$45, 0) -> 0 | AR8: =IF(AR7>Assumptions!$I$45, AQ8*(1+AC22), IF(AR7=Assumptions!$I$45, Assumptions!$D$45, 0)) -> 0 | AS8: =IF(AS7>Assumptions!$I$45, AR8*(1+AD22), IF(AS7=Assumptions!$I$45, Assumptions!$D$45, 0)) -> 0 | AT8: =IF(AT7>Assumptions!$I$45, AS8*(1+AE22), IF(AT7=Assumptions!$I$45, Assumptions!$D$45, 0)) -> 1540 | AU8: =IF(AU7>Assumptions!$I$45, AT8*(1+AF22), IF(AU7=Assumptions!$I$45, Assumptions!$D$45, 0)) -> 1586.513 | AV8: =IF(AV7>Assumptions!$I$45, AU8*(1+AG22), IF(AV7=Assumptions!$I$45, Assumptions!$D$45, 0)) -> 1638.5199 | AW8: =IF(AW7>Assumptions!$I$45, AV8*(1+AH22), IF(AW7=Assumptions!$I$45, Assumptions!$D$45, 0)) -> 1697.5539 | AX8: =IF(AX7>Assumptions!$I$45, AW8*(1+AI22), IF(AX7=Assumptions!$I$45, Assumptions!$D$45, 0)) -> 1763.2846 | AY8: =IF(AY7>Assumptions!$I$45, AX8*(1+AJ22), IF(AY7=Assumptions!$I$45, Assumptions!$D$45, 0)) -> 1838.5712 | AZ8: =IF(AZ7>Assumptions!$I$45, AY8*(1+AK22), IF(AZ7=Assumptions!$I$45, Assumptions!$D$45, 0)) -> 1921.6894
B9: Rover | C9: =IF(C7=Assumptions!$F$46, Assumptions!$P$46, 0) -> 7000 | D9: =IF(D7>Assumptions!$F$46, C9*(1+C3), IF(D7=Assumptions!$F$46, Assumptions!$P$46, 0)) -> 7322 | E9: =IF(E7>Assumptions!$F$46, D9*(1+D3), IF(E7=Assumptions!$F$46, Assumptions!$P$46, 0)) -> 7658.812 | F9: =IF(F7>Assumptions!$F$46, E9*(1+E3), IF(F7=Assumptions!$F$46, Assumptions!$P$46, 0)) -> 8011.1174 | G9: =IF(G7>Assumptions!$F$46, F9*(1+F3), IF(G7=Assumptions!$F$46, Assumptions!$P$46, 0)) -> 8379.6288 | H9: =IF(H7>Assumptions!$F$46, G9*(1+G3), IF(H7=Assumptions!$F$46, Assumptions!$P$46, 0)) -> 8765.0917 | I9: =IF(I7>Assumptions!$F$46, H9*(1+H3), IF(I7=Assumptions!$F$46, Assumptions!$P$46, 0)) -> 9168.2859 | J9: =IF(J7>Assumptions!$F$46, I9*(1+I3), IF(J7=Assumptions!$F$46, Assumptions!$P$46, 0)) -> 9590.027 | K9: =IF(K7>Assumptions!$F$46, J9*(1+J3), IF(K7=Assumptions!$F$46, Assumptions!$P$46, 0)) -> 10031.168 | L9: =IF(L7>Assumptions!$F$46, K9*(1+K3), IF(L7=Assumptions!$F$46, Assumptions!$P$46, 0)) -> 10492.602 | P9: Rover | Q9: =IF(Q7=Assumptions!$F$46, Assumptions!$D$46, 0) -> 1000 | R9: =IF(R7>Assumptions!$F$46, Q9*(1+C23), IF(R7=Assumptions!$F$46, Assumptions!$D$46, 0)) -> 1090 | S9: =IF(S7>Assumptions!$F$46, R9*(1+D23), IF(S7=Assumptions!$F$46, Assumptions!$D$46, 0)) -> 1191.1311 | T9: =IF(T7>Assumptions!$F$46, S9*(1+E23), IF(T7=Assumptions!$F$46, Assumptions!$D$46, 0)) -> 1305.699 | U9: =IF(U7>Assumptions!$F$46, T9*(1+F23), IF(U7=Assumptions!$F$46, Assumptions!$D$46, 0)) -> 1434.6548 | V9: =IF(V7>Assumptions!$F$46, U9*(1+G23), IF(V7=Assumptions!$F$46, Assumptions!$D$46, 0)) -> 1581.3162 | W9: =IF(W7>Assumptions!$F$46, V9*(1+H23), IF(W7=Assumptions!$F$46, Assumptions!$D$46, 0)) -> 1749.1918 | X9: =IF(X7>Assumptions!$F$46, W9*(1+I23), IF(X7=Assumptions!$F$46, Assumptions!$D$46, 0)) -> 1941.7914 | Y9: =IF(Y7>Assumptions!$F$46, X9*(1+J23), IF(Y7=Assumptions!$F$46, Assumptions!$D$46, 0)) -> 2161.3431 | Z9: =IF(Z7>Assumptions!$F$46, Y9*(1+K23), IF(Z7=Assumptions!$F$46, Assumptions!$D$46, 0)) -> 2414.0286 | AB9: Rover | AC9: =IF(AC$67=Assumptions!$I$46, Assumptions!$P$46, 0) -> 0 | AD9: =IF(AD7>Assumptions!$I$46, AC9*(1+AC3), IF(AD7=Assumptions!$I$46, Assumptions!$P$46, 0)) -> 0 | AE9: =IF(AE7>Assumptions!$I$46, AD9*(1+AD3), IF(AE7=Assumptions!$I$46, Assumptions!$P$46, 0)) -> 0 | AF9: =IF(AF7>Assumptions!$I$46, AE9*(1+AE3), IF(AF7=Assumptions!$I$46, Assumptions!$P$46, 0)) -> 7000 | AG9: =IF(AG7>Assumptions!$I$46, AF9*(1+AF3), IF(AG7=Assumptions!$I$46, Assumptions!$P$46, 0)) -> 7280 | AH9: =IF(AH7>Assumptions!$I$46, AG9*(1+AG3), IF(AH7=Assumptions!$I$46, Assumptions!$P$46, 0)) -> 7571.2 | AI9: =IF(AI7>Assumptions!$I$46, AH9*(1+AH3), IF(AI7=Assumptions!$I$46, Assumptions!$P$46, 0)) -> 7874.048 | AJ9: =IF(AJ7>Assumptions!$I$46, AI9*(1+AI3), IF(AJ7=Assumptions!$I$46, Assumptions!$P$46, 0)) -> 8189.0099 | AK9: =IF(AK7>Assumptions!$I$46, AJ9*(1+AJ3), IF(AK7=Assumptions!$I$46, Assumptions!$P$46, 0)) -> 8516.5703 | AL9: =IF(AL7>Assumptions!$I$46, AK9*(1+AK3), IF(AL7=Assumptions!$I$46, Assumptions!$P$46, 0)) -> 8857.2331 | AP9: Rover | AQ9: =IF(AQ7=Assumptions!$I$45, Assumptions!$D$46, 0) -> 0 | AR9: =IF(AR7>Assumptions!$I$45, AQ9*(1+AC23), IF(AR7=Assumptions!$I$45, Assumptions!$D$46, 0)) -> 0 | AS9: =IF(AS7>Assumptions!$I$45, AR9*(1+AD23), IF(AS7=Assumptions!$I$45, Assumptions!$D$46, 0)) -> 0 | AT9: =IF(AT7>Assumptions!$I$45, AS9*(1+AE23), IF(AT7=Assumptions!$I$45, Assumptions!$D$46, 0)) -> 1000 | AU9: =IF(AU7>Assumptions!$I$45, AT9*(1+AF23), IF(AU7=Assumptions!$I$45, Assumptions!$D$46, 0)) -> 1059.8638 | AV9: =IF(AV7>Assumptions!$I$45, AU9*(1+AG23), IF(AV7=Assumptions!$I$45, Assumptions!$D$46, 0)) -> 1126.7767 | AW9: =IF(AW7>Assumptions!$I$45, AV9*(1+AH23), IF(AW7=Assumptions!$I$45, Assumptions!$D$46, 0)) -> 1201.2485 | AX9: =IF(AX7>Assumptions!$I$45, AW9*(1+AI23), IF(AX7=Assumptions!$I$45, Assumptions!$D$46, 0)) -> 1284.6965 | AY9: =IF(AY7>Assumptions!$I$45, AX9*(1+AJ23), IF(AY7=Assumptions!$I$45, Assumptions!$D$46, 0)) -> 1378.1671 | AZ9: =IF(AZ7>Assumptions!$I$45, AY9*(1+AK23), IF(AZ7=Assumptions!$I$45, Assumptions!$D$46, 0)) -> 1483.5935
B10: Edge | C10: =IF(C7=Assumptions!$F$47, Assumptions!$P$47, 0) -> 4000 | D10: =IF(D7>Assumptions!$F$47, C10*(1+C3), IF(D7=Assumptions!$F$47, Assumptions!$P$45, 0)) -> 4184 | E10: =IF(E7>Assumptions!$F$47, D10*(1+D3), IF(E7=Assumptions!$F$47, Assumptions!$P$45, 0)) -> 4376.464 | F10: =IF(F7>Assumptions!$F$47, E10*(1+E3), IF(F7=Assumptions!$F$47, Assumptions!$P$45, 0)) -> 4577.7813 | G10: =IF(G7>Assumptions!$F$47, F10*(1+F3), IF(G7=Assumptions!$F$47, Assumptions!$P$45, 0)) -> 4788.3593 | H10: =IF(H7>Assumptions!$F$47, G10*(1+G3), IF(H7=Assumptions!$F$47, Assumptions!$P$45, 0)) -> 5008.6238 | I10: =IF(I7>Assumptions!$F$47, H10*(1+H3), IF(I7=Assumptions!$F$47, Assumptions!$P$45, 0)) -> 5239.0205 | J10: =IF(J7>Assumptions!$F$47, I10*(1+I3), IF(J7=Assumptions!$F$47, Assumptions!$P$45, 0)) -> 5480.0155 | K10: =IF(K7>Assumptions!$F$47, J10*(1+J3), IF(K7=Assumptions!$F$47, Assumptions!$P$45, 0)) -> 5732.0962 | L10: =IF(L7>Assumptions!$F$47, K10*(1+K3), IF(L7=Assumptions!$F$47, Assumptions!$P$45, 0)) -> 5995.7726 | P10: Edge | Q10: =IF(Q7=Assumptions!$F$47, Assumptions!$D$47, 0) -> 1270 | R10: =IF(R7>Assumptions!$F$47, Q10*(1+C24), IF(R7=Assumptions!$F$47, Assumptions!$D$47, 0)) -> 1295.4 | S10: =IF(S7>Assumptions!$F$47, R10*(1+D24), IF(S7=Assumptions!$F$47, Assumptions!$D$47, 0)) -> 1324.8782 | T10: =IF(T7>Assumptions!$F$47, S10*(1+E24), IF(T7=Assumptions!$F$47, Assumptions!$D$47, 0)) -> 1359.2991 | U10: =IF(U7>Assumptions!$F$47, T10*(1+F24), IF(U7=Assumptions!$F$47, Assumptions!$D$47, 0)) -> 1398.8753 | V10: =IF(V7>Assumptions!$F$47, U10*(1+G24), IF(V7=Assumptions!$F$47, Assumptions!$D$47, 0)) -> 1445.0453 | W10: =IF(W7>Assumptions!$F$47, V10*(1+H24), IF(W7=Assumptions!$F$47, Assumptions!$D$47, 0)) -> 1498.1249 | X10: =IF(X7>Assumptions!$F$47, W10*(1+I24), IF(X7=Assumptions!$F$47, Assumptions!$D$47, 0)) -> 1559.078 | Y10: =IF(Y7>Assumptions!$F$47, X10*(1+J24), IF(Y7=Assumptions!$F$47, Assumptions!$D$47, 0)) -> 1627.7145 | Z10: =IF(Z7>Assumptions!$F$47, Y10*(1+K24), IF(Z7=Assumptions!$F$47, Assumptions!$D$47, 0)) -> 1705.796 | AB10: Edge | AC10: =IF(AC$67=Assumptions!$I$47, Assumptions!$P$47, 0) -> 0 | AD10: =IF(AD7>Assumptions!$I$47, AC10*(1+AC3), IF(AD7=Assumptions!$I$47, Assumptions!$P$47, 0)) -> 0 | AE10: =IF(AE7>Assumptions!$I$47, AD10*(1+AD3), IF(AE7=Assumptions!$I$47, Assumptions!$P$47, 0)) -> 0 | AF10: =IF(AF7>Assumptions!$I$47, AE10*(1+AE3), IF(AF7=Assumptions!$I$47, Assumptions!$P$47, 0)) -> 4000 | AG10: =IF(AG7>Assumptions!$I$47, AF10*(1+AF3), IF(AG7=Assumptions!$I$47, Assumptions!$P$47, 0)) -> 4160 | AH10: =IF(AH7>Assumptions!$I$47, AG10*(1+AG3), IF(AH7=Assumptions!$I$47, Assumptions!$P$47, 0)) -> 4326.4 | AI10: =IF(AI7>Assumptions!$I$47, AH10*(1+AH3), IF(AI7=Assumptions!$I$47, Assumptions!$P$47, 0)) -> 4499.456 | AJ10: =IF(AJ7>Assumptions!$I$47, AI10*(1+AI3), IF(AJ7=Assumptions!$I$47, Assumptions!$P$47, 0)) -> 4679.4342 | AK10: =IF(AK7>Assumptions!$I$47, AJ10*(1+AJ3), IF(AK7=Assumptions!$I$47, Assumptions!$P$47, 0)) -> 4866.6116 | AL10: =IF(AL7>Assumptions!$I$47, AK10*(1+AK3), IF(AL7=Assumptions!$I$47, Assumptions!$P$47, 0)) -> 5061.2761 | AP10: Edge | AQ10: =IF(AQ7=Assumptions!$I$47, Assumptions!$D$47, 0) -> 0 | AR10: =IF(AR7>Assumptions!$I$47, AQ10*(1+AC24), IF(AR7=Assumptions!$I$47, Assumptions!$D$47, 0)) -> 0 | AS10: =IF(AS7>Assumptions!$I$47, AR10*(1+AD24), IF(AS7=Assumptions!$I$47, Assumptions!$D$47, 0)) -> 0 | AT10: =IF(AT7>Assumptions!$I$47, AS10*(1+AE24), IF(AT7=Assumptions!$I$47, Assumptions!$D$47, 0)) -> 1270 | AU10: =IF(AU7>Assumptions!$I$47, AT10*(1+AF24), IF(AU7=Assumptions!$I$47, Assumptions!$D$47, 0)) -> 1320.9413 | AV10: =IF(AV7>Assumptions!$I$47, AU10*(1+AG24), IF(AV7=Assumptions!$I$47, Assumptions!$D$47, 0)) -> 1378.6799 | AW10: =IF(AW7>Assumptions!$I$47, AV10*(1+AH24), IF(AW7=Assumptions!$I$47, Assumptions!$D$47, 0)) -> 1444.3893 | AX10: =IF(AX7>Assumptions!$I$47, AW10*(1+AI24), IF(AX7=Assumptions!$I$47, Assumptions!$D$47, 0)) -> 1518.9926 | AY10: =IF(AY7>Assumptions!$I$47, AX10*(1+AJ24), IF(AY7=Assumptions!$I$47, Assumptions!$D$47, 0)) -> 1602.5893 | AZ10: =IF(AZ7>Assumptions!$I$47, AY10*(1+AK24), IF(AZ7=Assumptions!$I$47, Assumptions!$D$47, 0)) -> 1696.1658
B11: Fog | C11: =IF(C7=Assumptions!$F$48, Assumptions!$P$48, 0) -> 0 | D11: =IF(D7>Assumptions!$F$48, C11*(1+C3), IF(D7=Assumptions!$F$48, Assumptions!$P$48, 0)) -> 9500 | E11: =IF(E7>Assumptions!$F$48, D11*(1+D3), IF(E7=Assumptions!$F$48, Assumptions!$P$48, 0)) -> 9937 | F11: =IF(F7>Assumptions!$F$48, E11*(1+E3), IF(F7=Assumptions!$F$48, Assumptions!$P$48, 0)) -> 10394.102 | G11: =IF(G7>Assumptions!$F$48, F11*(1+F3), IF(G7=Assumptions!$F$48, Assumptions!$P$48, 0)) -> 10872.231 | H11: =IF(H7>Assumptions!$F$48, G11*(1+G3), IF(H7=Assumptions!$F$48, Assumptions!$P$48, 0)) -> 11372.353 | I11: =IF(I7>Assumptions!$F$48, H11*(1+H3), IF(I7=Assumptions!$F$48, Assumptions!$P$48, 0)) -> 11895.482 | J11: =IF(J7>Assumptions!$F$48, I11*(1+I3), IF(J7=Assumptions!$F$48, Assumptions!$P$48, 0)) -> 12442.674 | K11: =IF(K7>Assumptions!$F$48, J11*(1+J3), IF(K7=Assumptions!$F$48, Assumptions!$P$48, 0)) -> 13015.037 | L11: =IF(L7>Assumptions!$F$48, K11*(1+K3), IF(L7=Assumptions!$F$48, Assumptions!$P$48, 0)) -> 13613.728 | P11: Fog | Q11: =IF(Q7=Assumptions!$F$48, Assumptions!$D$48, 0) -> 0 | R11: =IF(R7>Assumptions!$F$48, Q11*(1+C25), IF(R7=Assumptions!$F$48, Assumptions!$D$48, 0)) -> 635 | S11: =IF(S7>Assumptions!$F$48, R11*(1+D25), IF(S7=Assumptions!$F$48, Assumptions!$D$48, 0)) -> 661.97592 | T11: =IF(T7>Assumptions!$F$48, S11*(1+E25), IF(T7=Assumptions!$F$48, Assumptions!$D$48, 0)) -> 692.7 | U11: =IF(U7>Assumptions!$F$48, T11*(1+F25), IF(U7=Assumptions!$F$48, Assumptions!$D$48, 0)) -> 726.80095 | V11: =IF(V7>Assumptions!$F$48, U11*(1+G25), IF(V7=Assumptions!$F$48, Assumptions!$D$48, 0)) -> 764.38275 | W11: =IF(W7>Assumptions!$F$48, V11*(1+H25), IF(W7=Assumptions!$F$48, Assumptions!$D$48, 0)) -> 806.54934 | X11: =IF(X7>Assumptions!$F$48, W11*(1+I25), IF(X7=Assumptions!$F$48, Assumptions!$D$48, 0)) -> 853.65643 | Y11: =IF(Y7>Assumptions!$F$48, X11*(1+J25), IF(Y7=Assumptions!$F$48, Assumptions!$D$48, 0)) -> 906.17049 | Z11: =IF(Z7>Assumptions!$F$48, Y11*(1+K25), IF(Z7=Assumptions!$F$48, Assumptions!$D$48, 0)) -> 964.9294 | AB11: Fog | AC11: =IF(AC$67=Assumptions!$I$48, Assumptions!$P$48, 0) -> 0 | AD11: =IF(AD7>Assumptions!$I$48, AC11*(1+AC3), IF(AD7=Assumptions!$I$48, Assumptions!$P$48, 0)) -> 0 | AE11: =IF(AE7>Assumptions!$I$48, AD11*(1+AD3), IF(AE7=Assumptions!$I$48, Assumptions!$P$48, 0)) -> 0 | AF11: =IF(AF7>Assumptions!$I$48, AE11*(1+AE3), IF(AF7=Assumptions!$I$48, Assumptions!$P$48, 0)) -> 0 | AG11: =IF(AG7>Assumptions!$I$48, AF11*(1+AF3), IF(AG7=Assumptions!$I$48, Assumptions!$P$48, 0)) -> 9500 | AH11: =IF(AH7>Assumptions!$I$48, AG11*(1+AG3), IF(AH7=Assumptions!$I$48, Assumptions!$P$48, 0)) -> 9880 | AI11: =IF(AI7>Assumptions!$I$48, AH11*(1+AH3), IF(AI7=Assumptions!$I$48, Assumptions!$P$48, 0)) -> 10275.2 | AJ11: =IF(AJ7>Assumptions!$I$48, AI11*(1+AI3), IF(AJ7=Assumptions!$I$48, Assumptions!$P$48, 0)) -> 10686.208 | AK11: =IF(AK7>Assumptions!$I$48, AJ11*(1+AJ3), IF(AK7=Assumptions!$I$48, Assumptions!$P$48, 0)) -> 11113.656 | AL11: =IF(AL7>Assumptions!$I$48, AK11*(1+AK3), IF(AL7=Assumptions!$I$48, Assumptions!$P$48, 0)) -> 11558.203 | AP11: Fog | AQ11: =IF(AQ7=Assumptions!$I$48, Assumptions!$D$48, 0) -> 0 | AR11: =IF(AR7>Assumptions!$I$48, AQ11*(1+AC25), IF(AR7=Assumptions!$I$48, Assumptions!$D$48, 0)) -> 0 | AS11: =IF(AS7>Assumptions!$I$48, AR11*(1+AD25), IF(AS7=Assumptions!$I$48, Assumptions!$D$48, 0)) -> 0 | AT11: =IF(AT7>Assumptions!$I$48, AS11*(1+AE25), IF(AT7=Assumptions!$I$48, Assumptions!$D$48, 0)) -> 0 | AU11: =IF(AU7>Assumptions!$I$48, AT11*(1+AF25), IF(AU7=Assumptions!$I$48, Assumptions!$D$48, 0)) -> 635 | AV11: =IF(AV7>Assumptions!$I$48, AU11*(1+AG25), IF(AV7=Assumptions!$I$48, Assumptions!$D$48, 0)) -> 668.7262 | AW11: =IF(AW7>Assumptions!$I$48, AV11*(1+AH25), IF(AW7=Assumptions!$I$48, Assumptions!$D$48, 0)) -> 706.48755 | AX11: =IF(AX7>Assumptions!$I$48, AW11*(1+AI25), IF(AX7=Assumptions!$I$48, Assumptions!$D$48, 0)) -> 748.48108 | AY11: =IF(AY7>Assumptions!$I$48, AX11*(1+AJ25), IF(AY7=Assumptions!$I$48, Assumptions!$D$48, 0)) -> 795.49194 | AZ11: =IF(AZ7>Assumptions!$I$48, AY11*(1+AK25), IF(AZ7=Assumptions!$I$48, Assumptions!$D$48, 0)) -> 847.57291
B12: Enterprise | C12: =IF(C7=Assumptions!$F$49, Assumptions!$P$49, 0) -> 0 | D12: =IF(D7>Assumptions!$F$49, C12*(1+C3), IF(D7=Assumptions!$F$49, Assumptions!$P$49, 0)) -> 0 | E12: =IF(E7>Assumptions!$F$49, D12*(1+D3), IF(E7=Assumptions!$F$49, Assumptions!$P$49, 0)) -> 10000 | F12: =IF(F7>Assumptions!$F$49, E12*(1+E3), IF(F7=Assumptions!$F$49, Assumptions!$P$49, 0)) -> 10460 | G12: =IF(G7>Assumptions!$F$49, F12*(1+F3), IF(G7=Assumptions!$F$49, Assumptions!$P$49, 0)) -> 10941.16 | H12: =IF(H7>Assumptions!$F$49, G12*(1+G3), IF(H7=Assumptions!$F$49, Assumptions!$P$49, 0)) -> 11444.453 | I12: =IF(I7>Assumptions!$F$49, H12*(1+H3), IF(I7=Assumptions!$F$49, Assumptions!$P$49, 0)) -> 11970.898 | J12: =IF(J7>Assumptions!$F$49, I12*(1+I3), IF(J7=Assumptions!$F$49, Assumptions!$P$49, 0)) -> 12521.56 | K12: =IF(K7>Assumptions!$F$49, J12*(1+J3), IF(K7=Assumptions!$F$49, Assumptions!$P$49, 0)) -> 13097.551 | L12: =IF(L7>Assumptions!$F$49, K12*(1+K3), IF(L7=Assumptions!$F$49, Assumptions!$P$49, 0)) -> 13700.039 | P12: Enterprise | Q12: =IF(Q7=Assumptions!$F$49, Assumptions!$D$49, 0) -> 0 | R12: =IF(R7>Assumptions!$F$49, Q12*(1+C26), IF(R7=Assumptions!$F$49, Assumptions!$D$49, 0)) -> 0 | S12: =IF(S7>Assumptions!$F$49, R12*(1+D26), IF(S7=Assumptions!$F$49, Assumptions!$D$49, 0)) -> 318 | T12: =IF(T7>Assumptions!$F$49, S12*(1+E26), IF(T7=Assumptions!$F$49, Assumptions!$D$49, 0)) -> 332.93791 | U12: =IF(U7>Assumptions!$F$49, T12*(1+F26), IF(U7=Assumptions!$F$49, Assumptions!$D$49, 0)) -> 349.53121 | V12: =IF(V7>Assumptions!$F$49, U12*(1+G26), IF(V7=Assumptions!$F$49, Assumptions!$D$49, 0)) -> 367.85598 | W12: =IF(W7>Assumptions!$F$49, V12*(1+H26), IF(W7=Assumptions!$F$49, Assumptions!$D$49, 0)) -> 388.1685 | X12: =IF(X7>Assumptions!$F$49, W12*(1+I26), IF(X7=Assumptions!$F$49, Assumptions!$D$49, 0)) -> 411.015 | Y12: =IF(Y7>Assumptions!$F$49, X12*(1+J26), IF(Y7=Assumptions!$F$49, Assumptions!$D$49, 0)) -> 436.35246 | Z12: =IF(Z7>Assumptions!$F$49, Y12*(1+K26), IF(Z7=Assumptions!$F$49, Assumptions!$D$49, 0)) -> 464.93706 | AB12: Enterprise | AC12: =IF(AC$67=Assumptions!$I$49, Assumptions!$P$49, 0) -> 0 | AD12: =IF(AD7>Assumptions!$I$49, AC12*(1+AC3), IF(AD7=Assumptions!$I$49, Assumptions!$P$49, 0)) -> 0 | AE12: =IF(AE7>Assumptions!$I$49, AD12*(1+AD3), IF(AE7=Assumptions!$I$49, Assumptions!$P$49, 0)) -> 0 | AF12: =IF(AF7>Assumptions!$I$49, AE12*(1+AE3), IF(AF7=Assumptions!$I$49, Assumptions!$P$49, 0)) -> 0 | AG12: =IF(AG7>Assumptions!$I$49, AF12*(1+AF3), IF(AG7=Assumptions!$I$49, Assumptions!$P$49, 0)) -> 0 | AH12: =IF(AH7>Assumptions!$I$49, AG12*(1+AG3), IF(AH7=Assumptions!$I$49, Assumptions!$P$49, 0)) -> 10000 | AI12: =IF(AI7>Assumptions!$I$49, AH12*(1+AH3), IF(AI7=Assumptions!$I$49, Assumptions!$P$49, 0)) -> 10400 | AJ12: =IF(AJ7>Assumptions!$I$49, AI12*(1+AI3), IF(AJ7=Assumptions!$I$49, Assumptions!$P$49, 0)) -> 10816 | AK12: =IF(AK7>Assumptions!$I$49, AJ12*(1+AJ3), IF(AK7=Assumptions!$I$49, Assumptions!$P$49, 0)) -> 11248.64 | AL12: =IF(AL7>Assumptions!$I$49, AK12*(1+AK3), IF(AL7=Assumptions!$I$49, Assumptions!$P$49, 0)) -> 11698.586 | AP12: Enterprise | AQ12: =IF(AQ7=Assumptions!$I$49, Assumptions!$D$49, 0) -> 0 | AR12: =IF(AR7>Assumptions!$I$49, AQ12*(1+AC26), IF(AR7=Assumptions!$I$49, Assumptions!$D$49, 0)) -> 0 | AS12: =IF(AS7>Assumptions!$I$49, AR12*(1+AD26), IF(AS7=Assumptions!$I$49, Assumptions!$D$49, 0)) -> 0 | AT12: =IF(AT7>Assumptions!$I$49, AS12*(1+AE26), IF(AT7=Assumptions!$I$49, Assumptions!$D$49, 0)) -> 0 | AU12: =IF(AU7>Assumptions!$I$49, AT12*(1+AF26), IF(AU7=Assumptions!$I$49, Assumptions!$D$49, 0)) -> 0 | AV12: =IF(AV7>Assumptions!$I$49, AU12*(1+AG26), IF(AV7=Assumptions!$I$49, Assumptions!$D$49, 0)) -> 318 | AW12: =IF(AW7>Assumptions!$I$49, AV12*(1+AH26), IF(AW7=Assumptions!$I$49, Assumptions!$D$49, 0)) -> 345.54318 | AX12: =IF(AX7>Assumptions!$I$49, AW12*(1+AI26), IF(AX7=Assumptions!$I$49, Assumptions!$D$49, 0)) -> 376.84305 | AY12: =IF(AY7>Assumptions!$I$49, AX12*(1+AJ26), IF(AY7=Assumptions!$I$49, Assumptions!$D$49, 0)) -> 412.47139 | AZ12: =IF(AZ7>Assumptions!$I$49, AY12*(1+AK26), IF(AZ7=Assumptions!$I$49, Assumptions!$D$49, 0)) -> 452.94248
B13: software stacks (one time) | C13: =IF(C7=Assumptions!$F$50, Assumptions!$P$50, 0) -> 1900 | D13: =IF(D7>Assumptions!$F$50, C13*(1+C3), IF(D7=Assumptions!$F$50, Assumptions!$P$50, 0)) -> 1987.4 | E13: =IF(E7>Assumptions!$F$50, D13*(1+D3), IF(E7=Assumptions!$F$50, Assumptions!$P$50, 0)) -> 2078.8204 | F13: =IF(F7>Assumptions!$F$50, E13*(1+E3), IF(F7=Assumptions!$F$50, Assumptions!$P$50, 0)) -> 2174.4461 | G13: =IF(G7>Assumptions!$F$50, F13*(1+F3), IF(G7=Assumptions!$F$50, Assumptions!$P$50, 0)) -> 2274.4707 | H13: =IF(H7>Assumptions!$F$50, G13*(1+G3), IF(H7=Assumptions!$F$50, Assumptions!$P$50, 0)) -> 2379.0963 | I13: =IF(I7>Assumptions!$F$50, H13*(1+H3), IF(I7=Assumptions!$F$50, Assumptions!$P$50, 0)) -> 2488.5347 | J13: =IF(J7>Assumptions!$F$50, I13*(1+I3), IF(J7=Assumptions!$F$50, Assumptions!$P$50, 0)) -> 2603.0073 | K13: =IF(K7>Assumptions!$F$50, J13*(1+J3), IF(K7=Assumptions!$F$50, Assumptions!$P$50, 0)) -> 2722.7457 | L13: =IF(L7>Assumptions!$F$50, K13*(1+K3), IF(L7=Assumptions!$F$50, Assumptions!$P$50, 0)) -> 2847.992 | P13: software stacks (one time) | Q13: =IF(Q7=Assumptions!$F$50, Assumptions!$D$50, 0) -> 1900 | R13: =IF(R7>Assumptions!$F$50, Q13*(1+C27), IF(R7=Assumptions!$F$50, Assumptions!$D$50, 0)) -> 1900 | S13: =IF(S7>Assumptions!$F$50, R13*(1+D27), IF(S7=Assumptions!$F$50, Assumptions!$D$50, 0)) -> 1904.5977 | T13: =IF(T7>Assumptions!$F$50, S13*(1+E27), IF(T7=Assumptions!$F$50, Assumptions!$D$50, 0)) -> 1916.1631 | U13: =IF(U7>Assumptions!$F$50, T13*(1+F27), IF(U7=Assumptions!$F$50, Assumptions!$D$50, 0)) -> 1934.3377 | V13: =IF(V7>Assumptions!$F$50, U13*(1+G27), IF(V7=Assumptions!$F$50, Assumptions!$D$50, 0)) -> 1958.9943 | W13: =IF(W7>Assumptions!$F$50, V13*(1+H27), IF(W7=Assumptions!$F$50, Assumptions!$D$50, 0)) -> 1991.7705 | X13: =IF(X7>Assumptions!$F$50, W13*(1+I27), IF(X7=Assumptions!$F$50, Assumptions!$D$50, 0)) -> 2032.9209 | Y13: =IF(Y7>Assumptions!$F$50, X13*(1+J27), IF(Y7=Assumptions!$F$50, Assumptions!$D$50, 0)) -> 2079.9934 | Z13: =IF(Z7>Assumptions!$F$50, Y13*(1+K27), IF(Z7=Assumptions!$F$50, Assumptions!$D$50, 0)) -> 2135.577 | AB13: software stacks (one time) | AC13: =IF(AC$67=Assumptions!$I$50, Assumptions!$P$50, 0) -> 0 | AD13: =IF(AD7>Assumptions!$I$50, AC13*(1+AC3), IF(AD7=Assumptions!$I$50, Assumptions!$P$50, 0)) -> 0 | AE13: =IF(AE7>Assumptions!$I$50, AD13*(1+AD3), IF(AE7=Assumptions!$I$50, Assumptions!$P$50, 0)) -> 0 | AF13: =IF(AF7>Assumptions!$I$50, AE13*(1+AE3), IF(AF7=Assumptions!$I$50, Assumptions!$P$50, 0)) -> 1900 | AG13: =IF(AG7>Assumptions!$I$50, AF13*(1+AF3), IF(AG7=Assumptions!$I$50, Assumptions!$P$50, 0)) -> 1976 | AH13: =IF(AH7>Assumptions!$I$50, AG13*(1+AG3), IF(AH7=Assumptions!$I$50, Assumptions!$P$50, 0)) -> 2055.04 | AI13: =IF(AI7>Assumptions!$I$50, AH13*(1+AH3), IF(AI7=Assumptions!$I$50, Assumptions!$P$50, 0)) -> 2137.2416 | AJ13: =IF(AJ7>Assumptions!$I$50, AI13*(1+AI3), IF(AJ7=Assumptions!$I$50, Assumptions!$P$50, 0)) -> 2222.7313 | AK13: =IF(AK7>Assumptions!$I$50, AJ13*(1+AJ3), IF(AK7=Assumptions!$I$50, Assumptions!$P$50, 0)) -> 2311.6405 | AL13: =IF(AL7>Assumptions!$I$50, AK13*(1+AK3), IF(AL7=Assumptions!$I$50, Assumptions!$P$50, 0)) -> 2404.1061 | AP13: software stacks (one time) | AQ13: =IF(AQ7=Assumptions!$I$50, Assumptions!$D$50, 0) -> 0 | AR13: =IF(AR7>Assumptions!$I$50, AQ13*(1+AC27), IF(AR7=Assumptions!$I$50, Assumptions!$D$50, 0)) -> 0 | AS13: =IF(AS7>Assumptions!$I$50, AR13*(1+AD27), IF(AS7=Assumptions!$I$50, Assumptions!$D$50, 0)) -> 0 | AT13: =IF(AT7>Assumptions!$I$50, AS13*(1+AE27), IF(AT7=Assumptions!$I$50, Assumptions!$D$50, 0)) -> 1900 | AU13: =IF(AU7>Assumptions!$I$50, AT13*(1+AF27), IF(AU7=Assumptions!$I$50, Assumptions!$D$50, 0)) -> 1922.1616 | AV13: =IF(AV7>Assumptions!$I$50, AU13*(1+AG27), IF(AV7=Assumptions!$I$50, Assumptions!$D$50, 0)) -> 1949.3125 | AW13: =IF(AW7>Assumptions!$I$50, AV13*(1+AH27), IF(AW7=Assumptions!$I$50, Assumptions!$D$50, 0)) -> 1983.0224 | AX13: =IF(AX7>Assumptions!$I$50, AW13*(1+AI27), IF(AX7=Assumptions!$I$50, Assumptions!$D$50, 0)) -> 2025.0283 | AY13: =IF(AY7>Assumptions!$I$50, AX13*(1+AJ27), IF(AY7=Assumptions!$I$50, Assumptions!$D$50, 0)) -> 2074.584 | AZ13: =IF(AZ7>Assumptions!$I$50, AY13*(1+AK27), IF(AZ7=Assumptions!$I$50, Assumptions!$D$50, 0)) -> 2133.5234
B14: software stacks (subscription) | C14: =IF(C8=Assumptions!$F$50, Assumptions!$P$51, 0) -> 0 | D14: =IF(D7>Assumptions!$F$51, C14, IF(D7=Assumptions!$F$51, Assumptions!$P$51, 0)) -> 500 | E14: =IF(E7>Assumptions!$F$51, D14, IF(E7=Assumptions!$F$51, Assumptions!$P$51, 0)) -> 500 | F14: =IF(F7>Assumptions!$F$51, E14, IF(F7=Assumptions!$F$51, Assumptions!$P$51, 0)) -> 500 | G14: =IF(G7>Assumptions!$F$51, F14, IF(G7=Assumptions!$F$51, Assumptions!$P$51, 0)) -> 500 | H14: =IF(H7>Assumptions!$F$51, G14, IF(H7=Assumptions!$F$51, Assumptions!$P$51, 0)) -> 500 | I14: =IF(I7>Assumptions!$F$51, H14, IF(I7=Assumptions!$F$51, Assumptions!$P$51, 0)) -> 500 | J14: =IF(J7>Assumptions!$F$51, I14, IF(J7=Assumptions!$F$51, Assumptions!$P$51, 0)) -> 500 | K14: =IF(K7>Assumptions!$F$51, J14, IF(K7=Assumptions!$F$51, Assumptions!$P$51, 0)) -> 500 | L14: =IF(L7>Assumptions!$F$51, K14, IF(L7=Assumptions!$F$51, Assumptions!$P$51, 0)) -> 500 | P14: software stacks (subscription) | Q14: =IF(Q7=Assumptions!$F$51, Assumptions!$D$51, 0) -> 0 | R14: =IF(R7>Assumptions!$F$51, Q14*(1-Assumptions!$V$15) + Assumptions!$D$51*(1+C27), IF(R7=Assumptions!$F$51, Assumptions!$D$51, 0)) -> 400 | S14: =IF(S7>Assumptions!$F$51, R14*(1-Assumptions!$V$15) + Assumptions!$D$51*(1+D27), IF(S7=Assumptions!$F$51, Assumptions!$D$51, 0)) -> 740.96793 | T14: =IF(T7>Assumptions!$F$51, S14*(1-Assumptions!$V$15) + Assumptions!$D$51*(1+E27), IF(T7=Assumptions!$F$51, Assumptions!$D$51, 0)) -> 1032.2517 | U14: =IF(U7>Assumptions!$F$51, T14*(1-Assumptions!$V$15) + Assumptions!$D$51*(1+F27), IF(U7=Assumptions!$F$51, Assumptions!$D$51, 0)) -> 1281.2079 | V14: =IF(V7>Assumptions!$F$51, U14*(1-Assumptions!$V$15) + Assumptions!$D$51*(1+G27), IF(V7=Assumptions!$F$51, Assumptions!$D$51, 0)) -> 1494.1254 | W14: =IF(W7>Assumptions!$F$51, V14*(1-Assumptions!$V$15) + Assumptions!$D$51*(1+H27), IF(W7=Assumptions!$F$51, Assumptions!$D$51, 0)) -> 1676.6991 | X14: =IF(X7>Assumptions!$F$51, W14*(1-Assumptions!$V$15) + Assumptions!$D$51*(1+I27), IF(X7=Assumptions!$F$51, Assumptions!$D$51, 0)) -> 1833.4583 | Y14: =IF(Y7>Assumptions!$F$51, X14*(1-Assumptions!$V$15) + Assumptions!$D$51*(1+J27), IF(Y7=Assumptions!$F$51, Assumptions!$D$51, 0)) -> 1967.7016 | Z14: =IF(Z7>Assumptions!$F$51, Y14*(1-Assumptions!$V$15) + Assumptions!$D$51*(1+K27), IF(Z7=Assumptions!$F$51, Assumptions!$D$51, 0)) -> 2083.2355 | AB14: software stacks (subscription) | AC14: =IF(AC$67=Assumptions!$I$51, Assumptions!$P$51, 0) -> 0 | AD14: =IF(AD7>Assumptions!$I$51, AC14, IF(AD7=Assumptions!$I$51, Assumptions!$P$51, 0)) -> 0 | AE14: =IF(AE7>Assumptions!$I$51, AD14, IF(AE7=Assumptions!$I$51, Assumptions!$P$51, 0)) -> 0 | AF14: =IF(AF7>Assumptions!$I$51, AE14, IF(AF7=Assumptions!$I$51, Assumptions!$P$51, 0)) -> 0 | AG14: =IF(AG7>Assumptions!$I$51, AF14, IF(AG7=Assumptions!$I$51, Assumptions!$P$51, 0)) -> 500 | AH14: =IF(AH7>Assumptions!$I$51, AG14, IF(AH7=Assumptions!$I$51, Assumptions!$P$51, 0)) -> 500 | AI14: =IF(AI7>Assumptions!$I$51, AH14, IF(AI7=Assumptions!$I$51, Assumptions!$P$51, 0)) -> 500 | AJ14: =IF(AJ7>Assumptions!$I$51, AI14, IF(AJ7=Assumptions!$I$51, Assumptions!$P$51, 0)) -> 500 | AK14: =IF(AK7>Assumptions!$I$51, AJ14, IF(AK7=Assumptions!$I$51, Assumptions!$P$51, 0)) -> 500 | AL14: =IF(AL7>Assumptions!$I$51, AK14, IF(AL7=Assumptions!$I$51, Assumptions!$P$51, 0)) -> 500 | AP14: software stacks (subscription) | AQ14: =IF(AQ7=Assumptions!$I$51, Assumptions!$D$51, 0) -> 0 | AR14: =IF(AR7>Assumptions!$I$51, AQ14*(1-Assumptions!$V$17) + Assumptions!$D$51*(1+AC27), IF(AR7=Assumptions!$I$51, Assumptions!$D$51, 0)) -> 0 | AS14: =IF(AS7>Assumptions!$I$51, AR14*(1-Assumptions!$V$17) + Assumptions!$D$51*(1+AD27), IF(AS7=Assumptions!$I$51, Assumptions!$D$51, 0)) -> 0 | AT14: =IF(AT7>Assumptions!$I$51, AS14*(1-Assumptions!$V$17) + Assumptions!$D$51*(1+AE27), IF(AT7=Assumptions!$I$51, Assumptions!$D$51, 0)) -> 0 | AU14: =IF(AU7>Assumptions!$I$51, AT14*(1-Assumptions!$V$17) + Assumptions!$D$51*(1+AF27), IF(AU7=Assumptions!$I$51, Assumptions!$D$51, 0)) -> 400 | AV14: =IF(AV7>Assumptions!$I$51, AU14*(1-Assumptions!$V$17) + Assumptions!$D$51*(1+AG27), IF(AV7=Assumptions!$I$51, Assumptions!$D$51, 0)) -> 749.65008 | AW14: =IF(AW7>Assumptions!$I$51, AV14*(1-Assumptions!$V$17) + Assumptions!$D$51*(1+AH27), IF(AW7=Assumptions!$I$51, Assumptions!$D$51, 0)) -> 1051.6164 | AX14: =IF(AX7>Assumptions!$I$51, AW14*(1-Assumptions!$V$17) + Assumptions!$D$51*(1+AI27), IF(AX7=Assumptions!$I$51, Assumptions!$D$51, 0)) -> 1312.8632 | AY14: =IF(AY7>Assumptions!$I$51, AX14*(1-Assumptions!$V$17) + Assumptions!$D$51*(1+AJ27), IF(AY7=Assumptions!$I$51, Assumptions!$D$51, 0)) -> 1538.851 | AZ14: =IF(AZ7>Assumptions!$I$51, AY14*(1-Assumptions!$V$17) + Assumptions!$D$51*(1+AK27), IF(AZ7=Assumptions!$I$51, Assumptions!$D$51, 0)) -> 1734.7759
B15: system integration | C15: =IF(C7=Assumptions!$F$52, Assumptions!$P$52, 0) -> 0 | D15: =IF(D7>Assumptions!$F$52, C15*(1+C3), IF(D7=Assumptions!$F$52, Assumptions!$P$52, 0)) -> 500 | E15: =IF(E7>Assumptions!$F$52, D15*(1+D3), IF(E7=Assumptions!$F$52, Assumptions!$P$52, 0)) -> 523 | F15: =IF(F7>Assumptions!$F$52, E15*(1+E3), IF(F7=Assumptions!$F$52, Assumptions!$P$52, 0)) -> 547.058 | G15: =IF(G7>Assumptions!$F$52, F15*(1+F3), IF(G7=Assumptions!$F$52, Assumptions!$P$52, 0)) -> 572.22267 | H15: =IF(H7>Assumptions!$F$52, G15*(1+G3), IF(H7=Assumptions!$F$52, Assumptions!$P$52, 0)) -> 598.54491 | I15: =IF(I7>Assumptions!$F$52, H15*(1+H3), IF(I7=Assumptions!$F$52, Assumptions!$P$52, 0)) -> 626.07798 | J15: =IF(J7>Assumptions!$F$52, I15*(1+I3), IF(J7=Assumptions!$F$52, Assumptions!$P$52, 0)) -> 654.87756 | K15: =IF(K7>Assumptions!$F$52, J15*(1+J3), IF(K7=Assumptions!$F$52, Assumptions!$P$52, 0)) -> 685.00193 | L15: =IF(L7>Assumptions!$F$52, K15*(1+K3), IF(L7=Assumptions!$F$52, Assumptions!$P$52, 0)) -> 716.51202 | P15: system integration | Q15: =IF(Q7=Assumptions!$F$52, Assumptions!$D$52, 0) -> 0 | R15: =IF(R7>Assumptions!$F$52, Q15*(1+C28), IF(R7=Assumptions!$F$52, Assumptions!$D$52, 0)) -> 300 | S15: =IF(S7>Assumptions!$F$52, R15*(1+D28), IF(S7=Assumptions!$F$52, Assumptions!$D$52, 0)) -> 301.11278 | T15: =IF(T7>Assumptions!$F$52, S15*(1+E28), IF(T7=Assumptions!$F$52, Assumptions!$D$52, 0)) -> 303.20058 | U15: =IF(U7>Assumptions!$F$52, T15*(1+F28), IF(U7=Assumptions!$F$52, Assumptions!$D$52, 0)) -> 306.22802 | V15: =IF(V7>Assumptions!$F$52, U15*(1+G28), IF(V7=Assumptions!$F$52, Assumptions!$D$52, 0)) -> 310.47046 | W15: =IF(W7>Assumptions!$F$52, V15*(1+H28), IF(W7=Assumptions!$F$52, Assumptions!$D$52, 0)) -> 315.55677 | X15: =IF(X7>Assumptions!$F$52, W15*(1+I28), IF(X7=Assumptions!$F$52, Assumptions!$D$52, 0)) -> 321.87588 | Y15: =IF(Y7>Assumptions!$F$52, X15*(1+J28), IF(Y7=Assumptions!$F$52, Assumptions!$D$52, 0)) -> 329.15907 | Z15: =IF(Z7>Assumptions!$F$52, Y15*(1+K28), IF(Z7=Assumptions!$F$52, Assumptions!$D$52, 0)) -> 337.79284 | AB15: system integration | AC15: =IF(AC$67=Assumptions!$I$52, Assumptions!$P$52, 0) -> 0 | AD15: =IF(AD7>Assumptions!$I$52, AC15*(1+AC3), IF(AD7=Assumptions!$I$52, Assumptions!$P$52, 0)) -> 0 | AE15: =IF(AE7>Assumptions!$I$52, AD15*(1+AD3), IF(AE7=Assumptions!$I$52, Assumptions!$P$52, 0)) -> 0 | AF15: =IF(AF7>Assumptions!$I$52, AE15*(1+AE3), IF(AF7=Assumptions!$I$52, Assumptions!$P$52, 0)) -> 0 | AG15: =IF(AG7>Assumptions!$I$52, AF15*(1+AF3), IF(AG7=Assumptions!$I$52, Assumptions!$P$52, 0)) -> 500 | AH15: =IF(AH7>Assumptions!$I$52, AG15*(1+AG3), IF(AH7=Assumptions!$I$52, Assumptions!$P$52, 0)) -> 520 | AI15: =IF(AI7>Assumptions!$I$52, AH15*(1+AH3), IF(AI7=Assumptions!$I$52, Assumptions!$P$52, 0)) -> 540.8 | AJ15: =IF(AJ7>Assumptions!$I$52, AI15*(1+AI3), IF(AJ7=Assumptions!$I$52, Assumptions!$P$52, 0)) -> 562.432 | AK15: =IF(AK7>Assumptions!$I$52, AJ15*(1+AJ3), IF(AK7=Assumptions!$I$52, Assumptions!$P$52, 0)) -> 584.92928 | AL15: =IF(AL7>Assumptions!$I$52, AK15*(1+AK3), IF(AL7=Assumptions!$I$52, Assumptions!$P$52, 0)) -> 608.32645 | AP15: system integration | AQ15: =IF(AQ7=Assumptions!$I$52, Assumptions!$D$52, 0) -> 0 | AR15: =IF(AR7>Assumptions!$F$52, AQ15*(1+AC28), IF(AR7=Assumptions!$I$52, Assumptions!$D$52, 0)) -> 0 | AS15: =IF(AS7>Assumptions!$F$52, AR15*(1+AD28), IF(AS7=Assumptions!$I$52, Assumptions!$D$52, 0)) -> 0 | AT15: =IF(AT7>Assumptions!$F$52, AS15*(1+AE28), IF(AT7=Assumptions!$I$52, Assumptions!$D$52, 0)) -> 0 | AU15: =IF(AU7>Assumptions!$F$52, AT15*(1+AF28), IF(AU7=Assumptions!$I$52, Assumptions!$D$52, 0)) -> 0 | AV15: =IF(AV7>Assumptions!$F$52, AU15*(1+AG28), IF(AV7=Assumptions!$I$52, Assumptions!$D$52, 0)) -> 0 | AW15: =IF(AW7>Assumptions!$F$52, AV15*(1+AH28), IF(AW7=Assumptions!$I$52, Assumptions!$D$52, 0)) -> 0 | AX15: =IF(AX7>Assumptions!$F$52, AW15*(1+AI28), IF(AX7=Assumptions!$I$52, Assumptions!$D$52, 0)) -> 0 | AY15: =IF(AY7>Assumptions!$F$52, AX15*(1+AJ28), IF(AY7=Assumptions!$I$52, Assumptions!$D$52, 0)) -> 0 | AZ15: =IF(AZ7>Assumptions!$F$52, AY15*(1+AK28), IF(AZ7=Assumptions!$I$52, Assumptions!$D$52, 0)) -> 0
B16: liscencing | C16: =IF(C7=Assumptions!$F$53, Assumptions!$P$53, 0) -> 0 | D16: =IF(D7>Assumptions!$F$53, C16*(1+C3), IF(D7=Assumptions!$F$53, Assumptions!$P$53, 0)) -> 300 | E16: =IF(E7>Assumptions!$F$53, D16*(1+D3), IF(E7=Assumptions!$F$53, Assumptions!$P$53, 0)) -> 313.8 | F16: =IF(F7>Assumptions!$F$53, E16*(1+E3), IF(F7=Assumptions!$F$53, Assumptions!$P$53, 0)) -> 328.2348 | G16: =IF(G7>Assumptions!$F$53, F16*(1+F3), IF(G7=Assumptions!$F$53, Assumptions!$P$53, 0)) -> 343.3336 | H16: =IF(H7>Assumptions!$F$53, G16*(1+G3), IF(H7=Assumptions!$F$53, Assumptions!$P$53, 0)) -> 359.12695 | I16: =IF(I7>Assumptions!$F$53, H16*(1+H3), IF(I7=Assumptions!$F$53, Assumptions!$P$53, 0)) -> 375.64679 | J16: =IF(J7>Assumptions!$F$53, I16*(1+I3), IF(J7=Assumptions!$F$53, Assumptions!$P$53, 0)) -> 392.92654 | K16: =IF(K7>Assumptions!$F$53, J16*(1+J3), IF(K7=Assumptions!$F$53, Assumptions!$P$53, 0)) -> 411.00116 | L16: =IF(L7>Assumptions!$F$53, K16*(1+K3), IF(L7=Assumptions!$F$53, Assumptions!$P$53, 0)) -> 429.90721 | P16: liscencing | Q16: =IF(Q7=Assumptions!$F$53, Assumptions!$D$53, 0) -> 0 | R16: =IF(R7>Assumptions!$F$53, Q16*(1+C29), IF(R7=Assumptions!$F$53, Assumptions!$D$53, 0)) -> 1500 | S16: =IF(S7>Assumptions!$F$53, R16*(1+D29), IF(S7=Assumptions!$F$53, Assumptions!$D$53, 0)) -> 1505.3138 | T16: =IF(T7>Assumptions!$F$53, S16*(1+E29), IF(T7=Assumptions!$F$53, Assumptions!$D$53, 0)) -> 1514.5467 | U16: =IF(U7>Assumptions!$F$53, T16*(1+F29), IF(U7=Assumptions!$F$53, Assumptions!$D$53, 0)) -> 1529.6971 | V16: =IF(V7>Assumptions!$F$53, U16*(1+G29), IF(V7=Assumptions!$F$53, Assumptions!$D$53, 0)) -> 1550.8971 | W16: =IF(W7>Assumptions!$F$53, V16*(1+H29), IF(W7=Assumptions!$F$53, Assumptions!$D$53, 0)) -> 1578.5657 | X16: =IF(X7>Assumptions!$F$53, W16*(1+I29), IF(X7=Assumptions!$F$53, Assumptions!$D$53, 0)) -> 1612.4646 | Y16: =IF(Y7>Assumptions!$F$53, X16*(1+J29), IF(Y7=Assumptions!$F$53, Assumptions!$D$53, 0)) -> 1653.0737 | Z16: =IF(Z7>Assumptions!$F$53, Y16*(1+K29), IF(Z7=Assumptions!$F$53, Assumptions!$D$53, 0)) -> 1700.083 | AB16: liscencing | AC16: =IF(AC$67=Assumptions!$I$53, Assumptions!$P$53, 0) -> 0 | AD16: =IF(AD7>Assumptions!$I$53, AC16*(1+AC3), IF(AD7=Assumptions!$I$53, Assumptions!$P$53, 0)) -> 0 | AE16: =IF(AE7>Assumptions!$I$53, AD16*(1+AD3), IF(AE7=Assumptions!$I$53, Assumptions!$P$53, 0)) -> 0 | AF16: =IF(AF7>Assumptions!$I$53, AE16*(1+AE3), IF(AF7=Assumptions!$I$53, Assumptions!$P$53, 0)) -> 0 | AG16: =IF(AG7>Assumptions!$I$53, AF16*(1+AF3), IF(AG7=Assumptions!$I$53, Assumptions!$P$53, 0)) -> 300 | AH16: =IF(AH7>Assumptions!$I$53, AG16*(1+AG3), IF(AH7=Assumptions!$I$53, Assumptions!$P$53, 0)) -> 312 | AI16: =IF(AI7>Assumptions!$I$53, AH16*(1+AH3), IF(AI7=Assumptions!$I$53, Assumptions!$P$53, 0)) -> 324.48 | AJ16: =IF(AJ7>Assumptions!$I$53, AI16*(1+AI3), IF(AJ7=Assumptions!$I$53, Assumptions!$P$53, 0)) -> 337.4592 | AK16: =IF(AK7>Assumptions!$I$53, AJ16*(1+AJ3), IF(AK7=Assumptions!$I$53, Assumptions!$P$53, 0)) -> 350.95757 | AL16: =IF(AL7>Assumptions!$I$53, AK16*(1+AK3), IF(AL7=Assumptions!$I$53, Assumptions!$P$53, 0)) -> 364.99587 | AP16: liscencing | AQ16: =IF(AQ7=Assumptions!$I$53, Assumptions!$D$53, 0) -> 0 | AR16: =IF(AR7>Assumptions!$I$53, AQ16*(1+AC29), IF(AR7=Assumptions!$I$53, Assumptions!$D$53, 0)) -> 0 | AS16: =IF(AS7>Assumptions!$I$53, AR16*(1+AD29), IF(AS7=Assumptions!$I$53, Assumptions!$D$53, 0)) -> 0 | AT16: =IF(AT7>Assumptions!$I$53, AS16*(1+AE29), IF(AT7=Assumptions!$I$53, Assumptions!$D$53, 0)) -> 0 | AU16: =IF(AU7>Assumptions!$I$53, AT16*(1+AF29), IF(AU7=Assumptions!$I$53, Assumptions!$D$53, 0)) -> 1500 | AV16: =IF(AV7>Assumptions!$I$53, AU16*(1+AG29), IF(AV7=Assumptions!$I$53, Assumptions!$D$53, 0)) -> 1521.7306 | AW16: =IF(AW7>Assumptions!$I$53, AV16*(1+AH29), IF(AW7=Assumptions!$I$53, Assumptions!$D$53, 0)) -> 1548.937 | AX16: =IF(AX7>Assumptions!$I$53, AW16*(1+AI29), IF(AX7=Assumptions!$I$53, Assumptions!$D$53, 0)) -> 1582.6628 | AY16: =IF(AY7>Assumptions!$I$53, AX16*(1+AJ29), IF(AY7=Assumptions!$I$53, Assumptions!$D$53, 0)) -> 1621.7024 | AZ16: =IF(AZ7>Assumptions!$I$53, AY16*(1+AK29), IF(AZ7=Assumptions!$I$53, Assumptions!$D$53, 0)) -> 1667.4294
B17: maintenance | C17: =IF(C7=Assumptions!$F$54, Assumptions!$P$54, 0) -> 0 | D17: =IF(D7>Assumptions!$F$54, C17*(1+C3), IF(D7=Assumptions!$F$54, Assumptions!$P$54, 0)) -> 700 | E17: =IF(E7>Assumptions!$F$54, D17*(1+D3), IF(E7=Assumptions!$F$54, Assumptions!$P$54, 0)) -> 732.2 | F17: =IF(F7>Assumptions!$F$54, E17*(1+E3), IF(F7=Assumptions!$F$54, Assumptions!$P$54, 0)) -> 765.8812 | G17: =IF(G7>Assumptions!$F$54, F17*(1+F3), IF(G7=Assumptions!$F$54, Assumptions!$P$54, 0)) -> 801.11174 | H17: =IF(H7>Assumptions!$F$54, G17*(1+G3), IF(H7=Assumptions!$F$54, Assumptions!$P$54, 0)) -> 837.96288 | I17: =IF(I7>Assumptions!$F$54, H17*(1+H3), IF(I7=Assumptions!$F$54, Assumptions!$P$54, 0)) -> 876.50917 | J17: =IF(J7>Assumptions!$F$54, I17*(1+I3), IF(J7=Assumptions!$F$54, Assumptions!$P$54, 0)) -> 916.82859 | K17: =IF(K7>Assumptions!$F$54, J17*(1+J3), IF(K7=Assumptions!$F$54, Assumptions!$P$54, 0)) -> 959.0027 | L17: =IF(L7>Assumptions!$F$54, K17*(1+K3), IF(L7=Assumptions!$F$54, Assumptions!$P$54, 0)) -> 1003.1168 | P17: maintenance | Q17: =IF(Q7=Assumptions!$F$53, Assumptions!$D$54, 0) -> 0 | R17: =IF(R7>Assumptions!$F$54, Q17*(1+C30), IF(R7=Assumptions!$F$54, Assumptions!$D$54, 0)) -> 700 | S17: =IF(S7>Assumptions!$F$54, R17*(1+D30), IF(S7=Assumptions!$F$54, Assumptions!$D$54, 0)) -> 702.53078 | T17: =IF(T7>Assumptions!$F$54, S17*(1+E30), IF(T7=Assumptions!$F$54, Assumptions!$D$54, 0)) -> 707.83708 | U17: =IF(U7>Assumptions!$F$54, T17*(1+F30), IF(U7=Assumptions!$F$54, Assumptions!$D$54, 0)) -> 715.58259 | V17: =IF(V7>Assumptions!$F$54, U17*(1+G30), IF(V7=Assumptions!$F$54, Assumptions!$D$54, 0)) -> 725.98917 | W17: =IF(W7>Assumptions!$F$54, V17*(1+H30), IF(W7=Assumptions!$F$54, Assumptions!$D$54, 0)) -> 738.65899 | X17: =IF(X7>Assumptions!$F$54, W17*(1+I30), IF(X7=Assumptions!$F$54, Assumptions!$D$54, 0)) -> 754.49559 | Y17: =IF(Y7>Assumptions!$F$54, X17*(1+J30), IF(Y7=Assumptions!$F$54, Assumptions!$D$54, 0)) -> 773.53003 | Z17: =IF(Z7>Assumptions!$F$54, Y17*(1+K30), IF(Z7=Assumptions!$F$54, Assumptions!$D$54, 0)) -> 795.7183 | AB17: maintenance | AC17: =IF(AC$67=Assumptions!$I$54, Assumptions!$P$54, 0) -> 0 | AD17: =IF(AD7>Assumptions!$I$54, AC17*(1+AC3), IF(AD7=Assumptions!$I$54, Assumptions!$P$54, 0)) -> 0 | AE17: =IF(AE7>Assumptions!$I$54, AD17*(1+AD3), IF(AE7=Assumptions!$I$54, Assumptions!$P$54, 0)) -> 0 | AF17: =IF(AF7>Assumptions!$I$54, AE17*(1+AE3), IF(AF7=Assumptions!$I$54, Assumptions!$P$54, 0)) -> 0 | AG17: =IF(AG7>Assumptions!$I$54, AF17*(1+AF3), IF(AG7=Assumptions!$I$54, Assumptions!$P$54, 0)) -> 700 | AH17: =IF(AH7>Assumptions!$I$54, AG17*(1+AG3), IF(AH7=Assumptions!$I$54, Assumptions!$P$54, 0)) -> 728 | AI17: =IF(AI7>Assumptions!$I$54, AH17*(1+AH3), IF(AI7=Assumptions!$I$54, Assumptions!$P$54, 0)) -> 757.12 | AJ17: =IF(AJ7>Assumptions!$I$54, AI17*(1+AI3), IF(AJ7=Assumptions!$I$54, Assumptions!$P$54, 0)) -> 787.4048 | AK17: =IF(AK7>Assumptions!$I$54, AJ17*(1+AJ3), IF(AK7=Assumptions!$I$54, Assumptions!$P$54, 0)) -> 818.90099 | AL17: =IF(AL7>Assumptions!$I$54, AK17*(1+AK3), IF(AL7=Assumptions!$I$54, Assumptions!$P$54, 0)) -> 851.65703 | AP17: maintenance | AQ17: =IF(AQ7=Assumptions!$I$53, Assumptions!$D$54, 0) -> 0 | AR17: =IF(AR7>Assumptions!$F$54, AQ17*(1+AC30), IF(AR7=Assumptions!$I$54, Assumptions!$D$54, 0)) -> 0 | AS17: =IF(AS7>Assumptions!$F$54, AR17*(1+AD30), IF(AS7=Assumptions!$I$54, Assumptions!$D$54, 0)) -> 0 | AT17: =IF(AT7>Assumptions!$F$54, AS17*(1+AE30), IF(AT7=Assumptions!$I$54, Assumptions!$D$54, 0)) -> 0 | AU17: =IF(AU7>Assumptions!$F$54, AT17*(1+AF30), IF(AU7=Assumptions!$I$54, Assumptions!$D$54, 0)) -> 0 | AV17: =IF(AV7>Assumptions!$F$54, AU17*(1+AG30), IF(AV7=Assumptions!$I$54, Assumptions!$D$54, 0)) -> 0 | AW17: =IF(AW7>Assumptions!$F$54, AV17*(1+AH30), IF(AW7=Assumptions!$I$54, Assumptions!$D$54, 0)) -> 0 | AX17: =IF(AX7>Assumptions!$F$54, AW17*(1+AI30), IF(AX7=Assumptions!$I$54, Assumptions!$D$54, 0)) -> 0 | AY17: =IF(AY7>Assumptions!$F$54, AX17*(1+AJ30), IF(AY7=Assumptions!$I$54, Assumptions!$D$54, 0)) -> 0 | AZ17: =IF(AZ7>Assumptions!$F$54, AY17*(1+AK30), IF(AZ7=Assumptions!$I$54, Assumptions!$D$54, 0)) -> 0
C20: Year | Q20: Year | AC20: Year | AQ20: Year
C21: 1 | D21: 2 | E21: 3 | F21: 4 | G21: 5 | H21: 6 | I21: 7 | J21: 8 | K21: 9 | L21: 10 | P21: REVENUE FROM SALES | Q21: 1 | R21: 2 | S21: 3 | T21: 4 | U21: 5 | V21: 6 | W21: 7 | X21: 8 | Y21: 9 | Z21: 10 | AC21: 1 | AD21: 2 | AE21: 3 | AF21: 4 | AG21: 5 | AH21: 6 | AI21: 7 | AJ21: 8 | AK21: 9 | AL21: 10 | AP21: REVENUE FROM SALES | AQ21: 1 | AR21: 2 | AS21: 3 | AT21: 4 | AU21: 5 | AV21: 6 | AW21: 7 | AX21: 8 | AY21: 9 | AZ21: 10
B22: Drone | C22: 0.05 | D22: =C22+_xlfn.NORM.DIST(RAND(), 0, 1, FALSE)% -> 0.052606948 | E22: =D22+_xlfn.NORM.DIST(RAND(), 0, 1, FALSE)% -> 0.055803081 | F22: =E22+_xlfn.NORM.DIST(RAND(), 0, 1, FALSE)% -> 0.058566259 | G22: =F22+_xlfn.NORM.DIST(RAND(), 0, 1, FALSE)% -> 0.061152988 | H22: =G22+_xlfn.NORM.DIST(RAND(), 0, 1, FALSE)% -> 0.065114901 | I22: =H22+_xlfn.NORM.DIST(RAND(), 0, 1, FALSE)% -> 0.068693133 | J22: =I22+_xlfn.NORM.DIST(RAND(), 0, 1, FALSE)% -> 0.072579253 | K22: =J22+_xlfn.NORM.DIST(RAND(), 0, 1, FALSE)% -> 0.076567339 | L22: =K22+_xlfn.NORM.DIST(RAND(), 0, 1, FALSE)% -> 0.080556375 | P22: Drone | Q22: =C8*Q8 -> 7700000 | R22: =D8*R8 -> 8456910 | S22: =E8*S8 -> 9311285.1 | T22: =F8*T8 -> 10283104 | U22: =G8*U8 -> 11386073 | V22: =H8*V8 -> 12638154 | W22: =I8*W8 -> 14080296 | X22: =J8*X8 -> 15739702 | ... Z22: =L8*Z8 -> 19885223 | AB22: Drone | AC22: 0.02 | AD22: =AC22+_xlfn.NORM.DIST(RAND(), 0, 1, FALSE)% -> 0.022847004 | AE22: =AD22+_xlfn.NORM.DIST(RAND(), 0, 1, FALSE)% -> 0.026216456 | AF22: =AE22+_xlfn.NORM.DIST(RAND(), 0, 1, FALSE)% -> 0.030203271 | AG22: =AF22+_xlfn.NORM.DIST(RAND(), 0, 1, FALSE)% -> 0.032780608 | AH22: =AG22+_xlfn.NORM.DIST(RAND(), 0, 1, FALSE)% -> 0.036028851 | AI22: =AH22+_xlfn.NORM.DIST(RAND(), 0, 1, FALSE)% -> 0.038720824 | AJ22: =AI22+_xlfn.NORM.DIST(RAND(), 0, 1, FALSE)% -> 0.042696784 | AK22: =AJ22+_xlfn.NORM.DIST(RAND(), 0, 1, FALSE)% -> 0.04520808 | AL22: =AK22+_xlfn.NORM.DIST(RAND(), 0, 1, FALSE)% -> 0.048000253 | AP22: Drone | AQ22: =AC8*AQ8 -> 0 | AR22: =AD8*AR8 -> 0 | AS22: =AE8*AS8 -> 0 | AT22: =AF8*AT8 -> 7700000 | AU22: =AG8*AU8 -> 8249867.8 | AV22: =AH8*AV8 -> 8861115.6 | AW22: =AI8*AW8 -> 9547586.3 | AX22: =AJ8*AX8 -> 10313968 | ... AZ22: =AL8*AZ8 -> 12157751
B23: Rover | C23: 0.09 | D23: =C23+_xlfn.NORM.DIST(RAND(), 0, 1, FALSE)% -> 0.092780869 | E23: =D23+_xlfn.NORM.DIST(RAND(), 0, 1, FALSE)% -> 0.096184068 | F23: =E23+_xlfn.NORM.DIST(RAND(), 0, 1, FALSE)% -> 0.09876379 | G23: =F23+_xlfn.NORM.DIST(RAND(), 0, 1, FALSE)% -> 0.10222766 | H23: =G23+_xlfn.NORM.DIST(RAND(), 0, 1, FALSE)% -> 0.106162 | I23: =H23+_xlfn.NORM.DIST(RAND(), 0, 1, FALSE)% -> 0.11010775 | J23: =I23+_xlfn.NORM.DIST(RAND(), 0, 1, FALSE)% -> 0.11306655 | K23: =J23+_xlfn.NORM.DIST(RAND(), 0, 1, FALSE)% -> 0.11691135 | L23: =K23+_xlfn.NORM.DIST(RAND(), 0, 1, FALSE)% -> 0.12015508 | P23: Rover | Q23: =C9*Q9 -> 7000000 | R23: =D9*R9 -> 7980980 | S23: =E9*S9 -> 9122649.5 | T23: =F9*T9 -> 10460108 | U23: =G9*U9 -> 12021874 | V23: =H9*V9 -> 13860381 | W23: =I9*W9 -> 16037091 | X23: =J9*X9 -> 18621832 | ... Z23: =L9*Z9 -> 25329442 | AB23: Rover | AC23: 0.05 | AD23: =AC23+_xlfn.NORM.DIST(RAND(), 0, 1, FALSE)% -> 0.053511262 | AE23: =AD23+_xlfn.NORM.DIST(RAND(), 0, 1, FALSE)% -> 0.057437971 | AF23: =AE23+_xlfn.NORM.DIST(RAND(), 0, 1, FALSE)% -> 0.059863823 | AG23: =AF23+_xlfn.NORM.DIST(RAND(), 0, 1, FALSE)% -> 0.063133472 | AH23: =AG23+_xlfn.NORM.DIST(RAND(), 0, 1, FALSE)% -> 0.066092783 | AI23: =AH23+_xlfn.NORM.DIST(RAND(), 0, 1, FALSE)% -> 0.06946769 | AJ23: =AI23+_xlfn.NORM.DIST(RAND(), 0, 1, FALSE)% -> 0.07275701 | AK23: =AJ23+_xlfn.NORM.DIST(RAND(), 0, 1, FALSE)% -> 0.076497518 | AL23: =AK23+_xlfn.NORM.DIST(RAND(), 0, 1, FALSE)% -> 0.080364664 | AP23: Rover | AQ23: =AC9*AQ9 -> 0 | AR23: =AD9*AR9 -> 0 | AS23: =AE9*AS9 -> 0 | AT23: =AF9*AT9 -> 7000000 | AU23: =AG9*AU9 -> 7715808.6 | AV23: =AH9*AV9 -> 8531051.8 | AW23: =AI9*AW9 -> 9458688.5 | AX23: =AJ9*AX9 -> 10520392 | ... AZ23: =AL9*AZ9 -> 13140534
B24: Edge | C24: 0.02 | D24: =C24+_xlfn.NORM.DIST(RAND(), 0, 1, FALSE)% -> 0.022756083 | E24: =D24+_xlfn.NORM.DIST(RAND(), 0, 1, FALSE)% -> 0.025980366 | F24: =E24+_xlfn.NORM.DIST(RAND(), 0, 1, FALSE)% -> 0.029115196 | G24: =F24+_xlfn.NORM.DIST(RAND(), 0, 1, FALSE)% -> 0.03300506 | H24: =G24+_xlfn.NORM.DIST(RAND(), 0, 1, FALSE)% -> 0.036732185 | I24: =H24+_xlfn.NORM.DIST(RAND(), 0, 1, FALSE)% -> 0.040686203 | J24: =I24+_xlfn.NORM.DIST(RAND(), 0, 1, FALSE)% -> 0.044023831 | K24: =J24+_xlfn.NORM.DIST(RAND(), 0, 1, FALSE)% -> 0.047969969 | L24: =K24+_xlfn.NORM.DIST(RAND(), 0, 1, FALSE)% -> 0.050898615 | P24: Edge | Q24: =C10*Q10 -> 5080000 | R24: =D10*R10 -> 5419953.6 | S24: =E10*S10 -> 5798281.9 | T24: =F10*T10 -> 6222573.8 | U24: =G10*U10 -> 6698317.6 | V24: =H10*V10 -> 7237688.2 | W24: =I10*W10 -> 7848707.3 | X24: =J10*X10 -> 8543771.3 | ... Z24: =L10*Z10 -> 10227565 | AB24: Edge | AC24: 0.03 | AD24: =AC24+_xlfn.NORM.DIST(RAND(), 0, 1, FALSE)% -> 0.032714504 | AE24: =AD24+_xlfn.NORM.DIST(RAND(), 0, 1, FALSE)% -> 0.036506928 | AF24: =AE24+_xlfn.NORM.DIST(RAND(), 0, 1, FALSE)% -> 0.040111221 | AG24: =AF24+_xlfn.NORM.DIST(RAND(), 0, 1, FALSE)% -> 0.043710267 | AH24: =AG24+_xlfn.NORM.DIST(RAND(), 0, 1, FALSE)% -> 0.047661069 | AI24: =AH24+_xlfn.NORM.DIST(RAND(), 0, 1, FALSE)% -> 0.05165043 | AJ24: =AI24+_xlfn.NORM.DIST(RAND(), 0, 1, FALSE)% -> 0.055034275 | AK24: =AJ24+_xlfn.NORM.DIST(RAND(), 0, 1, FALSE)% -> 0.058390817 | AL24: =AK24+_xlfn.NORM.DIST(RAND(), 0, 1, FALSE)% -> 0.062026005 | AP24: Edge | AQ24: =AC10*AQ10 -> 0 | AR24: =AD10*AR10 -> 0 | AS24: =AE10*AS10 -> 0 | AT24: =AF10*AT10 -> 5080000 | AU24: =AG10*AU10 -> 5495115.6 | AV24: =AH10*AV10 -> 5964720.9 | AW24: =AI10*AW10 -> 6498966.1 | AX24: =AJ10*AX10 -> 7108026.1 | ... AZ24: =AL10*AZ10 -> 8584763.3
B25: Fog | C25: 0.04 | D25: =C25+_xlfn.NORM.DIST(RAND(), 0, 1, FALSE)% -> 0.042481757 | E25: =D25+_xlfn.NORM.DIST(RAND(), 0, 1, FALSE)% -> 0.046412686 | F25: =E25+_xlfn.NORM.DIST(RAND(), 0, 1, FALSE)% -> 0.049229039 | G25: =F25+_xlfn.NORM.DIST(RAND(), 0, 1, FALSE)% -> 0.051708515 | H25: =G25+_xlfn.NORM.DIST(RAND(), 0, 1, FALSE)% -> 0.055164241 | I25: =H25+_xlfn.NORM.DIST(RAND(), 0, 1, FALSE)% -> 0.058405708 | J25: =I25+_xlfn.NORM.DIST(RAND(), 0, 1, FALSE)% -> 0.061516619 | K25: =J25+_xlfn.NORM.DIST(RAND(), 0, 1, FALSE)% -> 0.064843109 | L25: =K25+_xlfn.NORM.DIST(RAND(), 0, 1, FALSE)% -> 0.067475039 | P25: Fog | R25: =D11*R11 -> 6032500 | S25: =E11*S11 -> 6578054.7 | T25: =F11*T11 -> 7199994.4 | U25: =G11*U11 -> 7901947.6 | V25: =H11*V11 -> 8692830.7 | W25: =I11*W11 -> 9594292.8 | X25: =J11*X11 -> 10621768 | Y25: =K11*Y11 -> 11793842 | Z25: =L11*Z11 -> 13136287 | AB25: Fog | AC25: 0.04 | AD25: =AC25+_xlfn.NORM.DIST(RAND(), 0, 1, FALSE)% -> 0.042671591 | AE25: =AD25+_xlfn.NORM.DIST(RAND(), 0, 1, FALSE)% -> 0.046008782 | AF25: =AE25+_xlfn.NORM.DIST(RAND(), 0, 1, FALSE)% -> 0.049997498 | AG25: =AF25+_xlfn.NORM.DIST(RAND(), 0, 1, FALSE)% -> 0.053112123 | AH25: =AG25+_xlfn.NORM.DIST(RAND(), 0, 1, FALSE)% -> 0.056467589 | AI25: =AH25+_xlfn.NORM.DIST(RAND(), 0, 1, FALSE)% -> 0.059439861 | AJ25: =AI25+_xlfn.NORM.DIST(RAND(), 0, 1, FALSE)% -> 0.062808354 | AK25: =AJ25+_xlfn.NORM.DIST(RAND(), 0, 1, FALSE)% -> 0.06547014 | AL25: =AK25+_xlfn.NORM.DIST(RAND(), 0, 1, FALSE)% -> 0.069337543 | AP25: Fog | AR25: =AD11*AR11 -> 0 | AS25: =AE11*AS11 -> 0 | AT25: =AF11*AT11 -> 0 | AU25: =AG11*AU11 -> 6032500 | AV25: =AH11*AV11 -> 6607014.8 | AW25: =AI11*AW11 -> 7259300.9 | AX25: =AJ11*AX11 -> 7998424.5 | AY25: =AK11*AY11 -> 8840824 | AZ25: =AL11*AZ11 -> 9796419.4
B26: Enterprise | C26: 0.04 | D26: =C26+_xlfn.NORM.DIST(RAND(), 0, 1, FALSE)% -> 0.043427369 | E26: =D26+_xlfn.NORM.DIST(RAND(), 0, 1, FALSE)% -> 0.046974549 | F26: =E26+_xlfn.NORM.DIST(RAND(), 0, 1, FALSE)% -> 0.049839042 | G26: =F26+_xlfn.NORM.DIST(RAND(), 0, 1, FALSE)% -> 0.052426684 | H26: =G26+_xlfn.NORM.DIST(RAND(), 0, 1, FALSE)% -> 0.0552187 | I26: =H26+_xlfn.NORM.DIST(RAND(), 0, 1, FALSE)% -> 0.058857169 | J26: =I26+_xlfn.NORM.DIST(RAND(), 0, 1, FALSE)% -> 0.06164607 | K26: =J26+_xlfn.NORM.DIST(RAND(), 0, 1, FALSE)% -> 0.065508047 | L26: =K26+_xlfn.NORM.DIST(RAND(), 0, 1, FALSE)% -> 0.069062543 | P26: Enterprise | S26: =E12*S12 -> 3180000 | T26: =F12*T12 -> 3482530.5 | U26: =G12*U12 -> 3824276.9 | V26: =H12*V12 -> 4209910.6 | W26: =I12*W12 -> 4646725.7 | X26: =J12*X12 -> 5146548.8 | Y26: =K12*Y12 -> 5715148.8 | Z26: =L12*Z12 -> 6369655.7 | AB26: Enterprise | AC26: 0.07 | AD26: =AC26+_xlfn.NORM.DIST(RAND(), 0, 1, FALSE)% -> 0.07274012 | AE26: =AD26+_xlfn.NORM.DIST(RAND(), 0, 1, FALSE)% -> 0.07625308 | AF26: =AE26+_xlfn.NORM.DIST(RAND(), 0, 1, FALSE)% -> 0.080200414 | AG26: =AF26+_xlfn.NORM.DIST(RAND(), 0, 1, FALSE)% -> 0.08409782 | AH26: =AG26+_xlfn.NORM.DIST(RAND(), 0, 1, FALSE)% -> 0.086613789 | AI26: =AH26+_xlfn.NORM.DIST(RAND(), 0, 1, FALSE)% -> 0.090581625 | AJ26: =AI26+_xlfn.NORM.DIST(RAND(), 0, 1, FALSE)% -> 0.094544234 | AK26: =AJ26+_xlfn.NORM.DIST(RAND(), 0, 1, FALSE)% -> 0.098118548 | AL26: =AK26+_xlfn.NORM.DIST(RAND(), 0, 1, FALSE)% -> 0.10065132 | AP26: Enterprise | AS26: =AE12*AS12 -> 0 | AT26: =AF12*AT12 -> 0 | AU26: =AG12*AU12 -> 0 | AV26: =AH12*AV12 -> 3180000 | AW26: =AI12*AW12 -> 3593649.1 | AX26: =AJ12*AX12 -> 4075934.4 | AY26: =AK12*AY12 -> 4639742.1 | AZ26: =AL12*AZ12 -> 5298786.4
B27: software stacks | C27: 0 | D27: =C27+_xlfn.NORM.DIST(RAND(), 0, 1, FALSE)% -> 0.0024198308 | E27: =D27+_xlfn.NORM.DIST(RAND(), 0, 1, FALSE)% -> 0.0060723954 | F27: =E27+_xlfn.NORM.DIST(RAND(), 0, 1, FALSE)% -> 0.0094848452 | G27: =F27+_xlfn.NORM.DIST(RAND(), 0, 1, FALSE)% -> 0.012746829 | H27: =G27+_xlfn.NORM.DIST(RAND(), 0, 1, FALSE)% -> 0.016731129 | I27: =H27+_xlfn.NORM.DIST(RAND(), 0, 1, FALSE)% -> 0.020660217 | J27: =I27+_xlfn.NORM.DIST(RAND(), 0, 1, FALSE)% -> 0.02315507 | K27: =J27+_xlfn.NORM.DIST(RAND(), 0, 1, FALSE)% -> 0.026722995 | L27: =K27+_xlfn.NORM.DIST(RAND(), 0, 1, FALSE)% -> 0.029294816 | P27: software stacks | Q27: =C13*Q13 + C14*Q14 -> 3610000 | R27: =D13*R13 + D14*R14 -> 3976060 | S27: =E13*S13 + E14*S14 -> 4329800.5 | T27: =F13*T13 + F14*T14 -> 4682719.4 | U27: =G13*U13 + G14*U14 -> 5040198.2 | V27: =H13*V13 + H14*V14 -> 5407698.9 | W27: =I13*W13 + I14*W14 -> 5794939.7 | X27: =J13*X13 + J14*X14 -> 6208437.2 | ... Z27: =L13*Z13 + L14*Z14 -> 7123724 | AB27: software stacks | AC27: 0 | AD27: =AC27+_xlfn.NORM.DIST(RAND(), 0, 1, FALSE)% -> 0.0039872818 | AE27: =AD27+_xlfn.NORM.DIST(RAND(), 0, 1, FALSE)% -> 0.007707716 | AF27: =AE27+_xlfn.NORM.DIST(RAND(), 0, 1, FALSE)% -> 0.011663999 | AG27: =AF27+_xlfn.NORM.DIST(RAND(), 0, 1, FALSE)% -> 0.014125205 | AH27: =AG27+_xlfn.NORM.DIST(RAND(), 0, 1, FALSE)% -> 0.017293212 | AI27: =AH27+_xlfn.NORM.DIST(RAND(), 0, 1, FALSE)% -> 0.021182789 | AJ27: =AI27+_xlfn.NORM.DIST(RAND(), 0, 1, FALSE)% -> 0.02447159 | AK27: =AJ27+_xlfn.NORM.DIST(RAND(), 0, 1, FALSE)% -> 0.028410234 | AL27: =AK27+_xlfn.NORM.DIST(RAND(), 0, 1, FALSE)% -> 0.03118732 | AP27: software stacks | AQ27: =AC13*AQ13 + AC14*AQ14 -> 0 | AR27: =AD13*AR13 + AD14*AR14 -> 0 | AS27: =AE13*AS13 + AE14*AS14 -> 0 | AT27: =AF13*AT13 + AF14*AT14 -> 3610000 | AU27: =AG13*AU13 + AG14*AU14 -> 3998191.3 | AV27: =AH13*AV13 + AH14*AV14 -> 4380740.3 | AW27: =AI13*AW13 + AI14*AW14 -> 4764006.1 | AX27: =AJ13*AX13 + AJ14*AX14 -> 5157525.4 | ... AZ27: =AL13*AZ13 + AL14*AZ14 -> 5996604.7
B28: system integration | C28: 0 | D28: =C28+_xlfn.NORM.DIST(RAND(), 0, 1, FALSE)% -> 0.0037092559 | E28: =D28+_xlfn.NORM.DIST(RAND(), 0, 1, FALSE)% -> 0.0069336124 | F28: =E28+_xlfn.NORM.DIST(RAND(), 0, 1, FALSE)% -> 0.0099849569 | G28: =F28+_xlfn.NORM.DIST(RAND(), 0, 1, FALSE)% -> 0.013853866 | H28: =G28+_xlfn.NORM.DIST(RAND(), 0, 1, FALSE)% -> 0.016382583 | I28: =H28+_xlfn.NORM.DIST(RAND(), 0, 1, FALSE)% -> 0.020025272 | J28: =I28+_xlfn.NORM.DIST(RAND(), 0, 1, FALSE)% -> 0.022627311 | K28: =J28+_xlfn.NORM.DIST(RAND(), 0, 1, FALSE)% -> 0.0262298 | L28: =K28+_xlfn.NORM.DIST(RAND(), 0, 1, FALSE)% -> 0.02915587 | P28: system integration | Q28: =C15*Q15 -> 0 | R28: =D15*R15 -> 150000 | S28: =E15*S15 -> 157481.98 | T28: =F15*T15 -> 165868.3 | U28: =G15*U15 -> 175230.62 | V28: =H15*V15 -> 185830.52 | W28: =I15*W15 -> 197563.14 | X28: =J15*X15 -> 210789.29 | ... Z28: =L15*Z15 -> 242032.63 | AB28: system integration | AC28: 0 | AD28: =AC28+_xlfn.NORM.DIST(RAND(), 0, 1, FALSE)% -> 0.0036800015 | AE28: =AD28+_xlfn.NORM.DIST(RAND(), 0, 1, FALSE)% -> 0.007211035 | AF28: =AE28+_xlfn.NORM.DIST(RAND(), 0, 1, FALSE)% -> 0.010361938 | AG28: =AF28+_xlfn.NORM.DIST(RAND(), 0, 1, FALSE)% -> 0.01373378 | AH28: =AG28+_xlfn.NORM.DIST(RAND(), 0, 1, FALSE)% -> 0.017714899 | AI28: =AH28+_xlfn.NORM.DIST(RAND(), 0, 1, FALSE)% -> 0.020458929 | AJ28: =AI28+_xlfn.NORM.DIST(RAND(), 0, 1, FALSE)% -> 0.023382202 | AK28: =AJ28+_xlfn.NORM.DIST(RAND(), 0, 1, FALSE)% -> 0.026481294 | AL28: =AK28+_xlfn.NORM.DIST(RAND(), 0, 1, FALSE)% -> 0.029919851 | AP28: system integration | AQ28: =AC15*AQ15 -> 0 | AR28: =AD15*AR15 -> 0 | AS28: =AE15*AS15 -> 0 | AT28: =AF15*AT15 -> 0 | AU28: =AG15*AU15 -> 0 | AV28: =AH15*AV15 -> 0 | AW28: =AI15*AW15 -> 0 | AX28: =AJ15*AX15 -> 0 | ... AZ28: =AL15*AZ15 -> 0
B29: liscencing | C29: 0 | D29: =C29+_xlfn.NORM.DIST(RAND(), 0, 1, FALSE)% -> 0.0035425517 | E29: =D29+_xlfn.NORM.DIST(RAND(), 0, 1, FALSE)% -> 0.0061335179 | F29: =E29+_xlfn.NORM.DIST(RAND(), 0, 1, FALSE)% -> 0.010003255 | G29: =F29+_xlfn.NORM.DIST(RAND(), 0, 1, FALSE)% -> 0.013858944 | H29: =G29+_xlfn.NORM.DIST(RAND(), 0, 1, FALSE)% -> 0.017840378 | I29: =H29+_xlfn.NORM.DIST(RAND(), 0, 1, FALSE)% -> 0.021474522 | J29: =I29+_xlfn.NORM.DIST(RAND(), 0, 1, FALSE)% -> 0.025184509 | K29: =J29+_xlfn.NORM.DIST(RAND(), 0, 1, FALSE)% -> 0.02843751 | L29: =K29+_xlfn.NORM.DIST(RAND(), 0, 1, FALSE)% -> 0.032223297 | P29: liscencing | Q29: =C16*Q16 -> 0 | R29: =D16*R16 -> 450000 | S29: =E16*S16 -> 472367.48 | T29: =F16*T16 -> 497126.93 | U29: =G16*U16 -> 525196.41 | V29: =H16*V16 -> 556968.93 | W29: =I16*W16 -> 592983.12 | X29: =J16*X16 -> 633580.14 | ... Z29: =L16*Z16 -> 730877.96 | AB29: liscencing | AC29: 0 | AD29: =AC29+_xlfn.NORM.DIST(RAND(), 0, 1, FALSE)% -> 0.0039742413 | AE29: =AD29+_xlfn.NORM.DIST(RAND(), 0, 1, FALSE)% -> 0.0068750698 | AF29: =AE29+_xlfn.NORM.DIST(RAND(), 0, 1, FALSE)% -> 0.010607381 | AG29: =AF29+_xlfn.NORM.DIST(RAND(), 0, 1, FALSE)% -> 0.014487085 | AH29: =AG29+_xlfn.NORM.DIST(RAND(), 0, 1, FALSE)% -> 0.017878542 | AI29: =AH29+_xlfn.NORM.DIST(RAND(), 0, 1, FALSE)% -> 0.021773529 | AJ29: =AI29+_xlfn.NORM.DIST(RAND(), 0, 1, FALSE)% -> 0.024667037 | AK29: =AJ29+_xlfn.NORM.DIST(RAND(), 0, 1, FALSE)% -> 0.028196955 | AL29: =AK29+_xlfn.NORM.DIST(RAND(), 0, 1, FALSE)% -> 0.032179443 | AP29: liscencing | AQ29: =AC16*AQ16 -> 0 | AR29: =AD16*AR16 -> 0 | AS29: =AE16*AS16 -> 0 | AT29: =AF16*AT16 -> 0 | AU29: =AG16*AU16 -> 450000 | AV29: =AH16*AV16 -> 474779.96 | AW29: =AI16*AW16 -> 502599.06 | AX29: =AJ16*AX16 -> 534084.11 | ... AZ29: =AL16*AZ16 -> 608604.86
B30: maintenance | C30: 0 | D30: =C30+_xlfn.NORM.DIST(RAND(), 0, 1, FALSE)% -> 0.003615403 | E30: =D30+_xlfn.NORM.DIST(RAND(), 0, 1, FALSE)% -> 0.007553114 | F30: =E30+_xlfn.NORM.DIST(RAND(), 0, 1, FALSE)% -> 0.010942514 | G30: =F30+_xlfn.NORM.DIST(RAND(), 0, 1, FALSE)% -> 0.014542801 | H30: =G30+_xlfn.NORM.DIST(RAND(), 0, 1, FALSE)% -> 0.017451798 | I30: =H30+_xlfn.NORM.DIST(RAND(), 0, 1, FALSE)% -> 0.021439668 | J30: =I30+_xlfn.NORM.DIST(RAND(), 0, 1, FALSE)% -> 0.025228041 | K30: =J30+_xlfn.NORM.DIST(RAND(), 0, 1, FALSE)% -> 0.028684432 | L30: =K30+_xlfn.NORM.DIST(RAND(), 0, 1, FALSE)% -> 0.032361687 | P30: maintenance | Q30: =C17*Q17 -> 0 | R30: =D17*R17 -> 490000 | S30: =E17*S17 -> 514393.04 | T30: =F17*T17 -> 542119.11 | U30: =G17*U17 -> 573261.61 | V30: =H17*V17 -> 608351.97 | W30: =I17*W17 -> 647441.37 | X30: =J17*X17 -> 691743.13 | ... Z30: =L17*Z17 -> 798198.42 | AB30: maintenance | AC30: 0 | AD30: =AC30+_xlfn.NORM.DIST(RAND(), 0, 1, FALSE)% -> 0.0024973773 | AE30: =AD30+_xlfn.NORM.DIST(RAND(), 0, 1, FALSE)% -> 0.0063206403 | AF30: =AE30+_xlfn.NORM.DIST(RAND(), 0, 1, FALSE)% -> 0.0088013906 | AG30: =AF30+_xlfn.NORM.DIST(RAND(), 0, 1, FALSE)% -> 0.012134989 | AH30: =AG30+_xlfn.NORM.DIST(RAND(), 0, 1, FALSE)% -> 0.014764617 | AI30: =AH30+_xlfn.NORM.DIST(RAND(), 0, 1, FALSE)% -> 0.018048964 | AJ30: =AI30+_xlfn.NORM.DIST(RAND(), 0, 1, FALSE)% -> 0.020591002 | AK30: =AJ30+_xlfn.NORM.DIST(RAND(), 0, 1, FALSE)% -> 0.023578775 | AL30: =AK30+_xlfn.NORM.DIST(RAND(), 0, 1, FALSE)% -> 0.027530613 | AP30: maintenance | AQ30: =AC17*AQ17 -> 0 | AR30: =AD17*AR17 -> 0 | AS30: =AE17*AS17 -> 0 | AT30: =AF17*AT17 -> 0 | AU30: =AG17*AU17 -> 0 | AV30: =AH17*AV17 -> 0 | AW30: =AI17*AW17 -> 0 | AX30: =AJ17*AX17 -> 0 | ... AZ30: =AL17*AZ17 -> 0
P31: TOTAL | Q31: =SUM(Q22:Q30) -> 23390000 | R31: =SUM(R22:R30) -> 32956404 | S31: =SUM(S22:S30) -> 39464314 | T31: =SUM(T22:T30) -> 43536144 | U31: =SUM(U22:U30) -> 48146376 | V31: =SUM(V22:V30) -> 53397815 | W31: =SUM(W22:W30) -> 59440040 | X31: =SUM(X22:X30) -> 66418173 | ... Z31: =SUM(Z22:Z30) -> 83843004 | AP31: TOTAL | AQ31: =SUM(AQ22:AQ30) -> 0 | AR31: =SUM(AR22:AR30) -> 0 | AS31: =SUM(AS22:AS30) -> 0 | AT31: =SUM(AT22:AT30) -> 23390000 | AU31: =SUM(AU22:AU30) -> 31941483 | AV31: =SUM(AV22:AV30) -> 37999423 | AW31: =SUM(AW22:AW30) -> 41624796 | AX31: =SUM(AX22:AX30) -> 45708354 | ... AZ31: =SUM(AZ22:AZ30) -> 55583463
B33: CPI | C33: =Assumptions!J16 -> 0.02 | D33: =Assumptions!K16 -> 0.02 | E33: =Assumptions!L16 -> 0.02 | F33: =Assumptions!M16 -> 0.02 | G33: =Assumptions!N16 -> 0.02 | H33: =Assumptions!O16 -> 0.02 | I33: =Assumptions!P16 -> 0.02 | J33: =Assumptions!Q16 -> 0.02 | ... L33: =Assumptions!S16 -> 0.02 | AB33: CPI | AC33: =Assumptions!J18 -> 0.032 | AD33: =Assumptions!K18 -> 0.032 | AE33: =Assumptions!L18 -> 0.032 | AF33: =Assumptions!M18 -> 0.032 | AG33: =Assumptions!N18 -> 0.032 | AH33: =Assumptions!O18 -> 0.032 | AI33: =Assumptions!P18 -> 0.032 | AJ33: =Assumptions!Q18 -> 0.032 | ... AL33: =Assumptions!S18 -> 0.032
C36: Year | Q36: Year | AC36: Year | AQ36: Year
B37: SELLING PRICE | C37: 1 | D37: 2 | E37: 3 | F37: 4 | G37: 5 | H37: 6 | I37: 7 | J37: 8 | K37: 9 | L37: 10 | P37: UNITS SOLD | Q37: 1 | R37: 2 | S37: 3 | T37: 4 | U37: 5 | V37: 6 | W37: 7 | X37: 8 | Y37: 9 | Z37: 10 | AB37: SELLING PRICE | AC37: 1 | AD37: 2 | AE37: 3 | AF37: 4 | AG37: 5 | AH37: 6 | AI37: 7 | AJ37: 8 | AK37: 9 | AL37: 10 | AP37: UNITS SOLD | AQ37: 1 | AR37: 2 | AS37: 3 | AT37: 4 | AU37: 5 | AV37: 6 | AW37: 7 | AX37: 8 | AY37: 9 | AZ37: 10
B38: Drone | C38: =IF(C37=Assumptions!$G$45, Assumptions!$P$45, 0) -> 0 | D38: =IF(D37>Assumptions!$G$45, C38*(1+C33), IF(D37=Assumptions!$G$45, Assumptions!$P$45, 0)) -> 0 | E38: =IF(E37>Assumptions!$G$45, D38*(1+D33), IF(E37=Assumptions!$G$45, Assumptions!$P$45, 0)) -> 0 | F38: =IF(F37>Assumptions!$G$45, E38*(1+E33), IF(F37=Assumptions!$G$45, Assumptions!$P$45, 0)) -> 5000 | G38: =IF(G37>Assumptions!$G$45, F38*(1+F33), IF(G37=Assumptions!$G$45, Assumptions!$P$45, 0)) -> 5100 | H38: =IF(H37>Assumptions!$G$45, G38*(1+G33), IF(H37=Assumptions!$G$45, Assumptions!$P$45, 0)) -> 5202 | I38: =IF(I37>Assumptions!$G$45, H38*(1+H33), IF(I37=Assumptions!$G$45, Assumptions!$P$45, 0)) -> 5306.04 | J38: =IF(J37>Assumptions!$G$45, I38*(1+I33), IF(J37=Assumptions!$G$45, Assumptions!$P$45, 0)) -> 5412.1608 | K38: =IF(K37>Assumptions!$G$45, J38*(1+J33), IF(K37=Assumptions!$G$45, Assumptions!$P$45, 0)) -> 5520.404 | L38: =IF(L37>Assumptions!$G$45, K38*(1+K33), IF(L37=Assumptions!$G$45, Assumptions!$P$45, 0)) -> 5630.8121 | P38: Drone | Q38: =IF(Q37=Assumptions!$G$45, Assumptions!$D$45, 0) -> 0 | R38: =IF(R37>Assumptions!$G$45, Q38*(1+C52), IF(R37=Assumptions!$G$45, Assumptions!$D$45, 0)) -> 0 | S38: =IF(S37>Assumptions!$G$45, R38*(1+D52), IF(S37=Assumptions!$G$45, Assumptions!$D$45, 0)) -> 0 | T38: =IF(T37>Assumptions!$G$45, S38*(1+E52), IF(T37=Assumptions!$G$45, Assumptions!$D$45, 0)) -> 1540 | U38: =IF(U37>Assumptions!$G$45, T38*(1+F52), IF(U37=Assumptions!$G$45, Assumptions!$D$45, 0)) -> 1617.3792 | V38: =IF(V37>Assumptions!$G$45, U38*(1+G52), IF(V37=Assumptions!$G$45, Assumptions!$D$45, 0)) -> 1703.2302 | W38: =IF(W37>Assumptions!$G$45, V38*(1+H52), IF(W37=Assumptions!$G$45, Assumptions!$D$45, 0)) -> 1798.8961 | X38: =IF(X37>Assumptions!$G$45, W38*(1+I52), IF(X37=Assumptions!$G$45, Assumptions!$D$45, 0)) -> 1907.0243 | Y38: =IF(Y37>Assumptions!$G$45, X38*(1+J52), IF(Y37=Assumptions!$G$45, Assumptions!$D$45, 0)) -> 2028.5331 | Z38: =IF(Z37>Assumptions!$G$45, Y38*(1+K52), IF(Z37=Assumptions!$G$45, Assumptions!$D$45, 0)) -> 2164.953 | AB38: Drone | AC38: =IF(AC37=Assumptions!$J$45, Assumptions!$P$45, 0) -> 0 | AD38: =IF(AD37>Assumptions!$J$45, AC38*(1+AC33), IF(AD37=Assumptions!$J$45, Assumptions!$P$45, 0)) -> 0 | AE38: =IF(AE37>Assumptions!$J$45, AD38*(1+AD33), IF(AE37=Assumptions!$J$45, Assumptions!$P$45, 0)) -> 0 | AF38: =IF(AF37>Assumptions!$J$45, AE38*(1+AE33), IF(AF37=Assumptions!$J$45, Assumptions!$P$45, 0)) -> 5000 | AG38: =IF(AG37>Assumptions!$J$45, AF38*(1+AF33), IF(AG37=Assumptions!$J$45, Assumptions!$P$45, 0)) -> 5160 | AH38: =IF(AH37>Assumptions!$J$45, AG38*(1+AG33), IF(AH37=Assumptions!$J$45, Assumptions!$P$45, 0)) -> 5325.12 | AI38: =IF(AI37>Assumptions!$J$45, AH38*(1+AH33), IF(AI37=Assumptions!$J$45, Assumptions!$P$45, 0)) -> 5495.5238 | AJ38: =IF(AJ37>Assumptions!$J$45, AI38*(1+AI33), IF(AJ37=Assumptions!$J$45, Assumptions!$P$45, 0)) -> 5671.3806 | AK38: =IF(AK37>Assumptions!$J$45, AJ38*(1+AJ33), IF(AK37=Assumptions!$J$45, Assumptions!$P$45, 0)) -> 5852.8648 | AL38: =IF(AL37>Assumptions!$J$45, AK38*(1+AK33), IF(AL37=Assumptions!$J$45, Assumptions!$P$45, 0)) -> 6040.1565 | AP38: Drone | AQ38: =IF(AQ37=Assumptions!$J$45, Assumptions!$D$45, 0) -> 0 | AR38: =IF(AR37>Assumptions!$J$45, AQ38*(1+AC52), IF(AR37=Assumptions!$J$45, Assumptions!$D$45, 0)) -> 0 | AS38: =IF(AS37>Assumptions!$J$45, AR38*(1+AD52), IF(AS37=Assumptions!$J$45, Assumptions!$D$45, 0)) -> 0 | AT38: =IF(AT37>Assumptions!$J$45, AS38*(1+AE52), IF(AT37=Assumptions!$J$45, Assumptions!$D$45, 0)) -> 1540 | AU38: =IF(AU37>Assumptions!$J$45, AT38*(1+AF52), IF(AU37=Assumptions!$J$45, Assumptions!$D$45, 0)) -> 1602.0537 | AV38: =IF(AV37>Assumptions!$J$45, AU38*(1+AG52), IF(AV37=Assumptions!$J$45, Assumptions!$D$45, 0)) -> 1670.895 | AW38: =IF(AW37>Assumptions!$J$45, AV38*(1+AH52), IF(AW37=Assumptions!$J$45, Assumptions!$D$45, 0)) -> 1748.6039 | AX38: =IF(AX37>Assumptions!$J$45, AW38*(1+AI52), IF(AX37=Assumptions!$J$45, Assumptions!$D$45, 0)) -> 1836.7465 | AY38: =IF(AY37>Assumptions!$J$45, AX38*(1+AJ52), IF(AY37=Assumptions!$J$45, Assumptions!$D$45, 0)) -> 1935.3659 | AZ38: =IF(AZ37>Assumptions!$J$45, AY38*(1+AK52), IF(AZ37=Assumptions!$J$45, Assumptions!$D$45, 0)) -> 2044.652
B39: Rover | C39: =IF(C37=Assumptions!$G$46, Assumptions!$P$46, 0) -> 0 | D39: =IF(D37>Assumptions!$G$46, C39*(1+C33), IF(D37=Assumptions!$G$46, Assumptions!$P$46, 0)) -> 0 | E39: =IF(E37>Assumptions!$G$46, D39*(1+D33), IF(E37=Assumptions!$G$46, Assumptions!$P$46, 0)) -> 0 | F39: =IF(F37>Assumptions!$G$46, E39*(1+E33), IF(F37=Assumptions!$G$46, Assumptions!$P$46, 0)) -> 7000 | G39: =IF(G37>Assumptions!$G$46, F39*(1+F33), IF(G37=Assumptions!$G$46, Assumptions!$P$46, 0)) -> 7140 | H39: =IF(H37>Assumptions!$G$46, G39*(1+G33), IF(H37=Assumptions!$G$46, Assumptions!$P$46, 0)) -> 7282.8 | I39: =IF(I37>Assumptions!$G$46, H39*(1+H33), IF(I37=Assumptions!$G$46, Assumptions!$P$46, 0)) -> 7428.456 | J39: =IF(J37>Assumptions!$G$46, I39*(1+I33), IF(J37=Assumptions!$G$46, Assumptions!$P$46, 0)) -> 7577.0251 | K39: =IF(K37>Assumptions!$G$46, J39*(1+J33), IF(K37=Assumptions!$G$46, Assumptions!$P$46, 0)) -> 7728.5656 | L39: =IF(L37>Assumptions!$G$46, K39*(1+K33), IF(L37=Assumptions!$G$46, Assumptions!$P$46, 0)) -> 7883.1369 | P39: Rover | Q39: =IF(Q37=Assumptions!$G$46, Assumptions!$D$46, 0) -> 0 | R39: =IF(R37>Assumptions!$G$46, Q39*(1+C53), IF(R37=Assumptions!$G$46, Assumptions!$D$46, 0)) -> 0 | S39: =IF(S37>Assumptions!$G$46, R39*(1+D53), IF(S37=Assumptions!$G$46, Assumptions!$D$46, 0)) -> 0 | T39: =IF(T37>Assumptions!$G$46, S39*(1+E53), IF(T37=Assumptions!$G$46, Assumptions!$D$46, 0)) -> 1000 | U39: =IF(U37>Assumptions!$G$46, T39*(1+F53), IF(U37=Assumptions!$G$46, Assumptions!$D$46, 0)) -> 1041.1037 | V39: =IF(V37>Assumptions!$G$46, U39*(1+G53), IF(V37=Assumptions!$G$46, Assumptions!$D$46, 0)) -> 1087.9864 | W39: =IF(W37>Assumptions!$G$46, V39*(1+H53), IF(W37=Assumptions!$G$46, Assumptions!$D$46, 0)) -> 1139.9115 | X39: =IF(X37>Assumptions!$G$46, W39*(1+I53), IF(X37=Assumptions!$G$46, Assumptions!$D$46, 0)) -> 1198.5641 | Y39: =IF(Y37>Assumptions!$G$46, X39*(1+J53), IF(Y37=Assumptions!$G$46, Assumptions!$D$46, 0)) -> 1264.2585 | Z39: =IF(Z37>Assumptions!$G$46, Y39*(1+K53), IF(Z37=Assumptions!$G$46, Assumptions!$D$46, 0)) -> 1338.1205 | AB39: Rover | AC39: =IF(AC37=Assumptions!$J$46, Assumptions!$P$46, 0) -> 0 | AD39: =IF(AD37>Assumptions!$J$46, AC39*(1+AC33), IF(AD37=Assumptions!$J$46, Assumptions!$P$46, 0)) -> 0 | AE39: =IF(AE37>Assumptions!$J$46, AD39*(1+AD33), IF(AE37=Assumptions!$J$46, Assumptions!$P$46, 0)) -> 0 | AF39: =IF(AF37>Assumptions!$J$46, AE39*(1+AE33), IF(AF37=Assumptions!$J$46, Assumptions!$P$46, 0)) -> 7000 | AG39: =IF(AG37>Assumptions!$J$46, AF39*(1+AF33), IF(AG37=Assumptions!$J$46, Assumptions!$P$46, 0)) -> 7224 | AH39: =IF(AH37>Assumptions!$J$46, AG39*(1+AG33), IF(AH37=Assumptions!$J$46, Assumptions!$P$46, 0)) -> 7455.168 | AI39: =IF(AI37>Assumptions!$J$46, AH39*(1+AH33), IF(AI37=Assumptions!$J$46, Assumptions!$P$46, 0)) -> 7693.7334 | AJ39: =IF(AJ37>Assumptions!$J$46, AI39*(1+AI33), IF(AJ37=Assumptions!$J$46, Assumptions!$P$46, 0)) -> 7939.9328 | AK39: =IF(AK37>Assumptions!$J$46, AJ39*(1+AJ33), IF(AK37=Assumptions!$J$46, Assumptions!$P$46, 0)) -> 8194.0107 | AL39: =IF(AL37>Assumptions!$J$46, AK39*(1+AK33), IF(AL37=Assumptions!$J$46, Assumptions!$P$46, 0)) -> 8456.219 | AP39: Rover | AQ39: =IF(AQ37=Assumptions!$J$46, Assumptions!$D$46, 0) -> 0 | AR39: =IF(AR37>Assumptions!$J$46, AQ39*(1+AC53), IF(AR37=Assumptions!$J$46, Assumptions!$D$46, 0)) -> 0 | AS39: =IF(AS37>Assumptions!$J$46, AR39*(1+AD53), IF(AS37=Assumptions!$J$46, Assumptions!$D$46, 0)) -> 0 | AT39: =IF(AT37>Assumptions!$J$46, AS39*(1+AE53), IF(AT37=Assumptions!$J$46, Assumptions!$D$46, 0)) -> 1000 | AU39: =IF(AU37>Assumptions!$J$46, AT39*(1+AF53), IF(AU37=Assumptions!$J$46, Assumptions!$D$46, 0)) -> 1061.6594 | AV39: =IF(AV37>Assumptions!$J$46, AU39*(1+AG53), IF(AV37=Assumptions!$J$46, Assumptions!$D$46, 0)) -> 1131.352 | AW39: =IF(AW37>Assumptions!$J$46, AV39*(1+AH53), IF(AW37=Assumptions!$J$46, Assumptions!$D$46, 0)) -> 1209.3587 | AX39: =IF(AX37>Assumptions!$J$46, AW39*(1+AI53), IF(AX37=Assumptions!$J$46, Assumptions!$D$46, 0)) -> 1296.4666 | AY39: =IF(AY37>Assumptions!$J$46, AX39*(1+AJ53), IF(AY37=Assumptions!$J$46, Assumptions!$D$46, 0)) -> 1394.3736 | AZ39: =IF(AZ37>Assumptions!$J$46, AY39*(1+AK53), IF(AZ37=Assumptions!$J$46, Assumptions!$D$46, 0)) -> 1505.1874
B40: Edge | C40: =IF(C37=Assumptions!$G$47, Assumptions!$P$47, 0) -> 0 | D40: =IF(D37>Assumptions!$G$47, C40*(1+C33), IF(D37=Assumptions!$G$47, Assumptions!$P$45, 0)) -> 0 | E40: =IF(E37>Assumptions!$G$47, D40*(1+D33), IF(E37=Assumptions!$G$47, Assumptions!$P$45, 0)) -> 0 | F40: =IF(F37>Assumptions!$G$47, E40*(1+E33), IF(F37=Assumptions!$G$47, Assumptions!$P$45, 0)) -> 5000 | G40: =IF(G37>Assumptions!$G$47, F40*(1+F33), IF(G37=Assumptions!$G$47, Assumptions!$P$45, 0)) -> 5100 | H40: =IF(H37>Assumptions!$G$47, G40*(1+G33), IF(H37=Assumptions!$G$47, Assumptions!$P$45, 0)) -> 5202 | I40: =IF(I37>Assumptions!$G$47, H40*(1+H33), IF(I37=Assumptions!$G$47, Assumptions!$P$45, 0)) -> 5306.04 | J40: =IF(J37>Assumptions!$G$47, I40*(1+I33), IF(J37=Assumptions!$G$47, Assumptions!$P$45, 0)) -> 5412.1608 | K40: =IF(K37>Assumptions!$G$47, J40*(1+J33), IF(K37=Assumptions!$G$47, Assumptions!$P$45, 0)) -> 5520.404 | L40: =IF(L37>Assumptions!$G$47, K40*(1+K33), IF(L37=Assumptions!$G$47, Assumptions!$P$45, 0)) -> 5630.8121 | P40: Edge | Q40: =IF(Q37=Assumptions!$G$47, Assumptions!$D$47, 0) -> 0 | R40: =IF(R37>Assumptions!$G$47, Q40*(1+C54), IF(R37=Assumptions!$G$47, Assumptions!$D$47, 0)) -> 0 | S40: =IF(S37>Assumptions!$G$47, R40*(1+D54), IF(S37=Assumptions!$G$47, Assumptions!$D$47, 0)) -> 0 | T40: =IF(T37>Assumptions!$G$47, S40*(1+E54), IF(T37=Assumptions!$G$47, Assumptions!$D$47, 0)) -> 1270 | U40: =IF(U37>Assumptions!$G$47, T40*(1+F54), IF(U37=Assumptions!$G$47, Assumptions!$D$47, 0)) -> 1347.7154 | V40: =IF(V37>Assumptions!$G$47, U40*(1+G54), IF(V37=Assumptions!$G$47, Assumptions!$D$47, 0)) -> 1435.1174 | W40: =IF(W37>Assumptions!$G$47, V40*(1+H54), IF(W37=Assumptions!$G$47, Assumptions!$D$47, 0)) -> 1532.6503 | X40: =IF(X37>Assumptions!$G$47, W40*(1+I54), IF(X37=Assumptions!$G$47, Assumptions!$D$47, 0)) -> 1642.7965 | Y40: =IF(Y37>Assumptions!$G$47, X40*(1+J54), IF(Y37=Assumptions!$G$47, Assumptions!$D$47, 0)) -> 1766.3292 | Z40: =IF(Z37>Assumptions!$G$47, Y40*(1+K54), IF(Z37=Assumptions!$G$47, Assumptions!$D$47, 0)) -> 1904.7381 | AB40: Edge | AC40: =IF(AC37=Assumptions!$J$47, Assumptions!$P$47, 0) -> 0 | AD40: =IF(AD37>Assumptions!$J$47, AC40*(1+AC33), IF(AD37=Assumptions!$J$47, Assumptions!$P$45, 0)) -> 0 | AE40: =IF(AE37>Assumptions!$J$47, AD40*(1+AD33), IF(AE37=Assumptions!$J$47, Assumptions!$P$45, 0)) -> 0 | AF40: =IF(AF37>Assumptions!$J$47, AE40*(1+AE33), IF(AF37=Assumptions!$J$47, Assumptions!$P$45, 0)) -> 5000 | AG40: =IF(AG37>Assumptions!$J$47, AF40*(1+AF33), IF(AG37=Assumptions!$J$47, Assumptions!$P$45, 0)) -> 5160 | AH40: =IF(AH37>Assumptions!$J$47, AG40*(1+AG33), IF(AH37=Assumptions!$J$47, Assumptions!$P$45, 0)) -> 5325.12 | AI40: =IF(AI37>Assumptions!$J$47, AH40*(1+AH33), IF(AI37=Assumptions!$J$47, Assumptions!$P$45, 0)) -> 5495.5238 | AJ40: =IF(AJ37>Assumptions!$J$47, AI40*(1+AI33), IF(AJ37=Assumptions!$J$47, Assumptions!$P$45, 0)) -> 5671.3806 | AK40: =IF(AK37>Assumptions!$J$47, AJ40*(1+AJ33), IF(AK37=Assumptions!$J$47, Assumptions!$P$45, 0)) -> 5852.8648 | AL40: =IF(AL37>Assumptions!$J$47, AK40*(1+AK33), IF(AL37=Assumptions!$J$47, Assumptions!$P$45, 0)) -> 6040.1565 | AP40: Edge | AQ40: =IF(AQ37=Assumptions!$J$47, Assumptions!$D$47, 0) -> 0 | AR40: =IF(AR37>Assumptions!$J$47, AQ40*(1+AC54), IF(AR37=Assumptions!$J$47, Assumptions!$D$47, 0)) -> 0 | AS40: =IF(AS37>Assumptions!$J$47, AR40*(1+AD54), IF(AS37=Assumptions!$J$47, Assumptions!$D$47, 0)) -> 0 | AT40: =IF(AT37>Assumptions!$J$47, AS40*(1+AE54), IF(AT37=Assumptions!$J$47, Assumptions!$D$47, 0)) -> 1270 | AU40: =IF(AU37>Assumptions!$J$47, AT40*(1+AF54), IF(AU37=Assumptions!$J$47, Assumptions!$D$47, 0)) -> 1320.7385 | AV40: =IF(AV37>Assumptions!$J$47, AU40*(1+AG54), IF(AV37=Assumptions!$J$47, Assumptions!$D$47, 0)) -> 1377.1927 | AW40: =IF(AW37>Assumptions!$J$47, AV40*(1+AH54), IF(AW37=Assumptions!$J$47, Assumptions!$D$47, 0)) -> 1441.4779 | AX40: =IF(AX37>Assumptions!$J$47, AW40*(1+AI54), IF(AX37=Assumptions!$J$47, Assumptions!$D$47, 0)) -> 1514.3148 | AY40: =IF(AY37>Assumptions!$J$47, AX40*(1+AJ54), IF(AY37=Assumptions!$J$47, Assumptions!$D$47, 0)) -> 1596.8527 | AZ40: =IF(AZ37>Assumptions!$J$47, AY40*(1+AK54), IF(AZ37=Assumptions!$J$47, Assumptions!$D$47, 0)) -> 1690.2571
B41: Fog | C41: =IF(C37=Assumptions!$G$48, Assumptions!$P$48, 0) -> 0 | D41: =IF(D37>Assumptions!$G$48, C41*(1+C33), IF(D37=Assumptions!$G$48, Assumptions!$P$48, 0)) -> 0 | E41: =IF(E37>Assumptions!$G$48, D41*(1+D33), IF(E37=Assumptions!$G$48, Assumptions!$P$48, 0)) -> 0 | F41: =IF(F37>Assumptions!$G$48, E41*(1+E33), IF(F37=Assumptions!$G$48, Assumptions!$P$48, 0)) -> 0 | G41: =IF(G37>Assumptions!$G$48, F41*(1+F33), IF(G37=Assumptions!$G$48, Assumptions!$P$48, 0)) -> 9500 | H41: =IF(H37>Assumptions!$G$48, G41*(1+G33), IF(H37=Assumptions!$G$48, Assumptions!$P$48, 0)) -> 9690 | I41: =IF(I37>Assumptions!$G$48, H41*(1+H33), IF(I37=Assumptions!$G$48, Assumptions!$P$48, 0)) -> 9883.8 | J41: =IF(J37>Assumptions!$G$48, I41*(1+I33), IF(J37=Assumptions!$G$48, Assumptions!$P$48, 0)) -> 10081.476 | K41: =IF(K37>Assumptions!$G$48, J41*(1+J33), IF(K37=Assumptions!$G$48, Assumptions!$P$48, 0)) -> 10283.106 | L41: =IF(L37>Assumptions!$G$48, K41*(1+K33), IF(L37=Assumptions!$G$48, Assumptions!$P$48, 0)) -> 10488.768 | P41: Fog | Q41: =IF(Q37=Assumptions!$G$48, Assumptions!$D$48, 0) -> 0 | R41: =IF(R37>Assumptions!$G$48, Q41*(1+C55), IF(R37=Assumptions!$G$48, Assumptions!$D$48, 0)) -> 0 | S41: =IF(S37>Assumptions!$G$48, R41*(1+D55), IF(S37=Assumptions!$G$48, Assumptions!$D$48, 0)) -> 0 | T41: =IF(T37>Assumptions!$G$48, S41*(1+E55), IF(T37=Assumptions!$G$48, Assumptions!$D$48, 0)) -> 0 | U41: =IF(U37>Assumptions!$G$48, T41*(1+F55), IF(U37=Assumptions!$G$48, Assumptions!$D$48, 0)) -> 635 | V41: =IF(V37>Assumptions!$G$48, U41*(1+G55), IF(V37=Assumptions!$G$48, Assumptions!$D$48, 0)) -> 674.82606 | W41: =IF(W37>Assumptions!$G$48, V41*(1+H55), IF(W37=Assumptions!$G$48, Assumptions!$D$48, 0)) -> 719.77278 | X41: =IF(X37>Assumptions!$G$48, W41*(1+I55), IF(X37=Assumptions!$G$48, Assumptions!$D$48, 0)) -> 769.96231 | Y41: =IF(Y37>Assumptions!$G$48, X41*(1+J55), IF(Y37=Assumptions!$G$48, Assumptions!$D$48, 0)) -> 826.11777 | Z41: =IF(Z37>Assumptions!$G$48, Y41*(1+K55), IF(Z37=Assumptions!$G$48, Assumptions!$D$48, 0)) -> 889.02565 | AB41: Fog | AC41: =IF(AC37=Assumptions!$J$48, Assumptions!$P$48, 0) -> 0 | AD41: =IF(AD37>Assumptions!$J$48, AC41*(1+AC33), IF(AD37=Assumptions!$J$48, Assumptions!$P$48, 0)) -> 0 | AE41: =IF(AE37>Assumptions!$J$48, AD41*(1+AD33), IF(AE37=Assumptions!$J$48, Assumptions!$P$48, 0)) -> 0 | AF41: =IF(AF37>Assumptions!$J$48, AE41*(1+AE33), IF(AF37=Assumptions!$J$48, Assumptions!$P$48, 0)) -> 0 | AG41: =IF(AG37>Assumptions!$J$48, AF41*(1+AF33), IF(AG37=Assumptions!$J$48, Assumptions!$P$48, 0)) -> 9500 | AH41: =IF(AH37>Assumptions!$J$48, AG41*(1+AG33), IF(AH37=Assumptions!$J$48, Assumptions!$P$48, 0)) -> 9804 | AI41: =IF(AI37>Assumptions!$J$48, AH41*(1+AH33), IF(AI37=Assumptions!$J$48, Assumptions!$P$48, 0)) -> 10117.728 | AJ41: =IF(AJ37>Assumptions!$J$48, AI41*(1+AI33), IF(AJ37=Assumptions!$J$48, Assumptions!$P$48, 0)) -> 10441.495 | AK41: =IF(AK37>Assumptions!$J$48, AJ41*(1+AJ33), IF(AK37=Assumptions!$J$48, Assumptions!$P$48, 0)) -> 10775.623 | AL41: =IF(AL37>Assumptions!$J$48, AK41*(1+AK33), IF(AL37=Assumptions!$J$48, Assumptions!$P$48, 0)) -> 11120.443 | AP41: Fog | AQ41: =IF(AQ37=Assumptions!$J$48, Assumptions!$D$48, 0) -> 0 | AR41: =IF(AR37>Assumptions!$J$48, AQ41*(1+AC55), IF(AR37=Assumptions!$J$48, Assumptions!$D$48, 0)) -> 0 | AS41: =IF(AS37>Assumptions!$J$48, AR41*(1+AD55), IF(AS37=Assumptions!$J$48, Assumptions!$D$48, 0)) -> 0 | AT41: =IF(AT37>Assumptions!$J$48, AS41*(1+AE55), IF(AT37=Assumptions!$J$48, Assumptions!$D$48, 0)) -> 0 | AU41: =IF(AU37>Assumptions!$J$48, AT41*(1+AF55), IF(AU37=Assumptions!$J$48, Assumptions!$D$48, 0)) -> 635 | AV41: =IF(AV37>Assumptions!$J$48, AU41*(1+AG55), IF(AV37=Assumptions!$J$48, Assumptions!$D$48, 0)) -> 668.93156 | AW41: =IF(AW37>Assumptions!$J$48, AV41*(1+AH55), IF(AW37=Assumptions!$J$48, Assumptions!$D$48, 0)) -> 707.32804 | AX41: =IF(AX37>Assumptions!$J$48, AW41*(1+AI55), IF(AX37=Assumptions!$J$48, Assumptions!$D$48, 0)) -> 750.7057 | AY41: =IF(AY37>Assumptions!$J$48, AX41*(1+AJ55), IF(AY37=Assumptions!$J$48, Assumptions!$D$48, 0)) -> 798.70595 | AZ41: =IF(AZ37>Assumptions!$J$48, AY41*(1+AK55), IF(AZ37=Assumptions!$J$48, Assumptions!$D$48, 0)) -> 852.73248
B42: Enterprise | C42: =IF(C37=Assumptions!$G$49, Assumptions!$P$49, 0) -> 0 | D42: =IF(D37>Assumptions!$G$49, C42*(1+C33), IF(D37=Assumptions!$G$49, Assumptions!$P$49, 0)) -> 0 | E42: =IF(E37>Assumptions!$G$49, D42*(1+D33), IF(E37=Assumptions!$G$49, Assumptions!$P$49, 0)) -> 0 | F42: =IF(F37>Assumptions!$G$49, E42*(1+E33), IF(F37=Assumptions!$G$49, Assumptions!$P$49, 0)) -> 0 | G42: =IF(G37>Assumptions!$G$49, F42*(1+F33), IF(G37=Assumptions!$G$49, Assumptions!$P$49, 0)) -> 0 | H42: =IF(H37>Assumptions!$G$49, G42*(1+G33), IF(H37=Assumptions!$G$49, Assumptions!$P$49, 0)) -> 10000 | I42: =IF(I37>Assumptions!$G$49, H42*(1+H33), IF(I37=Assumptions!$G$49, Assumptions!$P$49, 0)) -> 10200 | J42: =IF(J37>Assumptions!$G$49, I42*(1+I33), IF(J37=Assumptions!$G$49, Assumptions!$P$49, 0)) -> 10404 | K42: =IF(K37>Assumptions!$G$49, J42*(1+J33), IF(K37=Assumptions!$G$49, Assumptions!$P$49, 0)) -> 10612.08 | L42: =IF(L37>Assumptions!$G$49, K42*(1+K33), IF(L37=Assumptions!$G$49, Assumptions!$P$49, 0)) -> 10824.322 | P42: Enterprise | Q42: =IF(Q37=Assumptions!$G$49, Assumptions!$D$49, 0) -> 0 | R42: =IF(R37>Assumptions!$G$49, Q42*(1+C56), IF(R37=Assumptions!$G$49, Assumptions!$D$49, 0)) -> 0 | S42: =IF(S37>Assumptions!$G$49, R42*(1+D56), IF(S37=Assumptions!$G$49, Assumptions!$D$49, 0)) -> 0 | T42: =IF(T37>Assumptions!$G$49, S42*(1+E56), IF(T37=Assumptions!$G$49, Assumptions!$D$49, 0)) -> 0 | U42: =IF(U37>Assumptions!$G$49, T42*(1+F56), IF(U37=Assumptions!$G$49, Assumptions!$D$49, 0)) -> 0 | V42: =IF(V37>Assumptions!$G$49, U42*(1+G56), IF(V37=Assumptions!$G$49, Assumptions!$D$49, 0)) -> 318 | W42: =IF(W37>Assumptions!$G$49, V42*(1+H56), IF(W37=Assumptions!$G$49, Assumptions!$D$49, 0)) -> 336.00794 | X42: =IF(X37>Assumptions!$G$49, W42*(1+I56), IF(X37=Assumptions!$G$49, Assumptions!$D$49, 0)) -> 356.37471 | Y42: =IF(Y37>Assumptions!$G$49, X42*(1+J56), IF(Y37=Assumptions!$G$49, Assumptions!$D$49, 0)) -> 379.0636 | Z42: =IF(Z37>Assumptions!$G$49, Y42*(1+K56), IF(Z37=Assumptions!$G$49, Assumptions!$D$49, 0)) -> 404.70847 | AB42: Enterprise | AC42: =IF(AC37=Assumptions!$J$49, Assumptions!$P$49, 0) -> 0 | AD42: =IF(AD37>Assumptions!$J$49, AC42*(1+AC33), IF(AD37=Assumptions!$J$49, Assumptions!$P$49, 0)) -> 0 | AE42: =IF(AE37>Assumptions!$J$49, AD42*(1+AD33), IF(AE37=Assumptions!$J$49, Assumptions!$P$49, 0)) -> 0 | AF42: =IF(AF37>Assumptions!$J$49, AE42*(1+AE33), IF(AF37=Assumptions!$J$49, Assumptions!$P$49, 0)) -> 0 | AG42: =IF(AG37>Assumptions!$J$49, AF42*(1+AF33), IF(AG37=Assumptions!$J$49, Assumptions!$P$49, 0)) -> 0 | AH42: =IF(AH37>Assumptions!$J$49, AG42*(1+AG33), IF(AH37=Assumptions!$J$49, Assumptions!$P$49, 0)) -> 10000 | AI42: =IF(AI37>Assumptions!$J$49, AH42*(1+AH33), IF(AI37=Assumptions!$J$49, Assumptions!$P$49, 0)) -> 10320 | AJ42: =IF(AJ37>Assumptions!$J$49, AI42*(1+AI33), IF(AJ37=Assumptions!$J$49, Assumptions!$P$49, 0)) -> 10650.24 | AK42: =IF(AK37>Assumptions!$J$49, AJ42*(1+AJ33), IF(AK37=Assumptions!$J$49, Assumptions!$P$49, 0)) -> 10991.048 | AL42: =IF(AL37>Assumptions!$J$49, AK42*(1+AK33), IF(AL37=Assumptions!$J$49, Assumptions!$P$49, 0)) -> 11342.761 | AP42: Enterprise | AQ42: =IF(AQ37=Assumptions!$J$49, Assumptions!$D$49, 0) -> 0 | AR42: =IF(AR37>Assumptions!$J$49, AQ42*(1+AC56), IF(AR37=Assumptions!$J$49, Assumptions!$D$49, 0)) -> 0 | AS42: =IF(AS37>Assumptions!$J$49, AR42*(1+AD56), IF(AS37=Assumptions!$J$49, Assumptions!$D$49, 0)) -> 0 | AT42: =IF(AT37>Assumptions!$J$49, AS42*(1+AE56), IF(AT37=Assumptions!$J$49, Assumptions!$D$49, 0)) -> 0 | AU42: =IF(AU37>Assumptions!$J$49, AT42*(1+AF56), IF(AU37=Assumptions!$J$49, Assumptions!$D$49, 0)) -> 0 | AV42: =IF(AV37>Assumptions!$J$49, AU42*(1+AG56), IF(AV37=Assumptions!$J$49, Assumptions!$D$49, 0)) -> 318 | AW42: =IF(AW37>Assumptions!$J$49, AV42*(1+AH56), IF(AW37=Assumptions!$J$49, Assumptions!$D$49, 0)) -> 346.18272 | AX42: =IF(AX37>Assumptions!$J$49, AW42*(1+AI56), IF(AX37=Assumptions!$J$49, Assumptions!$D$49, 0)) -> 378.22907 | AY42: =IF(AY37>Assumptions!$J$49, AX42*(1+AJ56), IF(AY37=Assumptions!$J$49, Assumptions!$D$49, 0)) -> 414.41467 | AZ42: =IF(AZ37>Assumptions!$J$49, AY42*(1+AK56), IF(AZ37=Assumptions!$J$49, Assumptions!$D$49, 0)) -> 455.55001
B43: software stacks (one time) | C43: =IF(C37=Assumptions!$G$50, Assumptions!$P$50, 0) -> 0 | D43: =IF(D37>Assumptions!$G$50, C43*(1+C33), IF(D37=Assumptions!$G$50, Assumptions!$P$50, 0)) -> 0 | E43: =IF(E37>Assumptions!$G$50, D43*(1+D33), IF(E37=Assumptions!$G$50, Assumptions!$P$50, 0)) -> 0 | F43: =IF(F37>Assumptions!$G$50, E43*(1+E33), IF(F37=Assumptions!$G$50, Assumptions!$P$50, 0)) -> 1900 | G43: =IF(G37>Assumptions!$G$50, F43*(1+F33), IF(G37=Assumptions!$G$50, Assumptions!$P$50, 0)) -> 1938 | H43: =IF(H37>Assumptions!$G$50, G43*(1+G33), IF(H37=Assumptions!$G$50, Assumptions!$P$50, 0)) -> 1976.76 | I43: =IF(I37>Assumptions!$G$50, H43*(1+H33), IF(I37=Assumptions!$G$50, Assumptions!$P$50, 0)) -> 2016.2952 | J43: =IF(J37>Assumptions!$G$50, I43*(1+I33), IF(J37=Assumptions!$G$50, Assumptions!$P$50, 0)) -> 2056.6211 | K43: =IF(K37>Assumptions!$G$50, J43*(1+J33), IF(K37=Assumptions!$G$50, Assumptions!$P$50, 0)) -> 2097.7535 | L43: =IF(L37>Assumptions!$G$50, K43*(1+K33), IF(L37=Assumptions!$G$50, Assumptions!$P$50, 0)) -> 2139.7086 | P43: software stacks (one time) | Q43: =IF(Q37=Assumptions!$G$50, Assumptions!$D$50, 0) -> 0 | R43: =IF(R37>Assumptions!$G$50, Q43*(1+C57), IF(R37=Assumptions!$G$50, Assumptions!$D$50, 0)) -> 0 | S43: =IF(S37>Assumptions!$G$50, R43*(1+D57), IF(S37=Assumptions!$G$50, Assumptions!$D$50, 0)) -> 0 | T43: =IF(T37>Assumptions!$G$50, S43*(1+E57), IF(T37=Assumptions!$G$50, Assumptions!$D$50, 0)) -> 1900 | U43: =IF(U37>Assumptions!$G$50, T43*(1+F57), IF(U37=Assumptions!$G$50, Assumptions!$D$50, 0)) -> 1917.7566 | V43: =IF(V37>Assumptions!$G$50, U43*(1+G57), IF(V37=Assumptions!$G$50, Assumptions!$D$50, 0)) -> 1942.8403 | W43: =IF(W37>Assumptions!$G$50, V43*(1+H57), IF(W37=Assumptions!$G$50, Assumptions!$D$50, 0)) -> 1973.0356 | X43: =IF(X37>Assumptions!$G$50, W43*(1+I57), IF(X37=Assumptions!$G$50, Assumptions!$D$50, 0)) -> 2011.5707 | Y43: =IF(Y37>Assumptions!$G$50, X43*(1+J57), IF(Y37=Assumptions!$G$50, Assumptions!$D$50, 0)) -> 2058.8665 | Z43: =IF(Z37>Assumptions!$G$50, Y43*(1+K57), IF(Z37=Assumptions!$G$50, Assumptions!$D$50, 0)) -> 2112.3993 | AB43: software stacks (one time) | AC43: =IF(AC37=Assumptions!$J$50, Assumptions!$P$50, 0) -> 0 | AD43: =IF(AD37>Assumptions!$J$50, AC43*(1+AC33), IF(AD37=Assumptions!$J$50, Assumptions!$P$50, 0)) -> 0 | AE43: =IF(AE37>Assumptions!$J$50, AD43*(1+AD33), IF(AE37=Assumptions!$J$50, Assumptions!$P$50, 0)) -> 0 | AF43: =IF(AF37>Assumptions!$J$50, AE43*(1+AE33), IF(AF37=Assumptions!$J$50, Assumptions!$P$50, 0)) -> 1900 | AG43: =IF(AG37>Assumptions!$J$50, AF43*(1+AF33), IF(AG37=Assumptions!$J$50, Assumptions!$P$50, 0)) -> 1960.8 | AH43: =IF(AH37>Assumptions!$J$50, AG43*(1+AG33), IF(AH37=Assumptions!$J$50, Assumptions!$P$50, 0)) -> 2023.5456 | AI43: =IF(AI37>Assumptions!$J$50, AH43*(1+AH33), IF(AI37=Assumptions!$J$50, Assumptions!$P$50, 0)) -> 2088.2991 | AJ43: =IF(AJ37>Assumptions!$J$50, AI43*(1+AI33), IF(AJ37=Assumptions!$J$50, Assumptions!$P$50, 0)) -> 2155.1246 | AK43: =IF(AK37>Assumptions!$J$50, AJ43*(1+AJ33), IF(AK37=Assumptions!$J$50, Assumptions!$P$50, 0)) -> 2224.0886 | AL43: =IF(AL37>Assumptions!$J$50, AK43*(1+AK33), IF(AL37=Assumptions!$J$50, Assumptions!$P$50, 0)) -> 2295.2595 | AP43: software stacks (one time) | AQ43: =IF(AQ37=Assumptions!$J$50, Assumptions!$D$50, 0) -> 0 | AR43: =IF(AR37>Assumptions!$J$50, AQ43*(1+AC57), IF(AR37=Assumptions!$J$50, Assumptions!$D$50, 0)) -> 0 | AS43: =IF(AS37>Assumptions!$J$50, AR43*(1+AD57), IF(AS37=Assumptions!$J$50, Assumptions!$D$50, 0)) -> 0 | AT43: =IF(AT37>Assumptions!$J$50, AS43*(1+AE57), IF(AT37=Assumptions!$J$50, Assumptions!$D$50, 0)) -> 1900 | AU43: =IF(AU37>Assumptions!$J$50, AT43*(1+AF57), IF(AU37=Assumptions!$J$50, Assumptions!$D$50, 0)) -> 1921.2113 | AV43: =IF(AV37>Assumptions!$J$50, AU43*(1+AG57), IF(AV37=Assumptions!$J$50, Assumptions!$D$50, 0)) -> 1949.1386 | AW43: =IF(AW37>Assumptions!$J$50, AV43*(1+AH57), IF(AW37=Assumptions!$J$50, Assumptions!$D$50, 0)) -> 1982.7152 | AX43: =IF(AX37>Assumptions!$J$50, AW43*(1+AI57), IF(AX37=Assumptions!$J$50, Assumptions!$D$50, 0)) -> 2023.2268 | AY43: =IF(AY37>Assumptions!$J$50, AX43*(1+AJ57), IF(AY37=Assumptions!$J$50, Assumptions!$D$50, 0)) -> 2069.7439 | AZ43: =IF(AZ37>Assumptions!$J$50, AY43*(1+AK57), IF(AZ37=Assumptions!$J$50, Assumptions!$D$50, 0)) -> 2124.8654
B44: software stacks (subscription) | C44: =IF(C38=Assumptions!$G$50, Assumptions!$P$51, 0) -> 0 | D44: =IF(D37>Assumptions!$G$51, C44, IF(D37=Assumptions!$G$51, Assumptions!$P$51, 0)) -> 0 | E44: =IF(E37>Assumptions!$G$51, D44, IF(E37=Assumptions!$G$51, Assumptions!$P$51, 0)) -> 0 | F44: =IF(F37>Assumptions!$G$51, E44, IF(F37=Assumptions!$G$51, Assumptions!$P$51, 0)) -> 0 | G44: =IF(G37>Assumptions!$G$51, F44, IF(G37=Assumptions!$G$51, Assumptions!$P$51, 0)) -> 500 | H44: =IF(H37>Assumptions!$G$51, G44, IF(H37=Assumptions!$G$51, Assumptions!$P$51, 0)) -> 500 | I44: =IF(I37>Assumptions!$G$51, H44, IF(I37=Assumptions!$G$51, Assumptions!$P$51, 0)) -> 500 | J44: =IF(J37>Assumptions!$G$51, I44, IF(J37=Assumptions!$G$51, Assumptions!$P$51, 0)) -> 500 | K44: =IF(K37>Assumptions!$G$51, J44, IF(K37=Assumptions!$G$51, Assumptions!$P$51, 0)) -> 500 | L44: =IF(L37>Assumptions!$G$51, K44, IF(L37=Assumptions!$G$51, Assumptions!$P$51, 0)) -> 500 | P44: software stacks (subscription) | Q44: =IF(Q37=Assumptions!$G$51, Assumptions!$D$51, 0) -> 0 | R44: =IF(R37>Assumptions!$G$51, Q44*(1-Assumptions!$V$16) + Assumptions!$D$51*(1+C57), IF(R37=Assumptions!$G$51, Assumptions!$D$51, 0)) -> 0 | S44: =IF(S37>Assumptions!$G$51, R44*(1-Assumptions!$V$16) + Assumptions!$D$51*(1+D57), IF(S37=Assumptions!$G$51, Assumptions!$D$51, 0)) -> 0 | T44: =IF(T37>Assumptions!$G$51, S44*(1-Assumptions!$V$16) + Assumptions!$D$51*(1+E57), IF(T37=Assumptions!$G$51, Assumptions!$D$51, 0)) -> 0 | U44: =IF(U37>Assumptions!$G$51, T44*(1-Assumptions!$V$16) + Assumptions!$D$51*(1+F57), IF(U37=Assumptions!$G$51, Assumptions!$D$51, 0)) -> 400 | V44: =IF(V37>Assumptions!$G$51, U44*(1-Assumptions!$V$16) + Assumptions!$D$51*(1+G57), IF(V37=Assumptions!$G$51, Assumptions!$D$51, 0)) -> 757.23187 | W44: =IF(W37>Assumptions!$G$51, V44*(1-Assumptions!$V$16) + Assumptions!$D$51*(1+H57), IF(W37=Assumptions!$G$51, Assumptions!$D$51, 0)) -> 1072.5808 | X44: =IF(X37>Assumptions!$G$51, W44*(1-Assumptions!$V$16) + Assumptions!$D$51*(1+I57), IF(X37=Assumptions!$G$51, Assumptions!$D$51, 0)) -> 1351.6834 | Y44: =IF(Y37>Assumptions!$G$51, X44*(1-Assumptions!$V$16) + Assumptions!$D$51*(1+J57), IF(Y37=Assumptions!$G$51, Assumptions!$D$51, 0)) -> 1598.8862 | Z44: =IF(Z37>Assumptions!$G$51, Y44*(1-Assumptions!$V$16) + Assumptions!$D$51*(1+K57), IF(Z37=Assumptions!$G$51, Assumptions!$D$51, 0)) -> 1817.4203 | AB44: software stacks (subscription) | AC44: =IF(AC38=Assumptions!$J$51, Assumptions!$P$51, 0) -> 0 | AD44: =IF(AD37>Assumptions!$J$51, AC44, IF(AD37=Assumptions!$J$51, Assumptions!$P$51, 0)) -> 0 | AE44: =IF(AE37>Assumptions!$J$51, AD44, IF(AE37=Assumptions!$J$51, Assumptions!$P$51, 0)) -> 0 | AF44: =IF(AF37>Assumptions!$J$51, AE44, IF(AF37=Assumptions!$J$51, Assumptions!$P$51, 0)) -> 0 | AG44: =IF(AG37>Assumptions!$J$51, AF44, IF(AG37=Assumptions!$J$51, Assumptions!$P$51, 0)) -> 500 | AH44: =IF(AH37>Assumptions!$J$51, AG44, IF(AH37=Assumptions!$J$51, Assumptions!$P$51, 0)) -> 500 | AI44: =IF(AI37>Assumptions!$J$51, AH44, IF(AI37=Assumptions!$J$51, Assumptions!$P$51, 0)) -> 500 | AJ44: =IF(AJ37>Assumptions!$J$51, AI44, IF(AJ37=Assumptions!$J$51, Assumptions!$P$51, 0)) -> 500 | AK44: =IF(AK37>Assumptions!$J$51, AJ44, IF(AK37=Assumptions!$J$51, Assumptions!$P$51, 0)) -> 500 | AL44: =IF(AL37>Assumptions!$J$51, AK44, IF(AL37=Assumptions!$J$51, Assumptions!$P$51, 0)) -> 500 | AP44: software stacks (subscription) | AQ44: =IF(AQ37=Assumptions!$J$51, Assumptions!$D$51, 0) -> 0 | AR44: =IF(AR37>Assumptions!$J$51, AQ44*(1-Assumptions!$V$18) + Assumptions!$D$51*(1+AC57), IF(AR37=Assumptions!$J$51, Assumptions!$D$51, 0)) -> 0 | AS44: =IF(AS37>Assumptions!$J$51, AR44*(1-Assumptions!$V$18) + Assumptions!$D$51*(1+AD57), IF(AS37=Assumptions!$J$51, Assumptions!$D$51, 0)) -> 0 | AT44: =IF(AT37>Assumptions!$J$51, AS44*(1-Assumptions!$V$18) + Assumptions!$D$51*(1+AE57), IF(AT37=Assumptions!$J$51, Assumptions!$D$51, 0)) -> 0 | AU44: =IF(AU37>Assumptions!$J$51, AT44*(1-Assumptions!$V$18) + Assumptions!$D$51*(1+AF57), IF(AU37=Assumptions!$J$51, Assumptions!$D$51, 0)) -> 400 | AV44: =IF(AV37>Assumptions!$J$51, AU44*(1-Assumptions!$V$18) + Assumptions!$D$51*(1+AG57), IF(AV37=Assumptions!$J$51, Assumptions!$D$51, 0)) -> 757.81451 | AW44: =IF(AW37>Assumptions!$J$51, AV44*(1-Assumptions!$V$18) + Assumptions!$D$51*(1+AH57), IF(AW37=Assumptions!$J$51, Assumptions!$D$51, 0)) -> 1073.7673 | AX44: =IF(AX37>Assumptions!$J$51, AW44*(1-Assumptions!$V$18) + Assumptions!$D$51*(1+AI57), IF(AX37=Assumptions!$J$51, Assumptions!$D$51, 0)) -> 1353.0882 | AY44: =IF(AY37>Assumptions!$J$51, AX44*(1-Assumptions!$V$18) + Assumptions!$D$51*(1+AJ57), IF(AY37=Assumptions!$J$51, Assumptions!$D$51, 0)) -> 1599.9142 | AZ44: =IF(AZ37>Assumptions!$J$51, AY44*(1-Assumptions!$V$18) + Assumptions!$D$51*(1+AK57), IF(AZ37=Assumptions!$J$51, Assumptions!$D$51, 0)) -> 1818.5773
B45: system integration | C45: =IF(C37=Assumptions!$G$52, Assumptions!$P$52, 0) -> 0 | D45: =IF(D37>Assumptions!$G$52, C45*(1+C33), IF(D37=Assumptions!$G$52, Assumptions!$P$52, 0)) -> 0 | E45: =IF(E37>Assumptions!$G$52, D45*(1+D33), IF(E37=Assumptions!$G$52, Assumptions!$P$52, 0)) -> 0 | F45: =IF(F37>Assumptions!$G$52, E45*(1+E33), IF(F37=Assumptions!$G$52, Assumptions!$P$52, 0)) -> 0 | G45: =IF(G37>Assumptions!$G$52, F45*(1+F33), IF(G37=Assumptions!$G$52, Assumptions!$P$52, 0)) -> 500 | H45: =IF(H37>Assumptions!$G$52, G45*(1+G33), IF(H37=Assumptions!$G$52, Assumptions!$P$52, 0)) -> 510 | I45: =IF(I37>Assumptions!$G$52, H45*(1+H33), IF(I37=Assumptions!$G$52, Assumptions!$P$52, 0)) -> 520.2 | J45: =IF(J37>Assumptions!$G$52, I45*(1+I33), IF(J37=Assumptions!$G$52, Assumptions!$P$52, 0)) -> 530.604 | K45: =IF(K37>Assumptions!$G$52, J45*(1+J33), IF(K37=Assumptions!$G$52, Assumptions!$P$52, 0)) -> 541.21608 | L45: =IF(L37>Assumptions!$G$52, K45*(1+K33), IF(L37=Assumptions!$G$52, Assumptions!$P$52, 0)) -> 552.0404 | P45: system integration | Q45: =IF(Q37=Assumptions!$G$52, Assumptions!$D$52, 0) -> 0 | R45: =IF(R37>Assumptions!$G$52, Q45*(1+C58), IF(R37=Assumptions!$G$52, Assumptions!$D$52, 0)) -> 0 | S45: =IF(S37>Assumptions!$G$52, R45*(1+D58), IF(S37=Assumptions!$G$52, Assumptions!$D$52, 0)) -> 0 | T45: =IF(T37>Assumptions!$G$52, S45*(1+E58), IF(T37=Assumptions!$G$52, Assumptions!$D$52, 0)) -> 0 | U45: =IF(U37>Assumptions!$G$52, T45*(1+F58), IF(U37=Assumptions!$G$52, Assumptions!$D$52, 0)) -> 300 | V45: =IF(V37>Assumptions!$G$52, U45*(1+G58), IF(V37=Assumptions!$G$52, Assumptions!$D$52, 0)) -> 303.83334 | W45: =IF(W37>Assumptions!$G$52, V45*(1+H58), IF(W37=Assumptions!$G$52, Assumptions!$D$52, 0)) -> 308.83755 | X45: =IF(X37>Assumptions!$G$52, W45*(1+I58), IF(X37=Assumptions!$G$52, Assumptions!$D$52, 0)) -> 315.09699 | Y45: =IF(Y37>Assumptions!$G$52, X45*(1+J58), IF(Y37=Assumptions!$G$52, Assumptions!$D$52, 0)) -> 322.62421 | Z45: =IF(Z37>Assumptions!$G$52, Y45*(1+K58), IF(Z37=Assumptions!$G$52, Assumptions!$D$52, 0)) -> 331.45917 | AB45: system integration | AC45: =IF(AC37=Assumptions!$J$52, Assumptions!$P$52, 0) -> 0 | AD45: =IF(AD37>Assumptions!$J$52, AC45*(1+AC33), IF(AD37=Assumptions!$J$52, Assumptions!$P$52, 0)) -> 0 | AE45: =IF(AE37>Assumptions!$J$52, AD45*(1+AD33), IF(AE37=Assumptions!$J$52, Assumptions!$P$52, 0)) -> 0 | AF45: =IF(AF37>Assumptions!$J$52, AE45*(1+AE33), IF(AF37=Assumptions!$J$52, Assumptions!$P$52, 0)) -> 0 | AG45: =IF(AG37>Assumptions!$J$52, AF45*(1+AF33), IF(AG37=Assumptions!$J$52, Assumptions!$P$52, 0)) -> 500 | AH45: =IF(AH37>Assumptions!$J$52, AG45*(1+AG33), IF(AH37=Assumptions!$J$52, Assumptions!$P$52, 0)) -> 516 | AI45: =IF(AI37>Assumptions!$J$52, AH45*(1+AH33), IF(AI37=Assumptions!$J$52, Assumptions!$P$52, 0)) -> 532.512 | AJ45: =IF(AJ37>Assumptions!$J$52, AI45*(1+AI33), IF(AJ37=Assumptions!$J$52, Assumptions!$P$52, 0)) -> 549.55238 | AK45: =IF(AK37>Assumptions!$J$52, AJ45*(1+AJ33), IF(AK37=Assumptions!$J$52, Assumptions!$P$52, 0)) -> 567.13806 | AL45: =IF(AL37>Assumptions!$J$52, AK45*(1+AK33), IF(AL37=Assumptions!$J$52, Assumptions!$P$52, 0)) -> 585.28648 | AP45: system integration | AQ45: =IF(AQ37=Assumptions!$J$52, Assumptions!$D$52, 0) -> 0 | AR45: =IF(AR37>Assumptions!$J$52, AQ45*(1+AC58), IF(AR37=Assumptions!$J$52, Assumptions!$D$52, 0)) -> 0 | AS45: =IF(AS37>Assumptions!$J$52, AR45*(1+AD58), IF(AS37=Assumptions!$J$52, Assumptions!$D$52, 0)) -> 0 | AT45: =IF(AT37>Assumptions!$J$52, AS45*(1+AE58), IF(AT37=Assumptions!$J$52, Assumptions!$D$52, 0)) -> 0 | AU45: =IF(AU37>Assumptions!$J$52, AT45*(1+AF58), IF(AU37=Assumptions!$J$52, Assumptions!$D$52, 0)) -> 300 | AV45: =IF(AV37>Assumptions!$J$52, AU45*(1+AG58), IF(AV37=Assumptions!$J$52, Assumptions!$D$52, 0)) -> 303.98991 | AW45: =IF(AW37>Assumptions!$J$52, AV45*(1+AH58), IF(AW37=Assumptions!$J$52, Assumptions!$D$52, 0)) -> 309.19841 | AX45: =IF(AX37>Assumptions!$J$52, AW45*(1+AI58), IF(AX37=Assumptions!$J$52, Assumptions!$D$52, 0)) -> 315.36755 | AY45: =IF(AY37>Assumptions!$J$52, AX45*(1+AJ58), IF(AY37=Assumptions!$J$52, Assumptions!$D$52, 0)) -> 322.81356 | AZ45: =IF(AZ37>Assumptions!$J$52, AY45*(1+AK58), IF(AZ37=Assumptions!$J$52, Assumptions!$D$52, 0)) -> 331.7232
B46: liscencing | C46: =IF(C37=Assumptions!$G$53, Assumptions!$P$53, 0) -> 0 | D46: =IF(D37>Assumptions!$G$53, C46*(1+C33), IF(D37=Assumptions!$G$53, Assumptions!$P$53, 0)) -> 0 | E46: =IF(E37>Assumptions!$G$53, D46*(1+D33), IF(E37=Assumptions!$G$53, Assumptions!$P$53, 0)) -> 0 | F46: =IF(F37>Assumptions!$G$53, E46*(1+E33), IF(F37=Assumptions!$G$53, Assumptions!$P$53, 0)) -> 0 | G46: =IF(G37>Assumptions!$G$53, F46*(1+F33), IF(G37=Assumptions!$G$53, Assumptions!$P$53, 0)) -> 300 | H46: =IF(H37>Assumptions!$G$53, G46*(1+G33), IF(H37=Assumptions!$G$53, Assumptions!$P$53, 0)) -> 306 | I46: =IF(I37>Assumptions!$G$53, H46*(1+H33), IF(I37=Assumptions!$G$53, Assumptions!$P$53, 0)) -> 312.12 | J46: =IF(J37>Assumptions!$G$53, I46*(1+I33), IF(J37=Assumptions!$G$53, Assumptions!$P$53, 0)) -> 318.3624 | K46: =IF(K37>Assumptions!$G$53, J46*(1+J33), IF(K37=Assumptions!$G$53, Assumptions!$P$53, 0)) -> 324.72965 | L46: =IF(L37>Assumptions!$G$53, K46*(1+K33), IF(L37=Assumptions!$G$53, Assumptions!$P$53, 0)) -> 331.22424 | P46: liscencing | Q46: =IF(Q37=Assumptions!$G$53, Assumptions!$D$53, 0) -> 0 | R46: =IF(R37>Assumptions!$G$53, Q46*(1+C59), IF(R37=Assumptions!$G$53, Assumptions!$D$53, 0)) -> 0 | S46: =IF(S37>Assumptions!$G$53, R46*(1+D59), IF(S37=Assumptions!$G$53, Assumptions!$D$53, 0)) -> 0 | T46: =IF(T37>Assumptions!$G$53, S46*(1+E59), IF(T37=Assumptions!$G$53, Assumptions!$D$53, 0)) -> 0 | U46: =IF(U37>Assumptions!$G$53, T46*(1+F59), IF(U37=Assumptions!$G$53, Assumptions!$D$53, 0)) -> 1500 | V46: =IF(V37>Assumptions!$G$53, U46*(1+G59), IF(V37=Assumptions!$G$53, Assumptions!$D$53, 0)) -> 1519.2838 | W46: =IF(W37>Assumptions!$G$53, V46*(1+H59), IF(W37=Assumptions!$G$53, Assumptions!$D$53, 0)) -> 1542.8121 | X46: =IF(X37>Assumptions!$G$53, W46*(1+I59), IF(X37=Assumptions!$G$53, Assumptions!$D$53, 0)) -> 1572.3233 | Y46: =IF(Y37>Assumptions!$G$53, X46*(1+J59), IF(Y37=Assumptions!$G$53, Assumptions!$D$53, 0)) -> 1606.4348 | Z46: =IF(Z37>Assumptions!$G$53, Y46*(1+K59), IF(Z37=Assumptions!$G$53, Assumptions!$D$53, 0)) -> 1645.5642 | AB46: liscencing | AC46: =IF(AC37=Assumptions!$J$53, Assumptions!$P$53, 0) -> 0 | AD46: =IF(AD37>Assumptions!$J$53, AC46*(1+AC33), IF(AD37=Assumptions!$J$53, Assumptions!$P$53, 0)) -> 0 | AE46: =IF(AE37>Assumptions!$J$53, AD46*(1+AD33), IF(AE37=Assumptions!$J$53, Assumptions!$P$53, 0)) -> 0 | AF46: =IF(AF37>Assumptions!$J$53, AE46*(1+AE33), IF(AF37=Assumptions!$J$53, Assumptions!$P$53, 0)) -> 0 | AG46: =IF(AG37>Assumptions!$J$53, AF46*(1+AF33), IF(AG37=Assumptions!$J$53, Assumptions!$P$53, 0)) -> 300 | AH46: =IF(AH37>Assumptions!$J$53, AG46*(1+AG33), IF(AH37=Assumptions!$J$53, Assumptions!$P$53, 0)) -> 309.6 | AI46: =IF(AI37>Assumptions!$J$53, AH46*(1+AH33), IF(AI37=Assumptions!$J$53, Assumptions!$P$53, 0)) -> 319.5072 | AJ46: =IF(AJ37>Assumptions!$J$53, AI46*(1+AI33), IF(AJ37=Assumptions!$J$53, Assumptions!$P$53, 0)) -> 329.73143 | AK46: =IF(AK37>Assumptions!$J$53, AJ46*(1+AJ33), IF(AK37=Assumptions!$J$53, Assumptions!$P$53, 0)) -> 340.28284 | AL46: =IF(AL37>Assumptions!$J$53, AK46*(1+AK33), IF(AL37=Assumptions!$J$53, Assumptions!$P$53, 0)) -> 351.17189 | AP46: liscencing | AQ46: =IF(AQ37=Assumptions!$J$53, Assumptions!$D$53, 0) -> 0 | AR46: =IF(AR37>Assumptions!$J$53, AQ46*(1+AC59), IF(AR37=Assumptions!$J$53, Assumptions!$D$53, 0)) -> 0 | AS46: =IF(AS37>Assumptions!$J$53, AR46*(1+AD59), IF(AS37=Assumptions!$J$53, Assumptions!$D$53, 0)) -> 0 | AT46: =IF(AT37>Assumptions!$J$53, AS46*(1+AE59), IF(AT37=Assumptions!$J$53, Assumptions!$D$53, 0)) -> 0 | AU46: =IF(AU37>Assumptions!$J$53, AT46*(1+AF59), IF(AU37=Assumptions!$J$53, Assumptions!$D$53, 0)) -> 1500 | AV46: =IF(AV37>Assumptions!$J$53, AU46*(1+AG59), IF(AV37=Assumptions!$J$53, Assumptions!$D$53, 0)) -> 1522.4007 | AW46: =IF(AW37>Assumptions!$J$53, AV46*(1+AH59), IF(AW37=Assumptions!$J$53, Assumptions!$D$53, 0)) -> 1549.2206 | AX46: =IF(AX37>Assumptions!$J$53, AW46*(1+AI59), IF(AX37=Assumptions!$J$53, Assumptions!$D$53, 0)) -> 1582.1428 | AY46: =IF(AY37>Assumptions!$J$53, AX46*(1+AJ59), IF(AY37=Assumptions!$J$53, Assumptions!$D$53, 0)) -> 1620.7751 | AZ46: =IF(AZ37>Assumptions!$J$53, AY46*(1+AK59), IF(AZ37=Assumptions!$J$53, Assumptions!$D$53, 0)) -> 1666.2652
B47: maintenance | C47: =IF(C37=Assumptions!$G$54, Assumptions!$P$54, 0) -> 0 | D47: =IF(D37>Assumptions!$G$54, C47*(1+C33), IF(D37=Assumptions!$G$54, Assumptions!$P$54, 0)) -> 0 | E47: =IF(E37>Assumptions!$G$54, D47*(1+D33), IF(E37=Assumptions!$G$54, Assumptions!$P$54, 0)) -> 0 | F47: =IF(F37>Assumptions!$G$54, E47*(1+E33), IF(F37=Assumptions!$G$54, Assumptions!$P$54, 0)) -> 0 | G47: =IF(G37>Assumptions!$G$54, F47*(1+F33), IF(G37=Assumptions!$G$54, Assumptions!$P$54, 0)) -> 700 | H47: =IF(H37>Assumptions!$G$54, G47*(1+G33), IF(H37=Assumptions!$G$54, Assumptions!$P$54, 0)) -> 714 | I47: =IF(I37>Assumptions!$G$54, H47*(1+H33), IF(I37=Assumptions!$G$54, Assumptions!$P$54, 0)) -> 728.28 | J47: =IF(J37>Assumptions!$G$54, I47*(1+I33), IF(J37=Assumptions!$G$54, Assumptions!$P$54, 0)) -> 742.8456 | K47: =IF(K37>Assumptions!$G$54, J47*(1+J33), IF(K37=Assumptions!$G$54, Assumptions!$P$54, 0)) -> 757.70251 | L47: =IF(L37>Assumptions!$G$54, K47*(1+K33), IF(L37=Assumptions!$G$54, Assumptions!$P$54, 0)) -> 772.85656 | P47: maintenance | Q47: =IF(Q37=Assumptions!$G$53, Assumptions!$D$54, 0) -> 0 | R47: =IF(R37>Assumptions!$G$54, Q47*(1+C60), IF(R37=Assumptions!$G$54, Assumptions!$D$54, 0)) -> 0 | S47: =IF(S37>Assumptions!$G$54, R47*(1+D60), IF(S37=Assumptions!$G$54, Assumptions!$D$54, 0)) -> 0 | T47: =IF(T37>Assumptions!$G$54, S47*(1+E60), IF(T37=Assumptions!$G$54, Assumptions!$D$54, 0)) -> 0 | U47: =IF(U37>Assumptions!$G$54, T47*(1+F60), IF(U37=Assumptions!$G$54, Assumptions!$D$54, 0)) -> 700 | V47: =IF(V37>Assumptions!$G$54, U47*(1+G60), IF(V37=Assumptions!$G$54, Assumptions!$D$54, 0)) -> 709.66257 | W47: =IF(W37>Assumptions!$G$54, V47*(1+H60), IF(W37=Assumptions!$G$54, Assumptions!$D$54, 0)) -> 722.19057 | X47: =IF(X37>Assumptions!$G$54, W47*(1+I60), IF(X37=Assumptions!$G$54, Assumptions!$D$54, 0)) -> 737.78901 | Y47: =IF(Y37>Assumptions!$G$54, X47*(1+J60), IF(Y37=Assumptions!$G$54, Assumptions!$D$54, 0)) -> 755.64097 | Z47: =IF(Z37>Assumptions!$G$54, Y47*(1+K60), IF(Z37=Assumptions!$G$54, Assumptions!$D$54, 0)) -> 776.09988 | AB47: maintenance | AC47: =IF(AC37=Assumptions!$J$54, Assumptions!$P$54, 0) -> 0 | AD47: =IF(AD37>Assumptions!$J$54, AC47*(1+AC33), IF(AD37=Assumptions!$J$54, Assumptions!$P$54, 0)) -> 0 | AE47: =IF(AE37>Assumptions!$J$54, AD47*(1+AD33), IF(AE37=Assumptions!$J$54, Assumptions!$P$54, 0)) -> 0 | AF47: =IF(AF37>Assumptions!$J$54, AE47*(1+AE33), IF(AF37=Assumptions!$J$54, Assumptions!$P$54, 0)) -> 0 | AG47: =IF(AG37>Assumptions!$J$54, AF47*(1+AF33), IF(AG37=Assumptions!$J$54, Assumptions!$P$54, 0)) -> 700 | AH47: =IF(AH37>Assumptions!$J$54, AG47*(1+AG33), IF(AH37=Assumptions!$J$54, Assumptions!$P$54, 0)) -> 722.4 | AI47: =IF(AI37>Assumptions!$J$54, AH47*(1+AH33), IF(AI37=Assumptions!$J$54, Assumptions!$P$54, 0)) -> 745.5168 | AJ47: =IF(AJ37>Assumptions!$J$54, AI47*(1+AI33), IF(AJ37=Assumptions!$J$54, Assumptions!$P$54, 0)) -> 769.37334 | AK47: =IF(AK37>Assumptions!$J$54, AJ47*(1+AJ33), IF(AK37=Assumptions!$J$54, Assumptions!$P$54, 0)) -> 793.99328 | AL47: =IF(AL37>Assumptions!$J$54, AK47*(1+AK33), IF(AL37=Assumptions!$J$54, Assumptions!$P$54, 0)) -> 819.40107 | AP47: maintenance | AQ47: =IF(AQ37=Assumptions!$J$53, Assumptions!$D$54, 0) -> 0 | AR47: =IF(AR37>Assumptions!$J$54, AQ47*(1+AC60), IF(AR37=Assumptions!$J$54, Assumptions!$D$54, 0)) -> 0 | AS47: =IF(AS37>Assumptions!$J$54, AR47*(1+AD60), IF(AS37=Assumptions!$J$54, Assumptions!$D$54, 0)) -> 0 | AT47: =IF(AT37>Assumptions!$J$54, AS47*(1+AE60), IF(AT37=Assumptions!$J$54, Assumptions!$D$54, 0)) -> 0 | AU47: =IF(AU37>Assumptions!$J$54, AT47*(1+AF60), IF(AU37=Assumptions!$J$54, Assumptions!$D$54, 0)) -> 700 | AV47: =IF(AV37>Assumptions!$J$54, AU47*(1+AG60), IF(AV37=Assumptions!$J$54, Assumptions!$D$54, 0)) -> 709.60865 | AW47: =IF(AW37>Assumptions!$J$54, AV47*(1+AH60), IF(AW37=Assumptions!$J$54, Assumptions!$D$54, 0)) -> 721.82085 | AX47: =IF(AX37>Assumptions!$J$54, AW47*(1+AI60), IF(AX37=Assumptions!$J$54, Assumptions!$D$54, 0)) -> 737.05893 | AY47: =IF(AY37>Assumptions!$J$54, AX47*(1+AJ60), IF(AY37=Assumptions!$J$54, Assumptions!$D$54, 0)) -> 755.5578 | AZ47: =IF(AZ37>Assumptions!$J$54, AY47*(1+AK60), IF(AZ37=Assumptions!$J$54, Assumptions!$D$54, 0)) -> 777.10082
C50: Year | Q50: Year | AC50: Year | AQ50: Year
C51: 1 | D51: 2 | E51: 3 | F51: 4 | G51: 5 | H51: 6 | I51: 7 | J51: 8 | K51: 9 | L51: 10 | P51: REVENUE FROM SALES | Q51: 1 | R51: 2 | S51: 3 | T51: 4 | U51: 5 | V51: 6 | W51: 7 | X51: 8 | Y51: 9 | Z51: 10 | AC51: 1 | AD51: 2 | AE51: 3 | AF51: 4 | AG51: 5 | AH51: 6 | AI51: 7 | AJ51: 8 | AK51: 9 | AL51: 10 | AP51: REVENUE FROM SALES | AQ51: 1 | AR51: 2 | AS51: 3 | AT51: 4 | AU51: 5 | AV51: 6 | AW51: 7 | AX51: 8 | AY51: 9 | AZ51: 10
B52: Drone | C52: 0.04 | D52: =C52+_xlfn.NORM.DIST(RAND(), 0, 1, FALSE)% -> 0.043917315 | E52: =D52+_xlfn.NORM.DIST(RAND(), 0, 1, FALSE)% -> 0.046369183 | F52: =E52+_xlfn.NORM.DIST(RAND(), 0, 1, FALSE)% -> 0.050246248 | G52: =F52+_xlfn.NORM.DIST(RAND(), 0, 1, FALSE)% -> 0.053080302 | H52: =G52+_xlfn.NORM.DIST(RAND(), 0, 1, FALSE)% -> 0.056167354 | I52: =H52+_xlfn.NORM.DIST(RAND(), 0, 1, FALSE)% -> 0.060108052 | J52: =I52+_xlfn.NORM.DIST(RAND(), 0, 1, FALSE)% -> 0.063716462 | K52: =J52+_xlfn.NORM.DIST(RAND(), 0, 1, FALSE)% -> 0.067250508 | L52: =K52+_xlfn.NORM.DIST(RAND(), 0, 1, FALSE)% -> 0.071214211 | P52: Drone | Q52: =C38*Q38 -> 0 | R52: =D38*R38 -> 0 | S52: =E38*S38 -> 0 | T52: =F38*T38 -> 7700000 | U52: =G38*U38 -> 8248634 | V52: =H38*V38 -> 8860203.5 | W52: =I38*W38 -> 9545014.8 | X52: =J38*X38 -> 10321122 | ... Z52: =L38*Z38 -> 12190444 | AB52: Drone | AC52: 0.03 | AD52: =AC52+_xlfn.NORM.DIST(RAND(), 0, 1, FALSE)% -> 0.033150048 | AE52: =AD52+_xlfn.NORM.DIST(RAND(), 0, 1, FALSE)% -> 0.036692683 | AF52: =AE52+_xlfn.NORM.DIST(RAND(), 0, 1, FALSE)% -> 0.040294607 | AG52: =AF52+_xlfn.NORM.DIST(RAND(), 0, 1, FALSE)% -> 0.042970642 | AH52: =AG52+_xlfn.NORM.DIST(RAND(), 0, 1, FALSE)% -> 0.046507345 | AI52: =AH52+_xlfn.NORM.DIST(RAND(), 0, 1, FALSE)% -> 0.050407464 | AJ52: =AI52+_xlfn.NORM.DIST(RAND(), 0, 1, FALSE)% -> 0.053692391 | AK52: =AJ52+_xlfn.NORM.DIST(RAND(), 0, 1, FALSE)% -> 0.056467956 | AL52: =AK52+_xlfn.NORM.DIST(RAND(), 0, 1, FALSE)% -> 0.060445805 | AP52: Drone | AQ52: =AC38*AQ38 -> 0 | AR52: =AD38*AR38 -> 0 | AS52: =AE38*AS38 -> 0 | AT52: =AF38*AT38 -> 7700000 | AU52: =AG38*AU38 -> 8266597.1 | AV52: =AH38*AV38 -> 8897716.2 | AW52: =AI38*AW38 -> 9609494.2 | AX52: =AJ38*AX38 -> 10416889 | ... AZ52: =AL38*AZ38 -> 12350018
B53: Rover | C53: 0.03 | D53: =C53+_xlfn.NORM.DIST(RAND(), 0, 1, FALSE)% -> 0.033396904 | E53: =D53+_xlfn.NORM.DIST(RAND(), 0, 1, FALSE)% -> 0.037382331 | F53: =E53+_xlfn.NORM.DIST(RAND(), 0, 1, FALSE)% -> 0.041103651 | G53: =F53+_xlfn.NORM.DIST(RAND(), 0, 1, FALSE)% -> 0.045031779 | H53: =G53+_xlfn.NORM.DIST(RAND(), 0, 1, FALSE)% -> 0.047725876 | I53: =H53+_xlfn.NORM.DIST(RAND(), 0, 1, FALSE)% -> 0.051453634 | J53: =I53+_xlfn.NORM.DIST(RAND(), 0, 1, FALSE)% -> 0.054810889 | K53: =J53+_xlfn.NORM.DIST(RAND(), 0, 1, FALSE)% -> 0.058423177 | L53: =K53+_xlfn.NORM.DIST(RAND(), 0, 1, FALSE)% -> 0.061213198 | P53: Rover | Q53: =C39*Q39 -> 0 | R53: =D39*R39 -> 0 | S53: =E39*S39 -> 0 | T53: =F39*T39 -> 7000000 | U53: =G39*U39 -> 7433480.1 | V53: =H39*V39 -> 7923587.4 | W53: =I39*W39 -> 8467782.5 | X53: =J39*X39 -> 9081550.3 | ... Z53: =L39*Z39 -> 10548587 | AB53: Rover | AC53: 0.05 | AD53: =AC53+_xlfn.NORM.DIST(RAND(), 0, 1, FALSE)% -> 0.053987512 | AE53: =AD53+_xlfn.NORM.DIST(RAND(), 0, 1, FALSE)% -> 0.057670196 | AF53: =AE53+_xlfn.NORM.DIST(RAND(), 0, 1, FALSE)% -> 0.061659355 | AG53: =AF53+_xlfn.NORM.DIST(RAND(), 0, 1, FALSE)% -> 0.065644983 | AH53: =AG53+_xlfn.NORM.DIST(RAND(), 0, 1, FALSE)% -> 0.068949979 | AI53: =AH53+_xlfn.NORM.DIST(RAND(), 0, 1, FALSE)% -> 0.07202824 | AJ53: =AI53+_xlfn.NORM.DIST(RAND(), 0, 1, FALSE)% -> 0.075518336 | AK53: =AJ53+_xlfn.NORM.DIST(RAND(), 0, 1, FALSE)% -> 0.079472087 | AL53: =AK53+_xlfn.NORM.DIST(RAND(), 0, 1, FALSE)% -> 0.083271567 | AP53: Rover | AQ53: =AC39*AQ39 -> 0 | AR53: =AD39*AR39 -> 0 | AS53: =AE39*AS39 -> 0 | AT53: =AF39*AT39 -> 7000000 | AU53: =AG39*AU39 -> 7669427.2 | AV53: =AH39*AV39 -> 8434419 | AW53: =AI39*AW39 -> 9304483.1 | AX53: =AJ39*AX39 -> 10293858 | ... AZ53: =AL39*AZ39 -> 12728195
B54: Edge | C54: 0.05 | D54: =C54+_xlfn.NORM.DIST(RAND(), 0, 1, FALSE)% -> 0.053899284 | E54: =D54+_xlfn.NORM.DIST(RAND(), 0, 1, FALSE)% -> 0.057888705 | F54: =E54+_xlfn.NORM.DIST(RAND(), 0, 1, FALSE)% -> 0.061193212 | G54: =F54+_xlfn.NORM.DIST(RAND(), 0, 1, FALSE)% -> 0.064852005 | H54: =G54+_xlfn.NORM.DIST(RAND(), 0, 1, FALSE)% -> 0.067961567 | I54: =H54+_xlfn.NORM.DIST(RAND(), 0, 1, FALSE)% -> 0.071866534 | J54: =I54+_xlfn.NORM.DIST(RAND(), 0, 1, FALSE)% -> 0.075196592 | K54: =J54+_xlfn.NORM.DIST(RAND(), 0, 1, FALSE)% -> 0.078359639 | L54: =K54+_xlfn.NORM.DIST(RAND(), 0, 1, FALSE)% -> 0.08231958 | P54: Edge | Q54: =C40*Q40 -> 0 | R54: =D40*R40 -> 0 | S54: =E40*S40 -> 0 | T54: =F40*T40 -> 6350000 | U54: =G40*U40 -> 6873348.4 | V54: =H40*V40 -> 7465480.8 | W54: =I40*W40 -> 8132303.5 | X54: =J40*X40 -> 8891078.9 | ... Z54: =L40*Z40 -> 10725223 | AB54: Edge | AC54: 0.03 | AD54: =AC54+_xlfn.NORM.DIST(RAND(), 0, 1, FALSE)% -> 0.032697522 | AE54: =AD54+_xlfn.NORM.DIST(RAND(), 0, 1, FALSE)% -> 0.036110564 | AF54: =AE54+_xlfn.NORM.DIST(RAND(), 0, 1, FALSE)% -> 0.039951544 | AG54: =AF54+_xlfn.NORM.DIST(RAND(), 0, 1, FALSE)% -> 0.042744432 | AH54: =AG54+_xlfn.NORM.DIST(RAND(), 0, 1, FALSE)% -> 0.046678441 | AI54: =AH54+_xlfn.NORM.DIST(RAND(), 0, 1, FALSE)% -> 0.050529337 | AJ54: =AI54+_xlfn.NORM.DIST(RAND(), 0, 1, FALSE)% -> 0.054505104 | AK54: =AJ54+_xlfn.NORM.DIST(RAND(), 0, 1, FALSE)% -> 0.05849279 | AL54: =AK54+_xlfn.NORM.DIST(RAND(), 0, 1, FALSE)% -> 0.062474479 | AP54: Edge | AQ54: =AC40*AQ40 -> 0 | AR54: =AD40*AR40 -> 0 | AS54: =AE40*AS40 -> 0 | AT54: =AF40*AT40 -> 6350000 | AU54: =AG40*AU40 -> 6815010.5 | AV54: =AH40*AV40 -> 7333716.3 | AW54: =AI40*AW40 -> 7921676.1 | AX54: =AJ40*AX40 -> 8588255.6 | ... AZ54: =AL40*AZ40 -> 10209417
B55: Fog | C55: 0.05 | D55: =C55+_xlfn.NORM.DIST(RAND(), 0, 1, FALSE)% -> 0.053284938 | E55: =D55+_xlfn.NORM.DIST(RAND(), 0, 1, FALSE)% -> 0.057162455 | F55: =E55+_xlfn.NORM.DIST(RAND(), 0, 1, FALSE)% -> 0.060241171 | G55: =F55+_xlfn.NORM.DIST(RAND(), 0, 1, FALSE)% -> 0.062718201 | H55: =G55+_xlfn.NORM.DIST(RAND(), 0, 1, FALSE)% -> 0.066604896 | I55: =H55+_xlfn.NORM.DIST(RAND(), 0, 1, FALSE)% -> 0.069729696 | J55: =I55+_xlfn.NORM.DIST(RAND(), 0, 1, FALSE)% -> 0.072932727 | K55: =J55+_xlfn.NORM.DIST(RAND(), 0, 1, FALSE)% -> 0.076148813 | L55: =K55+_xlfn.NORM.DIST(RAND(), 0, 1, FALSE)% -> 0.080022211 | P55: Fog | R55: =D41*R41 -> 0 | S55: =E41*S41 -> 0 | T55: =F41*T41 -> 0 | U55: =G41*U41 -> 6032500 | V55: =H41*V41 -> 6539064.5 | W55: =I41*W41 -> 7114090.2 | X55: =J41*X41 -> 7762356.6 | Y55: =K41*Y41 -> 8495056.2 | Z55: =L41*Z41 -> 9324783.5 | AB55: Fog | AC55: 0.04 | AD55: =AC55+_xlfn.NORM.DIST(RAND(), 0, 1, FALSE)% -> 0.04268051 | AE55: =AD55+_xlfn.NORM.DIST(RAND(), 0, 1, FALSE)% -> 0.045459648 | AF55: =AE55+_xlfn.NORM.DIST(RAND(), 0, 1, FALSE)% -> 0.049446199 | AG55: =AF55+_xlfn.NORM.DIST(RAND(), 0, 1, FALSE)% -> 0.053435533 | AH55: =AG55+_xlfn.NORM.DIST(RAND(), 0, 1, FALSE)% -> 0.057399711 | AI55: =AH55+_xlfn.NORM.DIST(RAND(), 0, 1, FALSE)% -> 0.061326088 | AJ55: =AI55+_xlfn.NORM.DIST(RAND(), 0, 1, FALSE)% -> 0.063940165 | AK55: =AJ55+_xlfn.NORM.DIST(RAND(), 0, 1, FALSE)% -> 0.067642578 | AL55: =AK55+_xlfn.NORM.DIST(RAND(), 0, 1, FALSE)% -> 0.070199299 | AP55: Fog | AR55: =AD41*AR41 -> 0 | AS55: =AE41*AS41 -> 0 | AT55: =AF41*AT41 -> 0 | AU55: =AG41*AU41 -> 6032500 | AV55: =AH41*AV41 -> 6558205 | AW55: =AI41*AW41 -> 7156552.7 | AX55: =AJ41*AX41 -> 7838490.1 | AY55: =AK41*AY41 -> 8606554.3 | AZ55: =AL41*AZ41 -> 9482763
B56: Enterprise | C56: 0.04 | D56: =C56+_xlfn.NORM.DIST(RAND(), 0, 1, FALSE)% -> 0.043737184 | E56: =D56+_xlfn.NORM.DIST(RAND(), 0, 1, FALSE)% -> 0.046313536 | F56: =E56+_xlfn.NORM.DIST(RAND(), 0, 1, FALSE)% -> 0.049081492 | G56: =F56+_xlfn.NORM.DIST(RAND(), 0, 1, FALSE)% -> 0.053051862 | H56: =G56+_xlfn.NORM.DIST(RAND(), 0, 1, FALSE)% -> 0.056628736 | I56: =H56+_xlfn.NORM.DIST(RAND(), 0, 1, FALSE)% -> 0.06061397 | J56: =I56+_xlfn.NORM.DIST(RAND(), 0, 1, FALSE)% -> 0.063665808 | K56: =J56+_xlfn.NORM.DIST(RAND(), 0, 1, FALSE)% -> 0.067653208 | L56: =K56+_xlfn.NORM.DIST(RAND(), 0, 1, FALSE)% -> 0.071600088 | P56: Enterprise | S56: =E42*S42 -> 0 | T56: =F42*T42 -> 0 | U56: =G42*U42 -> 0 | V56: =H42*V42 -> 3180000 | W56: =I42*W42 -> 3427281 | X56: =J42*X42 -> 3707722.5 | Y56: =K42*Y42 -> 4022653.2 | Z56: =L42*Z42 -> 4380694.6 | AB56: Enterprise | AC56: 0.07 | AD56: =AC56+_xlfn.NORM.DIST(RAND(), 0, 1, FALSE)% -> 0.073543749 | AE56: =AD56+_xlfn.NORM.DIST(RAND(), 0, 1, FALSE)% -> 0.07734936 | AF56: =AE56+_xlfn.NORM.DIST(RAND(), 0, 1, FALSE)% -> 0.080956184 | AG56: =AF56+_xlfn.NORM.DIST(RAND(), 0, 1, FALSE)% -> 0.084941501 | AH56: =AG56+_xlfn.NORM.DIST(RAND(), 0, 1, FALSE)% -> 0.088624917 | AI56: =AH56+_xlfn.NORM.DIST(RAND(), 0, 1, FALSE)% -> 0.092570603 | AJ56: =AI56+_xlfn.NORM.DIST(RAND(), 0, 1, FALSE)% -> 0.095671145 | AK56: =AJ56+_xlfn.NORM.DIST(RAND(), 0, 1, FALSE)% -> 0.099261288 | AL56: =AK56+_xlfn.NORM.DIST(RAND(), 0, 1, FALSE)% -> 0.1028841 | AP56: Enterprise | AS56: =AE42*AS42 -> 0 | AT56: =AF42*AT42 -> 0 | AU56: =AG42*AU42 -> 0 | AV56: =AH42*AV42 -> 3180000 | AW56: =AI42*AW42 -> 3572605.7 | AX56: =AJ42*AX42 -> 4028230.3 | AY56: =AK42*AY42 -> 4554851.5 | AZ56: =AL42*AZ42 -> 5167195
B57: software stacks | C57: 0 | D57: =C57+_xlfn.NORM.DIST(RAND(), 0, 1, FALSE)% -> 0.0039859432 | E57: =D57+_xlfn.NORM.DIST(RAND(), 0, 1, FALSE)% -> 0.0069243843 | F57: =E57+_xlfn.NORM.DIST(RAND(), 0, 1, FALSE)% -> 0.0093455923 | G57: =F57+_xlfn.NORM.DIST(RAND(), 0, 1, FALSE)% -> 0.013079687 | H57: =G57+_xlfn.NORM.DIST(RAND(), 0, 1, FALSE)% -> 0.015541866 | I57: =H57+_xlfn.NORM.DIST(RAND(), 0, 1, FALSE)% -> 0.01953084 | J57: =I57+_xlfn.NORM.DIST(RAND(), 0, 1, FALSE)% -> 0.023511879 | K57: =J57+_xlfn.NORM.DIST(RAND(), 0, 1, FALSE)% -> 0.026001112 | L57: =K57+_xlfn.NORM.DIST(RAND(), 0, 1, FALSE)% -> 0.028536712 | P57: software stacks | Q57: =C43*Q43 + C44*Q44 -> 0 | R57: =D43*R43 + D44*R44 -> 0 | S57: =E43*S43 + E44*S44 -> 0 | T57: =F43*T43 + F44*T44 -> 3610000 | U57: =G43*U43 + G44*U44 -> 3916612.3 | V57: =H43*V43 + H44*V44 -> 4219144.9 | W57: =I43*W43 + I44*W44 -> 4514512.7 | X57: =J43*X43 + J44*X44 -> 4812880.4 | ... Z57: =L43*Z43 + L44*Z44 -> 5428629.1 | AB57: software stacks | AC57: 0 | AD57: =AC57+_xlfn.NORM.DIST(RAND(), 0, 1, FALSE)% -> 0.0038457364 | AE57: =AD57+_xlfn.NORM.DIST(RAND(), 0, 1, FALSE)% -> 0.0073654955 | AF57: =AE57+_xlfn.NORM.DIST(RAND(), 0, 1, FALSE)% -> 0.011163851 | AG57: =AF57+_xlfn.NORM.DIST(RAND(), 0, 1, FALSE)% -> 0.01453628 | AH57: =AG57+_xlfn.NORM.DIST(RAND(), 0, 1, FALSE)% -> 0.017226394 | AI57: =AH57+_xlfn.NORM.DIST(RAND(), 0, 1, FALSE)% -> 0.020432397 | AJ57: =AI57+_xlfn.NORM.DIST(RAND(), 0, 1, FALSE)% -> 0.022991508 | AK57: =AJ57+_xlfn.NORM.DIST(RAND(), 0, 1, FALSE)% -> 0.026632065 | AL57: =AK57+_xlfn.NORM.DIST(RAND(), 0, 1, FALSE)% -> 0.030343703 | AP57: software stacks | AQ57: =AC43*AQ43 + AC44*AQ44 -> 0 | AR57: =AD43*AR43 + AD44*AR44 -> 0 | AS57: =AE43*AS43 + AE44*AS44 -> 0 | AT57: =AF43*AT43 + AF44*AT44 -> 3610000 | AU57: =AG43*AU43 + AG44*AU44 -> 3967111.1 | AV57: =AH43*AV43 + AH44*AV44 -> 4323078.1 | AW57: =AI43*AW43 + AI44*AW44 -> 4677386 | AX57: =AJ43*AX43 + AJ44*AX44 -> 5036850.1 | ... AZ57: =AL43*AZ43 + AL44*AZ44 -> 5786406.1
B58: system integration | C58: 0 | D58: =C58+_xlfn.NORM.DIST(RAND(), 0, 1, FALSE)% -> 0.0027548709 | E58: =D58+_xlfn.NORM.DIST(RAND(), 0, 1, FALSE)% -> 0.0065348521 | F58: =E58+_xlfn.NORM.DIST(RAND(), 0, 1, FALSE)% -> 0.0092536967 | G58: =F58+_xlfn.NORM.DIST(RAND(), 0, 1, FALSE)% -> 0.012777786 | H58: =G58+_xlfn.NORM.DIST(RAND(), 0, 1, FALSE)% -> 0.01647026 | I58: =H58+_xlfn.NORM.DIST(RAND(), 0, 1, FALSE)% -> 0.020267741 | J58: =I58+_xlfn.NORM.DIST(RAND(), 0, 1, FALSE)% -> 0.023888593 | K58: =J58+_xlfn.NORM.DIST(RAND(), 0, 1, FALSE)% -> 0.027384662 | L58: =K58+_xlfn.NORM.DIST(RAND(), 0, 1, FALSE)% -> 0.03128543 | P58: system integration | Q58: =C45*Q45 -> 0 | R58: =D45*R45 -> 0 | S58: =E45*S45 -> 0 | T58: =F45*T45 -> 0 | U58: =G45*U45 -> 150000 | V58: =H45*V45 -> 154955 | W58: =I45*W45 -> 160657.29 | X58: =J45*X45 -> 167191.72 | ... Z58: =L45*Z45 -> 182978.85 | AB58: system integration | AC58: 0 | AD58: =AC58+_xlfn.NORM.DIST(RAND(), 0, 1, FALSE)% -> 0.0031876686 | AE58: =AD58+_xlfn.NORM.DIST(RAND(), 0, 1, FALSE)% -> 0.0070101525 | AF58: =AE58+_xlfn.NORM.DIST(RAND(), 0, 1, FALSE)% -> 0.010559455 | AG58: =AF58+_xlfn.NORM.DIST(RAND(), 0, 1, FALSE)% -> 0.013299712 | AH58: =AG58+_xlfn.NORM.DIST(RAND(), 0, 1, FALSE)% -> 0.017133775 | AI58: =AH58+_xlfn.NORM.DIST(RAND(), 0, 1, FALSE)% -> 0.019952054 | AJ58: =AI58+_xlfn.NORM.DIST(RAND(), 0, 1, FALSE)% -> 0.02361058 | AK58: =AJ58+_xlfn.NORM.DIST(RAND(), 0, 1, FALSE)% -> 0.027599937 | AL58: =AK58+_xlfn.NORM.DIST(RAND(), 0, 1, FALSE)% -> 0.031507326 | AP58: system integration | AQ58: =AC45*AQ45 -> 0 | AR58: =AD45*AR45 -> 0 | AS58: =AE45*AS45 -> 0 | AT58: =AF45*AT45 -> 0 | AU58: =AG45*AU45 -> 150000 | AV58: =AH45*AV45 -> 156858.8 | AW58: =AI45*AW45 -> 164651.86 | AX58: =AJ45*AX45 -> 173310.99 | ... AZ58: =AL45*AZ45 -> 194153.1
B59: liscencing | C59: 0 | D59: =C59+_xlfn.NORM.DIST(RAND(), 0, 1, FALSE)% -> 0.0037063368 | E59: =D59+_xlfn.NORM.DIST(RAND(), 0, 1, FALSE)% -> 0.0072041219 | F59: =E59+_xlfn.NORM.DIST(RAND(), 0, 1, FALSE)% -> 0.010318098 | G59: =F59+_xlfn.NORM.DIST(RAND(), 0, 1, FALSE)% -> 0.012855858 | H59: =G59+_xlfn.NORM.DIST(RAND(), 0, 1, FALSE)% -> 0.015486429 | I59: =H59+_xlfn.NORM.DIST(RAND(), 0, 1, FALSE)% -> 0.019128185 | J59: =I59+_xlfn.NORM.DIST(RAND(), 0, 1, FALSE)% -> 0.021694994 | K59: =J59+_xlfn.NORM.DIST(RAND(), 0, 1, FALSE)% -> 0.024357884 | L59: =K59+_xlfn.NORM.DIST(RAND(), 0, 1, FALSE)% -> 0.028343486 | P59: liscencing | Q59: =C46*Q46 -> 0 | R59: =D46*R46 -> 0 | S59: =E46*S46 -> 0 | T59: =F46*T46 -> 0 | U59: =G46*U46 -> 450000 | V59: =H46*V46 -> 464900.84 | W59: =I46*W46 -> 481542.5 | X59: =J46*X46 -> 500568.61 | ... Z59: =L46*Z46 -> 545050.74 | AB59: liscencing | AC59: 0 | AD59: =AC59+_xlfn.NORM.DIST(RAND(), 0, 1, FALSE)% -> 0.0035396501 | AE59: =AD59+_xlfn.NORM.DIST(RAND(), 0, 1, FALSE)% -> 0.0071501346 | AF59: =AE59+_xlfn.NORM.DIST(RAND(), 0, 1, FALSE)% -> 0.011096826 | AG59: =AF59+_xlfn.NORM.DIST(RAND(), 0, 1, FALSE)% -> 0.014933775 | AH59: =AG59+_xlfn.NORM.DIST(RAND(), 0, 1, FALSE)% -> 0.017616897 | AI59: =AH59+_xlfn.NORM.DIST(RAND(), 0, 1, FALSE)% -> 0.021250791 | AJ59: =AI59+_xlfn.NORM.DIST(RAND(), 0, 1, FALSE)% -> 0.02441772 | AK59: =AJ59+_xlfn.NORM.DIST(RAND(), 0, 1, FALSE)% -> 0.028066886 | AL59: =AK59+_xlfn.NORM.DIST(RAND(), 0, 1, FALSE)% -> 0.031356193 | AP59: liscencing | AQ59: =AC46*AQ46 -> 0 | AR59: =AD46*AR46 -> 0 | AS59: =AE46*AS46 -> 0 | AT59: =AF46*AT46 -> 0 | AU59: =AG46*AU46 -> 450000 | AV59: =AH46*AV46 -> 471335.24 | AW59: =AI46*AW46 -> 494987.15 | AX59: =AJ46*AX46 -> 521682.21 | ... AZ59: =AL46*AZ46 -> 585145.51
B60: maintenance | C60: 0 | D60: =C60+_xlfn.NORM.DIST(RAND(), 0, 1, FALSE)% -> 0.0030695817 | E60: =D60+_xlfn.NORM.DIST(RAND(), 0, 1, FALSE)% -> 0.0069825453 | F60: =E60+_xlfn.NORM.DIST(RAND(), 0, 1, FALSE)% -> 0.010116969 | G60: =F60+_xlfn.NORM.DIST(RAND(), 0, 1, FALSE)% -> 0.013803669 | H60: =G60+_xlfn.NORM.DIST(RAND(), 0, 1, FALSE)% -> 0.017653463 | I60: =H60+_xlfn.NORM.DIST(RAND(), 0, 1, FALSE)% -> 0.021598785 | J60: =I60+_xlfn.NORM.DIST(RAND(), 0, 1, FALSE)% -> 0.024196569 | K60: =J60+_xlfn.NORM.DIST(RAND(), 0, 1, FALSE)% -> 0.027074911 | L60: =K60+_xlfn.NORM.DIST(RAND(), 0, 1, FALSE)% -> 0.030891045 | P60: maintenance | Q60: =C47*Q47 -> 0 | R60: =D47*R47 -> 0 | S60: =E47*S47 -> 0 | T60: =F47*T47 -> 0 | U60: =G47*U47 -> 490000 | V60: =H47*V47 -> 506699.07 | W60: =I47*W47 -> 525956.95 | X60: =J47*X47 -> 548063.32 | ... Z60: =L47*Z47 -> 599813.89 | AB60: maintenance | AC60: 0 | AD60: =AC60+_xlfn.NORM.DIST(RAND(), 0, 1, FALSE)% -> 0.0039642905 | AE60: =AD60+_xlfn.NORM.DIST(RAND(), 0, 1, FALSE)% -> 0.0068966885 | AF60: =AE60+_xlfn.NORM.DIST(RAND(), 0, 1, FALSE)% -> 0.010554935 | AG60: =AF60+_xlfn.NORM.DIST(RAND(), 0, 1, FALSE)% -> 0.013726647 | AH60: =AG60+_xlfn.NORM.DIST(RAND(), 0, 1, FALSE)% -> 0.017209768 | AI60: =AH60+_xlfn.NORM.DIST(RAND(), 0, 1, FALSE)% -> 0.021110606 | AJ60: =AI60+_xlfn.NORM.DIST(RAND(), 0, 1, FALSE)% -> 0.025098219 | AK60: =AJ60+_xlfn.NORM.DIST(RAND(), 0, 1, FALSE)% -> 0.028512736 | AL60: =AK60+_xlfn.NORM.DIST(RAND(), 0, 1, FALSE)% -> 0.031492358 | AP60: maintenance | AQ60: =AC47*AQ47 -> 0 | AR60: =AD47*AR47 -> 0 | AS60: =AE47*AS47 -> 0 | AT60: =AF47*AT47 -> 0 | AU60: =AG47*AU47 -> 490000 | AV60: =AH47*AV47 -> 512621.29 | AW60: =AI47*AW47 -> 538129.57 | AX60: =AJ47*AX47 -> 567073.49 | ... AZ60: =AL47*AZ47 -> 636757.24
P61: TOTAL | Q61: =SUM(Q52:Q60) -> 0 | R61: =SUM(R52:R60) -> 0 | S61: =SUM(S52:S60) -> 0 | T61: =SUM(T52:T60) -> 24660000 | U61: =SUM(U52:U60) -> 33594575 | V61: =SUM(V52:V60) -> 39314036 | W61: =SUM(W52:W60) -> 42369141 | X61: =SUM(X52:X60) -> 45792534 | ... Z61: =SUM(Z52:Z60) -> 53926203 | AP61: TOTAL | AQ61: =SUM(AQ52:AQ60) -> 0 | AR61: =SUM(AR52:AR60) -> 0 | AS61: =SUM(AS52:AS60) -> 0 | AT61: =SUM(AT52:AT60) -> 24660000 | AU61: =SUM(AU52:AU60) -> 33840646 | AV61: =SUM(AV52:AV60) -> 39867950 | AW61: =SUM(AW52:AW60) -> 43439966 | AX61: =SUM(AX52:AX60) -> 47464640 | ... AZ61: =SUM(AZ52:AZ60) -> 57140050
B63: CPI | C63: =Assumptions!J19 -> 0.0315 | D63: =Assumptions!K19 -> 0.0315 | E63: =Assumptions!L19 -> 0.0315 | F63: =Assumptions!M19 -> 0.0315 | G63: =Assumptions!N19 -> 0.0315 | H63: =Assumptions!O19 -> 0.0315 | I63: =Assumptions!P19 -> 0.0315 | J63: =Assumptions!Q19 -> 0.0315 | ... L63: =Assumptions!S19 -> 0.0315 | AB63: CPI | AC63: =Assumptions!J20 -> 0.1 | AD63: =Assumptions!K20 -> 0.1 | AE63: =Assumptions!L20 -> 0.1 | AF63: =Assumptions!M20 -> 0.1 | AG63: =Assumptions!N20 -> 0.1 | AH63: =Assumptions!O20 -> 0.1 | AI63: =Assumptions!P20 -> 0.1 | AJ63: =Assumptions!Q20 -> 0.1 | ... AL63: =Assumptions!S20 -> 0.1
C66: Year | Q66: Year | AC66: Year | AQ66: Year
B67: SELLING PRICE | C67: 1 | D67: 2 | E67: 3 | F67: 4 | G67: 5 | H67: 6 | I67: 7 | J67: 8 | K67: 9 | L67: 10 | P67: UNITS SOLD | Q67: 1 | R67: 2 | S67: 3 | T67: 4 | U67: 5 | V67: 6 | W67: 7 | X67: 8 | Y67: 9 | Z67: 10 | AB67: SELLING PRICE | AC67: 1 | AD67: 2 | AE67: 3 | AF67: 4 | AG67: 5 | AH67: 6 | AI67: 7 | AJ67: 8 | AK67: 9 | AL67: 10 | AP67: UNITS SOLD | AQ67: 1 | AR67: 2 | AS67: 3 | AT67: 4 | AU67: 5 | AV67: 6 | AW67: 7 | AX67: 8 | AY67: 9 | AZ67: 10
B68: Drone | C68: =IF(C$67=Assumptions!$H$45, Assumptions!$P$45, 0) -> 0 | D68: =IF(D67>Assumptions!$H$45, C68*(1+C63), IF(D67=Assumptions!$H$45, Assumptions!$P$45, 0)) -> 0 | E68: =IF(E67>Assumptions!$H$45, D68*(1+D63), IF(E67=Assumptions!$H$45, Assumptions!$P$45, 0)) -> 0 | F68: =IF(F67>Assumptions!$H$45, E68*(1+E63), IF(F67=Assumptions!$H$45, Assumptions!$P$45, 0)) -> 5000 | G68: =IF(G67>Assumptions!$H$45, F68*(1+F63), IF(G67=Assumptions!$H$45, Assumptions!$P$45, 0)) -> 5157.5 | H68: =IF(H67>Assumptions!$H$45, G68*(1+G63), IF(H67=Assumptions!$H$45, Assumptions!$P$45, 0)) -> 5319.9613 | I68: =IF(I67>Assumptions!$H$45, H68*(1+H63), IF(I67=Assumptions!$H$45, Assumptions!$P$45, 0)) -> 5487.54 | J68: =IF(J67>Assumptions!$H$45, I68*(1+I63), IF(J67=Assumptions!$H$45, Assumptions!$P$45, 0)) -> 5660.3975 | K68: =IF(K67>Assumptions!$H$45, J68*(1+J63), IF(K67=Assumptions!$H$45, Assumptions!$P$45, 0)) -> 5838.7001 | L68: =IF(L67>Assumptions!$H$45, K68*(1+K63), IF(L67=Assumptions!$H$45, Assumptions!$P$45, 0)) -> 6022.6191 | P68: Drone | Q68: =IF(Q$67=Assumptions!$H$45, Assumptions!$D45, 0) -> 0 | R68: =IF(R67>Assumptions!$H$45, Q68*(1+C82), IF(R67=Assumptions!$H$45, Assumptions!$D$45, 0)) -> 0 | S68: =IF(S67>Assumptions!$I$45, R68*(1+D82), IF(S67=Assumptions!$I$45, Assumptions!$D$45, 0)) -> 0 | T68: =IF(T67>Assumptions!$I$45, S68*(1+E82), IF(T67=Assumptions!$I$45, Assumptions!$D$45, 0)) -> 1540 | U68: =IF(U67>Assumptions!$I$45, T68*(1+F82), IF(U67=Assumptions!$I$45, Assumptions!$D$45, 0)) -> 1633.6099 | V68: =IF(V67>Assumptions!$I$45, U68*(1+G82), IF(V67=Assumptions!$I$45, Assumptions!$D$45, 0)) -> 1738.6241 | W68: =IF(W67>Assumptions!$I$45, V68*(1+H82), IF(W67=Assumptions!$I$45, Assumptions!$D$45, 0)) -> 1857.3225 | X68: =IF(X67>Assumptions!$I$45, W68*(1+I82), IF(X67=Assumptions!$I$45, Assumptions!$D$45, 0)) -> 1989.0663 | Y68: =IF(Y67>Assumptions!$I$45, X68*(1+J82), IF(Y67=Assumptions!$I$45, Assumptions!$D$45, 0)) -> 2135.232 | Z68: =IF(Z67>Assumptions!$I$45, Y68*(1+K82), IF(Z67=Assumptions!$I$45, Assumptions!$D$45, 0)) -> 2299.1386 | AB68: Drone | AC68: =IF(AC67=Assumptions!$K$45, Assumptions!$P$45, 0) -> 0 | AD68: =IF(AD67>Assumptions!$K$45, AC68*(1+AC63), IF(AD67=Assumptions!$K$45, Assumptions!$P$45, 0)) -> 0 | AE68: =IF(AE67>Assumptions!$K$45, AD68*(1+AD63), IF(AE67=Assumptions!$K$45, Assumptions!$P$45, 0)) -> 0 | AF68: =IF(AF67>Assumptions!$K$45, AE68*(1+AE63), IF(AF67=Assumptions!$K$45, Assumptions!$P$45, 0)) -> 5000 | AG68: =IF(AG67>Assumptions!$K$45, AF68*(1+AF63), IF(AG67=Assumptions!$K$45, Assumptions!$P$45, 0)) -> 5500 | AH68: =IF(AH67>Assumptions!$K$45, AG68*(1+AG63), IF(AH67=Assumptions!$K$45, Assumptions!$P$45, 0)) -> 6050 | AI68: =IF(AI67>Assumptions!$K$45, AH68*(1+AH63), IF(AI67=Assumptions!$K$45, Assumptions!$P$45, 0)) -> 6655 | AJ68: =IF(AJ67>Assumptions!$K$45, AI68*(1+AI63), IF(AJ67=Assumptions!$K$45, Assumptions!$P$45, 0)) -> 7320.5 | AK68: =IF(AK67>Assumptions!$K$45, AJ68*(1+AJ63), IF(AK67=Assumptions!$K$45, Assumptions!$P$45, 0)) -> 8052.55 | AL68: =IF(AL67>Assumptions!$K$45, AK68*(1+AK63), IF(AL67=Assumptions!$K$45, Assumptions!$P$45, 0)) -> 8857.805 | AP68: Drone | AQ68: =IF(AQ67=Assumptions!$K$45, Assumptions!$D$45, 0) -> 0 | AR68: =IF(AR67>Assumptions!$K$45, AQ68*(1+AC82), IF(AR67=Assumptions!$K$45, Assumptions!$D$45, 0)) -> 0 | AS68: =IF(AS67>Assumptions!$K$45, AR68*(1+AD82), IF(AS67=Assumptions!$K$45, Assumptions!$D$45, 0)) -> 0 | AT68: =IF(AT67>Assumptions!$K$45, AS68*(1+AE82), IF(AT67=Assumptions!$K$45, Assumptions!$D$45, 0)) -> 1540 | AU68: =IF(AU67>Assumptions!$K$45, AT68*(1+AF82), IF(AU67=Assumptions!$K$45, Assumptions!$D$45, 0)) -> 1587.35 | AV68: =IF(AV67>Assumptions!$K$45, AU68*(1+AG82), IF(AV67=Assumptions!$K$45, Assumptions!$D$45, 0)) -> 1642.3136 | AW68: =IF(AW67>Assumptions!$K$45, AV68*(1+AH82), IF(AW67=Assumptions!$K$45, Assumptions!$D$45, 0)) -> 1705.7145 | AX68: =IF(AX67>Assumptions!$K$45, AW68*(1+AI82), IF(AX67=Assumptions!$K$45, Assumptions!$D$45, 0)) -> 1778.3003 | AY68: =IF(AY67>Assumptions!$K$45, AX68*(1+AJ82), IF(AY67=Assumptions!$K$45, Assumptions!$D$45, 0)) -> 1860.9566 | AZ68: =IF(AZ67>Assumptions!$K$45, AY68*(1+AK82), IF(AZ67=Assumptions!$K$45, Assumptions!$D$45, 0)) -> 1952.4882
B69: Rover | C69: =IF(C$67=Assumptions!$H$46, Assumptions!$P46, 0) -> 0 | D69: =IF(D67>Assumptions!$H$45, C69*(1+C63), IF(D67=Assumptions!$H$45, Assumptions!$P$46, 0)) -> 0 | E69: =IF(E67>Assumptions!$H$45, D69*(1+D63), IF(E67=Assumptions!$H$45, Assumptions!$P$46, 0)) -> 0 | F69: =IF(F67>Assumptions!$H$45, E69*(1+E63), IF(F67=Assumptions!$H$45, Assumptions!$P$46, 0)) -> 7000 | G69: =IF(G67>Assumptions!$H$45, F69*(1+F63), IF(G67=Assumptions!$H$45, Assumptions!$P$46, 0)) -> 7220.5 | H69: =IF(H67>Assumptions!$H$45, G69*(1+G63), IF(H67=Assumptions!$H$45, Assumptions!$P$46, 0)) -> 7447.9458 | I69: =IF(I67>Assumptions!$H$45, H69*(1+H63), IF(I67=Assumptions!$H$45, Assumptions!$P$46, 0)) -> 7682.556 | J69: =IF(J67>Assumptions!$H$45, I69*(1+I63), IF(J67=Assumptions!$H$45, Assumptions!$P$46, 0)) -> 7924.5566 | K69: =IF(K67>Assumptions!$H$45, J69*(1+J63), IF(K67=Assumptions!$H$45, Assumptions!$P$46, 0)) -> 8174.1801 | L69: =IF(L67>Assumptions!$H$45, K69*(1+K63), IF(L67=Assumptions!$H$45, Assumptions!$P$46, 0)) -> 8431.6668 | P69: Rover | Q69: =IF(Q$67=Assumptions!$H$46, Assumptions!$D46, 0) -> 0 | R69: =IF(R67>Assumptions!$H$45, Q69*(1+C83), IF(R67=Assumptions!$H$45, Assumptions!$D$46, 0)) -> 0 | S69: =IF(S67>Assumptions!$H$45, R69*(1+D83), IF(S67=Assumptions!$H$45, Assumptions!$D$46, 0)) -> 0 | T69: =IF(T67>Assumptions!$H$45, S69*(1+E83), IF(T67=Assumptions!$H$45, Assumptions!$D$46, 0)) -> 1000 | U69: =IF(U67>Assumptions!$H$45, T69*(1+F83), IF(U67=Assumptions!$H$45, Assumptions!$D$46, 0)) -> 1100.8229 | V69: =IF(V67>Assumptions!$H$45, U69*(1+G83), IF(V67=Assumptions!$H$45, Assumptions!$D$46, 0)) -> 1215.0611 | W69: =IF(W67>Assumptions!$H$45, V69*(1+H83), IF(W67=Assumptions!$H$45, Assumptions!$D$46, 0)) -> 1345.6151 | X69: =IF(X67>Assumptions!$H$45, W69*(1+I83), IF(X67=Assumptions!$H$45, Assumptions!$D$46, 0)) -> 1494.7349 | Y69: =IF(Y67>Assumptions!$H$45, X69*(1+J83), IF(Y67=Assumptions!$H$45, Assumptions!$D$46, 0)) -> 1666.1653 | Z69: =IF(Z67>Assumptions!$H$45, Y69*(1+K83), IF(Z67=Assumptions!$H$45, Assumptions!$D$46, 0)) -> 1861.9398 | AB69: Rover | AC69: =IF(AC67=Assumptions!$K$46, Assumptions!$P$46, 0) -> 0 | AD69: =IF(AD67>Assumptions!$K$46, AC69*(1+AC63), IF(AD67=Assumptions!$J$46, Assumptions!$P$46, 0)) -> 0 | AE69: =IF(AE67>Assumptions!$K$46, AD69*(1+AD63), IF(AE67=Assumptions!$J$46, Assumptions!$P$46, 0)) -> 0 | AF69: =IF(AF67>Assumptions!$K$46, AE69*(1+AE63), IF(AF67=Assumptions!$J$46, Assumptions!$P$46, 0)) -> 7000 | AG69: =IF(AG67>Assumptions!$K$46, AF69*(1+AF63), IF(AG67=Assumptions!$J$46, Assumptions!$P$46, 0)) -> 7700 | AH69: =IF(AH67>Assumptions!$K$46, AG69*(1+AG63), IF(AH67=Assumptions!$J$46, Assumptions!$P$46, 0)) -> 8470 | AI69: =IF(AI67>Assumptions!$K$46, AH69*(1+AH63), IF(AI67=Assumptions!$J$46, Assumptions!$P$46, 0)) -> 9317 | AJ69: =IF(AJ67>Assumptions!$K$46, AI69*(1+AI63), IF(AJ67=Assumptions!$J$46, Assumptions!$P$46, 0)) -> 10248.7 | AK69: =IF(AK67>Assumptions!$K$46, AJ69*(1+AJ63), IF(AK67=Assumptions!$J$46, Assumptions!$P$46, 0)) -> 11273.57 | AL69: =IF(AL67>Assumptions!$K$46, AK69*(1+AK63), IF(AL67=Assumptions!$J$46, Assumptions!$P$46, 0)) -> 12400.927 | AP69: Rover | AQ69: =IF(AQ67=Assumptions!$K$46, Assumptions!$D$46, 0) -> 0 | AR69: =IF(AR67>Assumptions!$K$46, AQ69*(1+AC83), IF(AR67=Assumptions!$K$46, Assumptions!$D$46, 0)) -> 0 | AS69: =IF(AS67>Assumptions!$K$46, AR69*(1+AD83), IF(AS67=Assumptions!$K$46, Assumptions!$D$46, 0)) -> 0 | AT69: =IF(AT67>Assumptions!$K$46, AS69*(1+AE83), IF(AT67=Assumptions!$K$46, Assumptions!$D$46, 0)) -> 1000 | AU69: =IF(AU67>Assumptions!$K$46, AT69*(1+AF83), IF(AU67=Assumptions!$K$46, Assumptions!$D$46, 0)) -> 1050.22 | AV69: =IF(AV67>Assumptions!$K$46, AU69*(1+AG83), IF(AV67=Assumptions!$K$46, Assumptions!$D$46, 0)) -> 1107.1505 | AW69: =IF(AW67>Assumptions!$K$46, AV69*(1+AH83), IF(AW67=Assumptions!$K$46, Assumptions!$D$46, 0)) -> 1170.531 | AX69: =IF(AX67>Assumptions!$K$46, AW69*(1+AI83), IF(AX67=Assumptions!$K$46, Assumptions!$D$46, 0)) -> 1242.2095 | AY69: =IF(AY67>Assumptions!$K$46, AX69*(1+AJ83), IF(AY67=Assumptions!$K$46, Assumptions!$D$46, 0)) -> 1323.146 | AZ69: =IF(AZ67>Assumptions!$K$46, AY69*(1+AK83), IF(AZ67=Assumptions!$K$46, Assumptions!$D$46, 0)) -> 1414.5944
B70: Edge | C70: =IF(C$67=Assumptions!$I$47, Assumptions!$P47, 0) -> 0 | D70: =IF(D67>Assumptions!$H$47, C70*(1+C63), IF(D67=Assumptions!$H$47, Assumptions!$P$45, 0)) -> 0 | E70: =IF(E67>Assumptions!$H$47, D70*(1+D63), IF(E67=Assumptions!$H$47, Assumptions!$P$45, 0)) -> 0 | F70: =IF(F67>Assumptions!$H$47, E70*(1+E63), IF(F67=Assumptions!$H$47, Assumptions!$P$45, 0)) -> 5000 | G70: =IF(G67>Assumptions!$H$47, F70*(1+F63), IF(G67=Assumptions!$H$47, Assumptions!$P$45, 0)) -> 5157.5 | H70: =IF(H67>Assumptions!$H$47, G70*(1+G63), IF(H67=Assumptions!$H$47, Assumptions!$P$45, 0)) -> 5319.9613 | I70: =IF(I67>Assumptions!$H$47, H70*(1+H63), IF(I67=Assumptions!$H$47, Assumptions!$P$45, 0)) -> 5487.54 | J70: =IF(J67>Assumptions!$H$47, I70*(1+I63), IF(J67=Assumptions!$H$47, Assumptions!$P$45, 0)) -> 5660.3975 | K70: =IF(K67>Assumptions!$H$47, J70*(1+J63), IF(K67=Assumptions!$H$47, Assumptions!$P$45, 0)) -> 5838.7001 | L70: =IF(L67>Assumptions!$H$47, K70*(1+K63), IF(L67=Assumptions!$H$47, Assumptions!$P$45, 0)) -> 6022.6191 | P70: Edge | Q70: =IF(Q$67=Assumptions!$H$47, Assumptions!$D47, 0) -> 0 | R70: =IF(R67>Assumptions!$H$47, Q70*(1+C84), IF(R67=Assumptions!$H$47, Assumptions!$D$47, 0)) -> 0 | S70: =IF(S67>Assumptions!$H$47, R70*(1+D84), IF(S67=Assumptions!$H$47, Assumptions!$D$47, 0)) -> 0 | T70: =IF(T67>Assumptions!$H$47, S70*(1+E84), IF(T67=Assumptions!$H$47, Assumptions!$D$47, 0)) -> 1270 | U70: =IF(U67>Assumptions!$H$47, T70*(1+F84), IF(U67=Assumptions!$H$47, Assumptions!$D$47, 0)) -> 1310.1052 | V70: =IF(V67>Assumptions!$H$47, U70*(1+G84), IF(V67=Assumptions!$H$47, Assumptions!$D$47, 0)) -> 1356.1577 | W70: =IF(W67>Assumptions!$H$47, V70*(1+H84), IF(W67=Assumptions!$H$47, Assumptions!$D$47, 0)) -> 1409.2144 | X70: =IF(X67>Assumptions!$H$47, W70*(1+I84), IF(X67=Assumptions!$H$47, Assumptions!$D$47, 0)) -> 1469.9241 | Y70: =IF(Y67>Assumptions!$H$47, X70*(1+J84), IF(Y67=Assumptions!$H$47, Assumptions!$D$47, 0)) -> 1538.2167 | Z70: =IF(Z67>Assumptions!$H$47, Y70*(1+K84), IF(Z67=Assumptions!$H$47, Assumptions!$D$47, 0)) -> 1615.7824 | AB70: Edge | AC70: =IF(AC67=Assumptions!$K$47, Assumptions!$P$47, 0) -> 0 | AD70: =IF(AD67>Assumptions!$K$47, AC70*(1+AC63), IF(AD67=Assumptions!$K$47, Assumptions!$P$45, 0)) -> 0 | AE70: =IF(AE67>Assumptions!$K$47, AD70*(1+AD63), IF(AE67=Assumptions!$K$47, Assumptions!$P$45, 0)) -> 0 | AF70: =IF(AF67>Assumptions!$K$47, AE70*(1+AE63), IF(AF67=Assumptions!$K$47, Assumptions!$P$45, 0)) -> 5000 | AG70: =IF(AG67>Assumptions!$K$47, AF70*(1+AF63), IF(AG67=Assumptions!$K$47, Assumptions!$P$45, 0)) -> 5500 | AH70: =IF(AH67>Assumptions!$K$47, AG70*(1+AG63), IF(AH67=Assumptions!$K$47, Assumptions!$P$45, 0)) -> 6050 | AI70: =IF(AI67>Assumptions!$K$47, AH70*(1+AH63), IF(AI67=Assumptions!$K$47, Assumptions!$P$45, 0)) -> 6655 | AJ70: =IF(AJ67>Assumptions!$K$47, AI70*(1+AI63), IF(AJ67=Assumptions!$K$47, Assumptions!$P$45, 0)) -> 7320.5 | AK70: =IF(AK67>Assumptions!$K$47, AJ70*(1+AJ63), IF(AK67=Assumptions!$K$47, Assumptions!$P$45, 0)) -> 8052.55 | AL70: =IF(AL67>Assumptions!$K$47, AK70*(1+AK63), IF(AL67=Assumptions!$K$47, Assumptions!$P$45, 0)) -> 8857.805 | AP70: Edge | AQ70: =IF(AQ67=Assumptions!$K$47, Assumptions!$D$47, 0) -> 0 | AR70: =IF(AR67>Assumptions!$K$47, AQ70*(1+AC84), IF(AR67=Assumptions!$K$47, Assumptions!$D$47, 0)) -> 0 | AS70: =IF(AS67>Assumptions!$K$47, AR70*(1+AD84), IF(AS67=Assumptions!$K$47, Assumptions!$D$47, 0)) -> 0 | AT70: =IF(AT67>Assumptions!$K$47, AS70*(1+AE84), IF(AT67=Assumptions!$K$47, Assumptions!$D$47, 0)) -> 1270 | AU70: =IF(AU67>Assumptions!$K$47, AT70*(1+AF84), IF(AU67=Assumptions!$K$47, Assumptions!$D$47, 0)) -> 1319.4868 | AV70: =IF(AV67>Assumptions!$K$47, AU70*(1+AG84), IF(AV67=Assumptions!$K$47, Assumptions!$D$47, 0)) -> 1374.1268 | AW70: =IF(AW67>Assumptions!$K$47, AV70*(1+AH84), IF(AW67=Assumptions!$K$47, Assumptions!$D$47, 0)) -> 1435.0696 | AX70: =IF(AX67>Assumptions!$K$47, AW70*(1+AI84), IF(AX67=Assumptions!$K$47, Assumptions!$D$47, 0)) -> 1504.3705 | AY70: =IF(AY67>Assumptions!$K$47, AX70*(1+AJ84), IF(AY67=Assumptions!$K$47, Assumptions!$D$47, 0)) -> 1583.0193 | AZ70: =IF(AZ67>Assumptions!$K$47, AY70*(1+AK84), IF(AZ67=Assumptions!$K$47, Assumptions!$D$47, 0)) -> 1671.4266
B71: Fog | C71: =IF(C$67=Assumptions!$H48, Assumptions!$P$48, 0) -> 0 | D71: =IF(D67>Assumptions!$H$48, C71*(1+C63), IF(D67=Assumptions!$H$48, Assumptions!$P$48, 0)) -> 0 | E71: =IF(E67>Assumptions!$H$48, D71*(1+D63), IF(E67=Assumptions!$H$48, Assumptions!$P$48, 0)) -> 0 | F71: =IF(F67>Assumptions!$H$48, E71*(1+E63), IF(F67=Assumptions!$H$48, Assumptions!$P$48, 0)) -> 0 | G71: =IF(G67>Assumptions!$H$48, F71*(1+F63), IF(G67=Assumptions!$H$48, Assumptions!$P$48, 0)) -> 9500 | H71: =IF(H67>Assumptions!$H$48, G71*(1+G63), IF(H67=Assumptions!$H$48, Assumptions!$P$48, 0)) -> 9799.25 | I71: =IF(I67>Assumptions!$H$48, H71*(1+H63), IF(I67=Assumptions!$H$48, Assumptions!$P$48, 0)) -> 10107.926 | J71: =IF(J67>Assumptions!$H$48, I71*(1+I63), IF(J67=Assumptions!$H$48, Assumptions!$P$48, 0)) -> 10426.326 | K71: =IF(K67>Assumptions!$H$48, J71*(1+J63), IF(K67=Assumptions!$H$48, Assumptions!$P$48, 0)) -> 10754.755 | L71: =IF(L67>Assumptions!$H$48, K71*(1+K63), IF(L67=Assumptions!$H$48, Assumptions!$P$48, 0)) -> 11093.53 | P71: Fog | Q71: =IF(Q$67=Assumptions!$H$48, Assumptions!$D48, 0) -> 0 | R71: =IF(R67>Assumptions!$H$48, Q71*(1+C85), IF(R67=Assumptions!$H$48, Assumptions!$D$48, 0)) -> 0 | S71: =IF(S67>Assumptions!$H$48, R71*(1+D85), IF(S67=Assumptions!$H$48, Assumptions!$D$48, 0)) -> 0 | T71: =IF(T67>Assumptions!$H$48, S71*(1+E85), IF(T67=Assumptions!$H$48, Assumptions!$D$48, 0)) -> 0 | U71: =IF(U67>Assumptions!$H$48, T71*(1+F85), IF(U67=Assumptions!$H$48, Assumptions!$D$48, 0)) -> 635 | V71: =IF(V67>Assumptions!$H$48, U71*(1+G85), IF(V67=Assumptions!$H$48, Assumptions!$D$48, 0)) -> 668.00648 | W71: =IF(W67>Assumptions!$H$48, V71*(1+H85), IF(W67=Assumptions!$H$48, Assumptions!$D$48, 0)) -> 704.59154 | X71: =IF(X67>Assumptions!$H$48, W71*(1+I85), IF(X67=Assumptions!$H$48, Assumptions!$D$48, 0)) -> 745.35171 | Y71: =IF(Y67>Assumptions!$H$48, X71*(1+J85), IF(Y67=Assumptions!$H$48, Assumptions!$D$48, 0)) -> 790.86631 | Z71: =IF(Z67>Assumptions!$H$48, Y71*(1+K85), IF(Z67=Assumptions!$H$48, Assumptions!$D$48, 0)) -> 842.11221 | AB71: Fog | AC71: =IF(AC67=Assumptions!$K$48, Assumptions!$P$48, 0) -> 0 | AD71: =IF(AD67>Assumptions!$K$48, AC71*(1+AC63), IF(AD67=Assumptions!$K$48, Assumptions!$P$48, 0)) -> 0 | AE71: =IF(AE67>Assumptions!$K$48, AD71*(1+AD63), IF(AE67=Assumptions!$K$48, Assumptions!$P$48, 0)) -> 0 | AF71: =IF(AF67>Assumptions!$K$48, AE71*(1+AE63), IF(AF67=Assumptions!$K$48, Assumptions!$P$48, 0)) -> 0 | AG71: =IF(AG67>Assumptions!$K$48, AF71*(1+AF63), IF(AG67=Assumptions!$K$48, Assumptions!$P$48, 0)) -> 9500 | AH71: =IF(AH67>Assumptions!$K$48, AG71*(1+AG63), IF(AH67=Assumptions!$K$48, Assumptions!$P$48, 0)) -> 10450 | AI71: =IF(AI67>Assumptions!$K$48, AH71*(1+AH63), IF(AI67=Assumptions!$K$48, Assumptions!$P$48, 0)) -> 11495 | AJ71: =IF(AJ67>Assumptions!$K$48, AI71*(1+AI63), IF(AJ67=Assumptions!$K$48, Assumptions!$P$48, 0)) -> 12644.5 | AK71: =IF(AK67>Assumptions!$K$48, AJ71*(1+AJ63), IF(AK67=Assumptions!$K$48, Assumptions!$P$48, 0)) -> 13908.95 | AL71: =IF(AL67>Assumptions!$K$48, AK71*(1+AK63), IF(AL67=Assumptions!$K$48, Assumptions!$P$48, 0)) -> 15299.845 | AP71: Fog | AQ71: =IF(AQ67=Assumptions!$K$48, Assumptions!$D$48, 0) -> 0 | AR71: =IF(AR67>Assumptions!$K$48, AQ71*(1+AC85), IF(AR67=Assumptions!$J$48, Assumptions!$D$48, 0)) -> 0 | AS71: =IF(AS67>Assumptions!$K$48, AR71*(1+AD85), IF(AS67=Assumptions!$J$48, Assumptions!$D$48, 0)) -> 0 | AT71: =IF(AT67>Assumptions!$K$48, AS71*(1+AE85), IF(AT67=Assumptions!$J$48, Assumptions!$D$48, 0)) -> 0 | AU71: =IF(AU67>Assumptions!$K$48, AT71*(1+AF85), IF(AU67=Assumptions!$J$48, Assumptions!$D$48, 0)) -> 635 | AV71: =IF(AV67>Assumptions!$K$48, AU71*(1+AG85), IF(AV67=Assumptions!$J$48, Assumptions!$D$48, 0)) -> 668.43403 | AW71: =IF(AW67>Assumptions!$K$48, AV71*(1+AH85), IF(AW67=Assumptions!$J$48, Assumptions!$D$48, 0)) -> 706.00831 | AX71: =IF(AX67>Assumptions!$K$48, AW71*(1+AI85), IF(AX67=Assumptions!$J$48, Assumptions!$D$48, 0)) -> 748.26899 | AY71: =IF(AY67>Assumptions!$K$48, AX71*(1+AJ85), IF(AY67=Assumptions!$J$48, Assumptions!$D$48, 0)) -> 795.32136 | AZ71: =IF(AZ67>Assumptions!$K$48, AY71*(1+AK85), IF(AZ67=Assumptions!$J$48, Assumptions!$D$48, 0)) -> 848.34182
B72: Enterprise | C72: =IF(C$67=Assumptions!$H$49, Assumptions!$P$49, 0) -> 0 | D72: =IF(D67>Assumptions!$H$49, C72*(1+C63), IF(D67=Assumptions!$H$49, Assumptions!$P$49, 0)) -> 0 | E72: =IF(E67>Assumptions!$H$49, D72*(1+D63), IF(E67=Assumptions!$H$49, Assumptions!$P$49, 0)) -> 0 | F72: =IF(F67>Assumptions!$H$49, E72*(1+E63), IF(F67=Assumptions!$H$49, Assumptions!$P$49, 0)) -> 0 | G72: =IF(G67>Assumptions!$H$49, F72*(1+F63), IF(G67=Assumptions!$H$49, Assumptions!$P$49, 0)) -> 0 | H72: =IF(H67>Assumptions!$H$49, G72*(1+G63), IF(H67=Assumptions!$H$49, Assumptions!$P$49, 0)) -> 10000 | I72: =IF(I67>Assumptions!$H$49, H72*(1+H63), IF(I67=Assumptions!$H$49, Assumptions!$P$49, 0)) -> 10315 | J72: =IF(J67>Assumptions!$H$49, I72*(1+I63), IF(J67=Assumptions!$H$49, Assumptions!$P$49, 0)) -> 10639.923 | K72: =IF(K67>Assumptions!$H$49, J72*(1+J63), IF(K67=Assumptions!$H$49, Assumptions!$P$49, 0)) -> 10975.08 | L72: =IF(L67>Assumptions!$H$49, K72*(1+K63), IF(L67=Assumptions!$H$49, Assumptions!$P$49, 0)) -> 11320.795 | P72: Enterprise | Q72: =IF(Q$67=Assumptions!$H$49, Assumptions!$D49, 0) -> 0 | R72: =IF(R67>Assumptions!$H$49, Q72*(1+C86), IF(R67=Assumptions!$H$49, Assumptions!$D$49, 0)) -> 0 | S72: =IF(S67>Assumptions!$H$49, R72*(1+D86), IF(S67=Assumptions!$H$49, Assumptions!$D$49, 0)) -> 0 | T72: =IF(T67>Assumptions!$H$49, S72*(1+E86), IF(T67=Assumptions!$H$49, Assumptions!$D$49, 0)) -> 0 | U72: =IF(U67>Assumptions!$H$49, T72*(1+F86), IF(U67=Assumptions!$H$49, Assumptions!$D$49, 0)) -> 0 | V72: =IF(V67>Assumptions!$H$49, U72*(1+G86), IF(V67=Assumptions!$H$49, Assumptions!$D$49, 0)) -> 318 | W72: =IF(W67>Assumptions!$H$49, V72*(1+H86), IF(W67=Assumptions!$H$49, Assumptions!$D$49, 0)) -> 336.27648 | X72: =IF(X67>Assumptions!$H$49, W72*(1+I86), IF(X67=Assumptions!$H$49, Assumptions!$D$49, 0)) -> 356.81825 | Y72: =IF(Y67>Assumptions!$H$49, X72*(1+J86), IF(Y67=Assumptions!$H$49, Assumptions!$D$49, 0)) -> 379.57622 | Z72: =IF(Z67>Assumptions!$H$49, Y72*(1+K86), IF(Z67=Assumptions!$H$49, Assumptions!$D$49, 0)) -> 405.00005 | AB72: Enterprise | AC72: =IF(AC67=Assumptions!$K$49, Assumptions!$P$49, 0) -> 0 | AD72: =IF(AD67>Assumptions!$K$49, AC72*(1+AC63), IF(AD67=Assumptions!$K$49, Assumptions!$P$49, 0)) -> 0 | AE72: =IF(AE67>Assumptions!$K$49, AD72*(1+AD63), IF(AE67=Assumptions!$K$49, Assumptions!$P$49, 0)) -> 0 | AF72: =IF(AF67>Assumptions!$K$49, AE72*(1+AE63), IF(AF67=Assumptions!$K$49, Assumptions!$P$49, 0)) -> 0 | AG72: =IF(AG67>Assumptions!$K$49, AF72*(1+AF63), IF(AG67=Assumptions!$K$49, Assumptions!$P$49, 0)) -> 0 | AH72: =IF(AH67>Assumptions!$K$49, AG72*(1+AG63), IF(AH67=Assumptions!$K$49, Assumptions!$P$49, 0)) -> 10000 | AI72: =IF(AI67>Assumptions!$K$49, AH72*(1+AH63), IF(AI67=Assumptions!$K$49, Assumptions!$P$49, 0)) -> 11000 | AJ72: =IF(AJ67>Assumptions!$K$49, AI72*(1+AI63), IF(AJ67=Assumptions!$K$49, Assumptions!$P$49, 0)) -> 12100 | AK72: =IF(AK67>Assumptions!$K$49, AJ72*(1+AJ63), IF(AK67=Assumptions!$K$49, Assumptions!$P$49, 0)) -> 13310 | AL72: =IF(AL67>Assumptions!$K$49, AK72*(1+AK63), IF(AL67=Assumptions!$K$49, Assumptions!$P$49, 0)) -> 14641 | AP72: Enterprise | AQ72: =IF(AQ67=Assumptions!$K$49, Assumptions!$D$49, 0) -> 0 | AR72: =IF(AR67>Assumptions!$K$49, AQ72*(1+AC86), IF(AR67=Assumptions!$K$49, Assumptions!$D$49, 0)) -> 0 | AS72: =IF(AS67>Assumptions!$K$49, AR72*(1+AD86), IF(AS67=Assumptions!$K$49, Assumptions!$D$49, 0)) -> 0 | AT72: =IF(AT67>Assumptions!$K$49, AS72*(1+AE86), IF(AT67=Assumptions!$K$49, Assumptions!$D$49, 0)) -> 0 | AU72: =IF(AU67>Assumptions!$K$49, AT72*(1+AF86), IF(AU67=Assumptions!$K$49, Assumptions!$D$49, 0)) -> 0 | AV72: =IF(AV67>Assumptions!$K$49, AU72*(1+AG86), IF(AV67=Assumptions!$K$49, Assumptions!$D$49, 0)) -> 318 | AW72: =IF(AW67>Assumptions!$K$49, AV72*(1+AH86), IF(AW67=Assumptions!$K$49, Assumptions!$D$49, 0)) -> 326.262 | AX72: =IF(AX67>Assumptions!$K$49, AW72*(1+AI86), IF(AX67=Assumptions!$K$49, Assumptions!$D$49, 0)) -> 335.64378 | AY72: =IF(AY67>Assumptions!$K$49, AX72*(1+AJ86), IF(AY67=Assumptions!$K$49, Assumptions!$D$49, 0)) -> 346.63166 | AZ72: =IF(AZ67>Assumptions!$K$49, AY72*(1+AK86), IF(AZ67=Assumptions!$K$49, Assumptions!$D$49, 0)) -> 359.00309
B73: software stacks (one time) | C73: =IF(C$67=Assumptions!$H$50, Assumptions!$P$50, 0) -> 0 | D73: =IF(D67>Assumptions!$H$50, C73*(1+C63), IF(D67=Assumptions!$H$50, Assumptions!$P$50, 0)) -> 0 | E73: =IF(E67>Assumptions!$H$50, D73*(1+D63), IF(E67=Assumptions!$H$50, Assumptions!$P$50, 0)) -> 0 | F73: =IF(F67>Assumptions!$H$50, E73*(1+E63), IF(F67=Assumptions!$H$50, Assumptions!$P$50, 0)) -> 1900 | G73: =IF(G67>Assumptions!$H$50, F73*(1+F63), IF(G67=Assumptions!$H$50, Assumptions!$P$50, 0)) -> 1959.85 | H73: =IF(H67>Assumptions!$H$50, G73*(1+G63), IF(H67=Assumptions!$H$50, Assumptions!$P$50, 0)) -> 2021.5853 | I73: =IF(I67>Assumptions!$H$50, H73*(1+H63), IF(I67=Assumptions!$H$50, Assumptions!$P$50, 0)) -> 2085.2652 | J73: =IF(J67>Assumptions!$H$50, I73*(1+I63), IF(J67=Assumptions!$H$50, Assumptions!$P$50, 0)) -> 2150.9511 | K73: =IF(K67>Assumptions!$H$50, J73*(1+J63), IF(K67=Assumptions!$H$50, Assumptions!$P$50, 0)) -> 2218.706 | L73: =IF(L67>Assumptions!$H$50, K73*(1+K63), IF(L67=Assumptions!$H$50, Assumptions!$P$50, 0)) -> 2288.5953 | P73: software stacks (one time) | Q73: =IF(Q$67=Assumptions!$H$50, Assumptions!$D50, 0) -> 0 | R73: =IF(R67>Assumptions!$H$50, Q73*(1+C87), IF(R67=Assumptions!$H$50, Assumptions!$D$50, 0)) -> 0 | S73: =IF(S67>Assumptions!$H$50, R73*(1+D87), IF(S67=Assumptions!$H$50, Assumptions!$D$50, 0)) -> 0 | T73: =IF(T67>Assumptions!$H$50, S73*(1+E87), IF(T67=Assumptions!$H$50, Assumptions!$D$50, 0)) -> 1900 | U73: =IF(U67>Assumptions!$H$50, T73*(1+F87), IF(U67=Assumptions!$H$50, Assumptions!$D$50, 0)) -> 1921.5638 | V73: =IF(V67>Assumptions!$H$50, U73*(1+G87), IF(V67=Assumptions!$H$50, Assumptions!$D$50, 0)) -> 1950.9366 | W73: =IF(W67>Assumptions!$H$50, V73*(1+H87), IF(W67=Assumptions!$H$50, Assumptions!$D$50, 0)) -> 1987.6762 | X73: =IF(X67>Assumptions!$H$50, W73*(1+I87), IF(X67=Assumptions!$H$50, Assumptions!$D$50, 0)) -> 2030.9204 | Y73: =IF(Y67>Assumptions!$H$50, X73*(1+J87), IF(Y67=Assumptions!$H$50, Assumptions!$D$50, 0)) -> 2080.2383 | Z73: =IF(Z67>Assumptions!$H$50, Y73*(1+K87), IF(Z67=Assumptions!$H$50, Assumptions!$D$50, 0)) -> 2138.336 | AB73: software stacks (one time) | AC73: =IF(AC67=Assumptions!$K$50, Assumptions!$P$50, 0) -> 0 | AD73: =IF(AD67>Assumptions!$K$50, AC73*(1+AC63), IF(AD67=Assumptions!$K$50, Assumptions!$P$50, 0)) -> 0 | AE73: =IF(AE67>Assumptions!$K$50, AD73*(1+AD63), IF(AE67=Assumptions!$K$50, Assumptions!$P$50, 0)) -> 0 | AF73: =IF(AF67>Assumptions!$K$50, AE73*(1+AE63), IF(AF67=Assumptions!$K$50, Assumptions!$P$50, 0)) -> 1900 | AG73: =IF(AG67>Assumptions!$K$50, AF73*(1+AF63), IF(AG67=Assumptions!$K$50, Assumptions!$P$50, 0)) -> 2090 | AH73: =IF(AH67>Assumptions!$K$50, AG73*(1+AG63), IF(AH67=Assumptions!$K$50, Assumptions!$P$50, 0)) -> 2299 | AI73: =IF(AI67>Assumptions!$K$50, AH73*(1+AH63), IF(AI67=Assumptions!$K$50, Assumptions!$P$50, 0)) -> 2528.9 | AJ73: =IF(AJ67>Assumptions!$K$50, AI73*(1+AI63), IF(AJ67=Assumptions!$K$50, Assumptions!$P$50, 0)) -> 2781.79 | AK73: =IF(AK67>Assumptions!$K$50, AJ73*(1+AJ63), IF(AK67=Assumptions!$K$50, Assumptions!$P$50, 0)) -> 3059.969 | AL73: =IF(AL67>Assumptions!$K$50, AK73*(1+AK63), IF(AL67=Assumptions!$K$50, Assumptions!$P$50, 0)) -> 3365.9659 | AP73: software stacks (one time) | AQ73: =IF(AQ67=Assumptions!$K$50, Assumptions!$D$50, 0) -> 0 | AR73: =IF(AR67>Assumptions!$K$50, AQ73*(1+AC87), IF(AR67=Assumptions!$K$50, Assumptions!$D$50, 0)) -> 0 | AS73: =IF(AS67>Assumptions!$K$50, AR73*(1+AD87), IF(AS67=Assumptions!$K$50, Assumptions!$D$50, 0)) -> 0 | AT73: =IF(AT67>Assumptions!$K$50, AS73*(1+AE87), IF(AT67=Assumptions!$K$50, Assumptions!$D$50, 0)) -> 1900 | AU73: =IF(AU67>Assumptions!$K$50, AT73*(1+AF87), IF(AU67=Assumptions!$K$50, Assumptions!$D$50, 0)) -> 1918.5528 | AV73: =IF(AV67>Assumptions!$K$50, AU73*(1+AG87), IF(AV67=Assumptions!$K$50, Assumptions!$D$50, 0)) -> 1944.1265 | AW73: =IF(AW67>Assumptions!$K$50, AV73*(1+AH87), IF(AW67=Assumptions!$K$50, Assumptions!$D$50, 0)) -> 1976.6749 | AX73: =IF(AX67>Assumptions!$K$50, AW73*(1+AI87), IF(AX67=Assumptions!$K$50, Assumptions!$D$50, 0)) -> 2017.6479 | AY73: =IF(AY67>Assumptions!$K$50, AX73*(1+AJ87), IF(AY67=Assumptions!$K$50, Assumptions!$D$50, 0)) -> 2067.5091 | AZ73: =IF(AZ67>Assumptions!$K$50, AY73*(1+AK87), IF(AZ67=Assumptions!$K$50, Assumptions!$D$50, 0)) -> 2125.9846
B74: software stacks (subscription) | C74: =IF(C$67=Assumptions!$H$51, Assumptions!$P$51, 0) -> 0 | D74: =IF(D67>Assumptions!$H$51, C74, IF(D67=Assumptions!$H$51, Assumptions!$P$51, 0)) -> 0 | E74: =IF(E67>Assumptions!$H$51, D74, IF(E67=Assumptions!$H$51, Assumptions!$P$51, 0)) -> 0 | F74: =IF(F67>Assumptions!$H$51, E74, IF(F67=Assumptions!$H$51, Assumptions!$P$51, 0)) -> 0 | G74: =IF(G67>Assumptions!$H$51, F74, IF(G67=Assumptions!$H$51, Assumptions!$P$51, 0)) -> 500 | H74: =IF(H67>Assumptions!$H$51, G74, IF(H67=Assumptions!$H$51, Assumptions!$P$51, 0)) -> 500 | I74: =IF(I67>Assumptions!$H$51, H74, IF(I67=Assumptions!$H$51, Assumptions!$P$51, 0)) -> 500 | J74: =IF(J67>Assumptions!$H$51, I74, IF(J67=Assumptions!$H$51, Assumptions!$P$51, 0)) -> 500 | K74: =IF(K67>Assumptions!$H$51, J74, IF(K67=Assumptions!$H$51, Assumptions!$P$51, 0)) -> 500 | L74: =IF(L67>Assumptions!$H$51, K74, IF(L67=Assumptions!$H$51, Assumptions!$P$51, 0)) -> 500 | P74: software stacks (subscription) | Q74: =IF(Q$67=Assumptions!$H$51, Assumptions!$D51, 0) -> 0 | R74: =IF(R67>Assumptions!$H$50, Q74*(1-Assumptions!$V$19) + Assumptions!$D$51*(1+C87), IF(R67=Assumptions!$H$50, Assumptions!$D$51, 0)) -> 0 | S74: =IF(S67>Assumptions!$H$50, R74*(1-Assumptions!$V$19) + Assumptions!$D$51*(1+D87), IF(S67=Assumptions!$H$50, Assumptions!$D$51, 0)) -> 0 | T74: =IF(T67>Assumptions!$H$50, S74*(1-Assumptions!$V$19) + Assumptions!$D$51*(1+E87), IF(T67=Assumptions!$H$50, Assumptions!$D$51, 0)) -> 400 | U74: =IF(U67>Assumptions!$H$50, T74*(1-Assumptions!$V$19) + Assumptions!$D$51*(1+F87), IF(U67=Assumptions!$H$50, Assumptions!$D$51, 0)) -> 752.53975 | V74: =IF(V67>Assumptions!$H$50, U74*(1-Assumptions!$V$19) + Assumptions!$D$51*(1+G87), IF(V67=Assumptions!$H$50, Assumptions!$D$51, 0)) -> 1060.8239 | W74: =IF(W67>Assumptions!$H$50, V74*(1-Assumptions!$V$19) + Assumptions!$D$51*(1+H87), IF(W67=Assumptions!$H$50, Assumptions!$D$51, 0)) -> 1330.4495 | X74: =IF(X67>Assumptions!$H$50, W74*(1-Assumptions!$V$19) + Assumptions!$D$51*(1+I87), IF(X67=Assumptions!$H$50, Assumptions!$D$51, 0)) -> 1566.1936 | Y74: =IF(Y67>Assumptions!$H$50, X74*(1-Assumptions!$V$19) + Assumptions!$D$51*(1+J87), IF(Y67=Assumptions!$H$50, Assumptions!$D$51, 0)) -> 1772.3018 | Z74: =IF(Z67>Assumptions!$H$50, Y74*(1-Assumptions!$V$19) + Assumptions!$D$51*(1+K87), IF(Z67=Assumptions!$H$50, Assumptions!$D$51, 0)) -> 1953.0739 | AB74: software stacks (subscription) | AC74: =IF(AC68=Assumptions!$K$50, Assumptions!$P$51, 0) -> 0 | AD74: =IF(AD67>Assumptions!$K$51, AC74, IF(AD67=Assumptions!$K$51, Assumptions!$P$51, 0)) -> 0 | AE74: =IF(AE67>Assumptions!$K$51, AD74, IF(AE67=Assumptions!$K$51, Assumptions!$P$51, 0)) -> 0 | AF74: =IF(AF67>Assumptions!$K$51, AE74, IF(AF67=Assumptions!$K$51, Assumptions!$P$51, 0)) -> 0 | AG74: =IF(AG67>Assumptions!$K$51, AF74, IF(AG67=Assumptions!$K$51, Assumptions!$P$51, 0)) -> 500 | AH74: =IF(AH67>Assumptions!$K$51, AG74, IF(AH67=Assumptions!$K$51, Assumptions!$P$51, 0)) -> 500 | AI74: =IF(AI67>Assumptions!$K$51, AH74, IF(AI67=Assumptions!$K$51, Assumptions!$P$51, 0)) -> 500 | AJ74: =IF(AJ67>Assumptions!$K$51, AI74, IF(AJ67=Assumptions!$K$51, Assumptions!$P$51, 0)) -> 500 | AK74: =IF(AK67>Assumptions!$K$51, AJ74, IF(AK67=Assumptions!$K$51, Assumptions!$P$51, 0)) -> 500 | AL74: =IF(AL67>Assumptions!$K$51, AK74, IF(AL67=Assumptions!$K$51, Assumptions!$P$51, 0)) -> 500 | AP74: software stacks (subscription) | AQ74: =IF(AQ67=Assumptions!$K$51, Assumptions!$D$51, 0) -> 0 | AR74: =IF(AR67>Assumptions!$K$51, AQ74*(1-Assumptions!$V$20) + Assumptions!$D$51*(1+AC87), IF(AR67=Assumptions!$K$51, Assumptions!$D$51, 0)) -> 0 | AS74: =IF(AS67>Assumptions!$K$51, AR74*(1-Assumptions!$V$20) + Assumptions!$D$51*(1+AD87), IF(AS67=Assumptions!$K$51, Assumptions!$D$51, 0)) -> 0 | AT74: =IF(AT67>Assumptions!$K$51, AS74*(1-Assumptions!$V$20) + Assumptions!$D$51*(1+AE87), IF(AT67=Assumptions!$K$51, Assumptions!$D$51, 0)) -> 0 | AU74: =IF(AU67>Assumptions!$K$51, AT74*(1-Assumptions!$V$20) + Assumptions!$D$51*(1+AF87), IF(AU67=Assumptions!$K$51, Assumptions!$D$51, 0)) -> 400 | AV74: =IF(AV67>Assumptions!$K$51, AU74*(1-Assumptions!$V$20) + Assumptions!$D$51*(1+AG87), IF(AV67=Assumptions!$K$51, Assumptions!$D$51, 0)) -> 761.33186 | AW74: =IF(AW67>Assumptions!$K$51, AV74*(1-Assumptions!$V$20) + Assumptions!$D$51*(1+AH87), IF(AW67=Assumptions!$K$51, Assumptions!$D$51, 0)) -> 1084.2821 | AX74: =IF(AX67>Assumptions!$K$51, AW74*(1-Assumptions!$V$20) + Assumptions!$D$51*(1+AI87), IF(AX67=Assumptions!$K$51, Assumptions!$D$51, 0)) -> 1373.3024 | AY74: =IF(AY67>Assumptions!$K$51, AX74*(1-Assumptions!$V$20) + Assumptions!$D$51*(1+AJ87), IF(AY67=Assumptions!$K$51, Assumptions!$D$51, 0)) -> 1632.1241 | AZ74: =IF(AZ67>Assumptions!$K$51, AY74*(1-Assumptions!$V$20) + Assumptions!$D$51*(1+AK87), IF(AZ67=Assumptions!$K$51, Assumptions!$D$51, 0)) -> 1863.9037
B75: system integration | C75: =IF(C$67=Assumptions!$H$52, Assumptions!$P$52, 0) -> 0 | D75: =IF(D67>Assumptions!$H$52, C75*(1+C63), IF(D67=Assumptions!$H$52, Assumptions!$P$52, 0)) -> 0 | E75: =IF(E67>Assumptions!$H$52, D75*(1+D63), IF(E67=Assumptions!$H$52, Assumptions!$P$52, 0)) -> 0 | F75: =IF(F67>Assumptions!$H$52, E75*(1+E63), IF(F67=Assumptions!$H$52, Assumptions!$P$52, 0)) -> 0 | G75: =IF(G67>Assumptions!$H$52, F75*(1+F63), IF(G67=Assumptions!$H$52, Assumptions!$P$52, 0)) -> 500 | H75: =IF(H67>Assumptions!$H$52, G75*(1+G63), IF(H67=Assumptions!$H$52, Assumptions!$P$52, 0)) -> 515.75 | I75: =IF(I67>Assumptions!$H$52, H75*(1+H63), IF(I67=Assumptions!$H$52, Assumptions!$P$52, 0)) -> 531.99613 | J75: =IF(J67>Assumptions!$H$52, I75*(1+I63), IF(J67=Assumptions!$H$52, Assumptions!$P$52, 0)) -> 548.754 | K75: =IF(K67>Assumptions!$H$52, J75*(1+J63), IF(K67=Assumptions!$H$52, Assumptions!$P$52, 0)) -> 566.03975 | L75: =IF(L67>Assumptions!$H$52, K75*(1+K63), IF(L67=Assumptions!$H$52, Assumptions!$P$52, 0)) -> 583.87001 | P75: system integration | Q75: =IF(Q$67=Assumptions!$H$52, Assumptions!$D52, 0) -> 0 | R75: =IF(R67>Assumptions!$H$52, Q75*(1+C88), IF(R67=Assumptions!$H$52, Assumptions!$D$52, 0)) -> 0 | S75: =IF(S67>Assumptions!$H$52, R75*(1+D88), IF(S67=Assumptions!$H$52, Assumptions!$D$52, 0)) -> 0 | T75: =IF(T67>Assumptions!$H$52, S75*(1+E88), IF(T67=Assumptions!$H$52, Assumptions!$D$52, 0)) -> 0 | U75: =IF(U67>Assumptions!$H$52, T75*(1+F88), IF(U67=Assumptions!$H$52, Assumptions!$D$52, 0)) -> 300 | V75: =IF(V67>Assumptions!$H$52, U75*(1+G88), IF(V67=Assumptions!$H$52, Assumptions!$D$52, 0)) -> 304.31533 | W75: =IF(W67>Assumptions!$H$52, V75*(1+H88), IF(W67=Assumptions!$H$52, Assumptions!$D$52, 0)) -> 309.89287 | X75: =IF(X67>Assumptions!$H$52, W75*(1+I88), IF(X67=Assumptions!$H$52, Assumptions!$D$52, 0)) -> 316.74077 | Y75: =IF(Y67>Assumptions!$H$52, X75*(1+J88), IF(Y67=Assumptions!$H$52, Assumptions!$D$52, 0)) -> 324.69639 | Z75: =IF(Z67>Assumptions!$H$52, Y75*(1+K88), IF(Z67=Assumptions!$H$52, Assumptions!$D$52, 0)) -> 334.13921 | AB75: system integration | AC75: =IF(AC67=Assumptions!$K$52, Assumptions!$P$52, 0) -> 0 | AD75: =IF(AD67>Assumptions!$K$52, AC75*(1+AC63), IF(AD67=Assumptions!$K$52, Assumptions!$P$52, 0)) -> 0 | AE75: =IF(AE67>Assumptions!$K$52, AD75*(1+AD63), IF(AE67=Assumptions!$K$52, Assumptions!$P$52, 0)) -> 0 | AF75: =IF(AF67>Assumptions!$K$52, AE75*(1+AE63), IF(AF67=Assumptions!$K$52, Assumptions!$P$52, 0)) -> 0 | AG75: =IF(AG67>Assumptions!$K$52, AF75*(1+AF63), IF(AG67=Assumptions!$K$52, Assumptions!$P$52, 0)) -> 500 | AH75: =IF(AH67>Assumptions!$K$52, AG75*(1+AG63), IF(AH67=Assumptions!$K$52, Assumptions!$P$52, 0)) -> 550 | AI75: =IF(AI67>Assumptions!$K$52, AH75*(1+AH63), IF(AI67=Assumptions!$K$52, Assumptions!$P$52, 0)) -> 605 | AJ75: =IF(AJ67>Assumptions!$K$52, AI75*(1+AI63), IF(AJ67=Assumptions!$K$52, Assumptions!$P$52, 0)) -> 665.5 | AK75: =IF(AK67>Assumptions!$K$52, AJ75*(1+AJ63), IF(AK67=Assumptions!$K$52, Assumptions!$P$52, 0)) -> 732.05 | AL75: =IF(AL67>Assumptions!$K$52, AK75*(1+AK63), IF(AL67=Assumptions!$K$52, Assumptions!$P$52, 0)) -> 805.255 | AP75: system integration | AQ75: =IF(AQ67=Assumptions!$K$52, Assumptions!$D$52, 0) -> 0 | AR75: =IF(AR67>Assumptions!$K$52, AQ75*(1+AC88), IF(AR67=Assumptions!$K$52, Assumptions!$D$52, 0)) -> 0 | AS75: =IF(AS67>Assumptions!$K$52, AR75*(1+AD88), IF(AS67=Assumptions!$K$52, Assumptions!$D$52, 0)) -> 0 | AT75: =IF(AT67>Assumptions!$K$52, AS75*(1+AE88), IF(AT67=Assumptions!$K$52, Assumptions!$D$52, 0)) -> 0 | AU75: =IF(AU67>Assumptions!$K$52, AT75*(1+AF88), IF(AU67=Assumptions!$K$52, Assumptions!$D$52, 0)) -> 300 | AV75: =IF(AV67>Assumptions!$K$52, AU75*(1+AG88), IF(AV67=Assumptions!$K$52, Assumptions!$D$52, 0)) -> 303.76899 | AW75: =IF(AW67>Assumptions!$K$52, AV75*(1+AH88), IF(AW67=Assumptions!$K$52, Assumptions!$D$52, 0)) -> 308.44019 | AX75: =IF(AX67>Assumptions!$K$52, AW75*(1+AI88), IF(AX67=Assumptions!$K$52, Assumptions!$D$52, 0)) -> 314.40844 | AY75: =IF(AY67>Assumptions!$K$52, AX75*(1+AJ88), IF(AY67=Assumptions!$K$52, Assumptions!$D$52, 0)) -> 321.74592 | AZ75: =IF(AZ67>Assumptions!$K$52, AY75*(1+AK88), IF(AZ67=Assumptions!$K$52, Assumptions!$D$52, 0)) -> 330.39272
B76: liscencing | C76: =IF(C$67=Assumptions!$H$53, Assumptions!$P$53, 0) -> 0 | D76: =IF(D67>Assumptions!$H$53, C76*(1+C63), IF(D67=Assumptions!$H$53, Assumptions!$P$53, 0)) -> 0 | E76: =IF(E67>Assumptions!$H$53, D76*(1+D63), IF(E67=Assumptions!$H$53, Assumptions!$P$53, 0)) -> 0 | F76: =IF(F67>Assumptions!$H$53, E76*(1+E63), IF(F67=Assumptions!$H$53, Assumptions!$P$53, 0)) -> 0 | G76: =IF(G67>Assumptions!$H$53, F76*(1+F63), IF(G67=Assumptions!$H$53, Assumptions!$P$53, 0)) -> 300 | H76: =IF(H67>Assumptions!$H$53, G76*(1+G63), IF(H67=Assumptions!$H$53, Assumptions!$P$53, 0)) -> 309.45 | I76: =IF(I67>Assumptions!$H$53, H76*(1+H63), IF(I67=Assumptions!$H$53, Assumptions!$P$53, 0)) -> 319.19768 | J76: =IF(J67>Assumptions!$H$53, I76*(1+I63), IF(J67=Assumptions!$H$53, Assumptions!$P$53, 0)) -> 329.2524 | K76: =IF(K67>Assumptions!$H$53, J76*(1+J63), IF(K67=Assumptions!$H$53, Assumptions!$P$53, 0)) -> 339.62385 | L76: =IF(L67>Assumptions!$H$53, K76*(1+K63), IF(L67=Assumptions!$H$53, Assumptions!$P$53, 0)) -> 350.322 | P76: liscencing | Q76: =IF(Q$67=Assumptions!$H$53, Assumptions!$D53, 0) -> 0 | R76: =IF(R67>Assumptions!$H$53, Q76*(1+C89), IF(R67=Assumptions!$H$53, Assumptions!$D$53, 0)) -> 0 | S76: =IF(S67>Assumptions!$H$53, R76*(1+D89), IF(S67=Assumptions!$H$53, Assumptions!$D$53, 0)) -> 0 | T76: =IF(T67>Assumptions!$H$53, S76*(1+E89), IF(T67=Assumptions!$H$53, Assumptions!$D$53, 0)) -> 0 | U76: =IF(U67>Assumptions!$H$53, T76*(1+F89), IF(U67=Assumptions!$H$53, Assumptions!$D$53, 0)) -> 1500 | V76: =IF(V67>Assumptions!$H$53, U76*(1+G89), IF(V67=Assumptions!$H$53, Assumptions!$D$53, 0)) -> 1521.7094 | W76: =IF(W67>Assumptions!$H$53, V76*(1+H89), IF(W67=Assumptions!$H$53, Assumptions!$D$53, 0)) -> 1549.0098 | X76: =IF(X67>Assumptions!$H$53, W76*(1+I89), IF(X67=Assumptions!$H$53, Assumptions!$D$53, 0)) -> 1581.5219 | Y76: =IF(Y67>Assumptions!$H$53, X76*(1+J89), IF(Y67=Assumptions!$H$53, Assumptions!$D$53, 0)) -> 1621.0109 | Z76: =IF(Z67>Assumptions!$H$53, Y76*(1+K89), IF(Z67=Assumptions!$H$53, Assumptions!$D$53, 0)) -> 1665.6996 | AB76: liscencing | AC76: =IF(AC67=Assumptions!$K$53, Assumptions!$P$53, 0) -> 0 | AD76: =IF(AD67>Assumptions!$K$53, AC76*(1+AC63), IF(AD67=Assumptions!$K$53, Assumptions!$P$53, 0)) -> 0 | AE76: =IF(AE67>Assumptions!$K$53, AD76*(1+AD63), IF(AE67=Assumptions!$K$53, Assumptions!$P$53, 0)) -> 0 | AF76: =IF(AF67>Assumptions!$K$53, AE76*(1+AE63), IF(AF67=Assumptions!$K$53, Assumptions!$P$53, 0)) -> 0 | AG76: =IF(AG67>Assumptions!$K$53, AF76*(1+AF63), IF(AG67=Assumptions!$K$53, Assumptions!$P$53, 0)) -> 300 | AH76: =IF(AH67>Assumptions!$K$53, AG76*(1+AG63), IF(AH67=Assumptions!$K$53, Assumptions!$P$53, 0)) -> 330 | AI76: =IF(AI67>Assumptions!$K$53, AH76*(1+AH63), IF(AI67=Assumptions!$K$53, Assumptions!$P$53, 0)) -> 363 | AJ76: =IF(AJ67>Assumptions!$K$53, AI76*(1+AI63), IF(AJ67=Assumptions!$K$53, Assumptions!$P$53, 0)) -> 399.3 | AK76: =IF(AK67>Assumptions!$K$53, AJ76*(1+AJ63), IF(AK67=Assumptions!$K$53, Assumptions!$P$53, 0)) -> 439.23 | AL76: =IF(AL67>Assumptions!$K$53, AK76*(1+AK63), IF(AL67=Assumptions!$K$53, Assumptions!$P$53, 0)) -> 483.153 | AP76: liscencing | AQ76: =IF(AQ67=Assumptions!$K$53, Assumptions!$D$53, 0) -> 0 | AR76: =IF(AR67>Assumptions!$K$53, AQ76*(1+AC89), IF(AR67=Assumptions!$K$53, Assumptions!$D$53, 0)) -> 0 | AS76: =IF(AS67>Assumptions!$K$53, AR76*(1+AD89), IF(AS67=Assumptions!$K$53, Assumptions!$D$53, 0)) -> 0 | AT76: =IF(AT67>Assumptions!$K$53, AS76*(1+AE89), IF(AT67=Assumptions!$K$53, Assumptions!$D$53, 0)) -> 0 | AU76: =IF(AU67>Assumptions!$K$53, AT76*(1+AF89), IF(AU67=Assumptions!$K$53, Assumptions!$D$53, 0)) -> 1500 | AV76: =IF(AV67>Assumptions!$K$53, AU76*(1+AG89), IF(AV67=Assumptions!$K$53, Assumptions!$D$53, 0)) -> 1522.2439 | AW76: =IF(AW67>Assumptions!$K$53, AV76*(1+AH89), IF(AW67=Assumptions!$K$53, Assumptions!$D$53, 0)) -> 1549.2297 | AX76: =IF(AX67>Assumptions!$K$53, AW76*(1+AI89), IF(AX67=Assumptions!$K$53, Assumptions!$D$53, 0)) -> 1582.5631 | AY76: =IF(AY67>Assumptions!$K$53, AX76*(1+AJ89), IF(AY67=Assumptions!$K$53, Assumptions!$D$53, 0)) -> 1622.5839 | AZ76: =IF(AZ67>Assumptions!$K$53, AY76*(1+AK89), IF(AZ67=Assumptions!$K$53, Assumptions!$D$53, 0)) -> 1668.7821
B77: maintenance | C77: =IF(C$67=Assumptions!$H$54, Assumptions!$P$54, 0) -> 0 | D77: =IF(D67>Assumptions!$H$54, C77*(1+C63), IF(D67=Assumptions!$H$54, Assumptions!$P$54, 0)) -> 0 | E77: =IF(E67>Assumptions!$H$54, D77*(1+D63), IF(E67=Assumptions!$H$54, Assumptions!$P$54, 0)) -> 0 | F77: =IF(F67>Assumptions!$H$54, E77*(1+E63), IF(F67=Assumptions!$H$54, Assumptions!$P$54, 0)) -> 0 | G77: =IF(G67>Assumptions!$H$54, F77*(1+F63), IF(G67=Assumptions!$H$54, Assumptions!$P$54, 0)) -> 700 | H77: =IF(H67>Assumptions!$H$54, G77*(1+G63), IF(H67=Assumptions!$H$54, Assumptions!$P$54, 0)) -> 722.05 | I77: =IF(I67>Assumptions!$H$54, H77*(1+H63), IF(I67=Assumptions!$H$54, Assumptions!$P$54, 0)) -> 744.79458 | J77: =IF(J67>Assumptions!$H$54, I77*(1+I63), IF(J67=Assumptions!$H$54, Assumptions!$P$54, 0)) -> 768.2556 | K77: =IF(K67>Assumptions!$H$54, J77*(1+J63), IF(K67=Assumptions!$H$54, Assumptions!$P$54, 0)) -> 792.45566 | L77: =IF(L67>Assumptions!$H$54, K77*(1+K63), IF(L67=Assumptions!$H$54, Assumptions!$P$54, 0)) -> 817.41801 | P77: maintenance | Q77: =IF(Q$67=Assumptions!$H$54, Assumptions!$D54, 0) -> 0 | R77: =IF(R67>Assumptions!$H$54, Q77*(1+C90), IF(R67=Assumptions!$H$54, Assumptions!$D$54, 0)) -> 0 | S77: =IF(S67>Assumptions!$H$54, R77*(1+D90), IF(S67=Assumptions!$H$54, Assumptions!$D$54, 0)) -> 0 | T77: =IF(T67>Assumptions!$H$54, S77*(1+E90), IF(T67=Assumptions!$H$54, Assumptions!$D$54, 0)) -> 0 | U77: =IF(U67>Assumptions!$H$54, T77*(1+F90), IF(U67=Assumptions!$H$54, Assumptions!$D$54, 0)) -> 700 | V77: =IF(V67>Assumptions!$H$54, U77*(1+G90), IF(V67=Assumptions!$H$54, Assumptions!$D$54, 0)) -> 708.87906 | W77: =IF(W67>Assumptions!$H$54, V77*(1+H90), IF(W67=Assumptions!$H$54, Assumptions!$D$54, 0)) -> 720.69475 | X77: =IF(X67>Assumptions!$H$54, W77*(1+I90), IF(X67=Assumptions!$H$54, Assumptions!$D$54, 0)) -> 735.23924 | Y77: =IF(Y67>Assumptions!$H$54, X77*(1+J90), IF(Y67=Assumptions!$H$54, Assumptions!$D$54, 0)) -> 752.38475 | Z77: =IF(Z67>Assumptions!$H$54, Y77*(1+K90), IF(Z67=Assumptions!$H$54, Assumptions!$D$54, 0)) -> 772.91902 | AB77: maintenance | AC77: =IF(AC67=Assumptions!$K$54, Assumptions!$P$54, 0) -> 0 | AD77: =IF(AD67>Assumptions!$K$54, AC77*(1+AC63), IF(AD67=Assumptions!$K$54, Assumptions!$P$54, 0)) -> 0 | AE77: =IF(AE67>Assumptions!$K$54, AD77*(1+AD63), IF(AE67=Assumptions!$K$54, Assumptions!$P$54, 0)) -> 0 | AF77: =IF(AF67>Assumptions!$K$54, AE77*(1+AE63), IF(AF67=Assumptions!$K$54, Assumptions!$P$54, 0)) -> 0 | AG77: =IF(AG67>Assumptions!$K$54, AF77*(1+AF63), IF(AG67=Assumptions!$K$54, Assumptions!$P$54, 0)) -> 700 | AH77: =IF(AH67>Assumptions!$K$54, AG77*(1+AG63), IF(AH67=Assumptions!$K$54, Assumptions!$P$54, 0)) -> 770 | AI77: =IF(AI67>Assumptions!$K$54, AH77*(1+AH63), IF(AI67=Assumptions!$K$54, Assumptions!$P$54, 0)) -> 847 | AJ77: =IF(AJ67>Assumptions!$K$54, AI77*(1+AI63), IF(AJ67=Assumptions!$K$54, Assumptions!$P$54, 0)) -> 931.7 | AK77: =IF(AK67>Assumptions!$K$54, AJ77*(1+AJ63), IF(AK67=Assumptions!$K$54, Assumptions!$P$54, 0)) -> 1024.87 | AL77: =IF(AL67>Assumptions!$K$54, AK77*(1+AK63), IF(AL67=Assumptions!$K$54, Assumptions!$P$54, 0)) -> 1127.357 | AP77: maintenance | AQ77: =IF(AQ67=Assumptions!$J$53, Assumptions!$D$54, 0) -> 0 | AR77: =IF(AR67>Assumptions!$K$54, AQ77*(1+AC90), IF(AR67=Assumptions!$K$54, Assumptions!$D$54, 0)) -> 0 | AS77: =IF(AS67>Assumptions!$K$54, AR77*(1+AD90), IF(AS67=Assumptions!$K$54, Assumptions!$D$54, 0)) -> 0 | AT77: =IF(AT67>Assumptions!$K$54, AS77*(1+AE90), IF(AT67=Assumptions!$K$54, Assumptions!$D$54, 0)) -> 0 | AU77: =IF(AU67>Assumptions!$K$54, AT77*(1+AF90), IF(AU67=Assumptions!$K$54, Assumptions!$D$54, 0)) -> 700 | AV77: =IF(AV67>Assumptions!$K$54, AU77*(1+AG90), IF(AV67=Assumptions!$K$54, Assumptions!$D$54, 0)) -> 710.23683 | AW77: =IF(AW67>Assumptions!$K$54, AV77*(1+AH90), IF(AW67=Assumptions!$K$54, Assumptions!$D$54, 0)) -> 723.38409 | AX77: =IF(AX67>Assumptions!$K$54, AW77*(1+AI90), IF(AX67=Assumptions!$K$54, Assumptions!$D$54, 0)) -> 738.65416 | AY77: =IF(AY67>Assumptions!$K$54, AX77*(1+AJ90), IF(AY67=Assumptions!$K$54, Assumptions!$D$54, 0)) -> 756.64471 | AZ77: =IF(AZ67>Assumptions!$K$54, AY77*(1+AK90), IF(AZ67=Assumptions!$K$54, Assumptions!$D$54, 0)) -> 778.03568
C80: Year | Q80: Year | AC80: Year | AQ80: Year
C81: 1 | D81: 2 | E81: 3 | F81: 4 | G81: 5 | H81: 6 | I81: 7 | J81: 8 | K81: 9 | L81: 10 | P81: REVENUE FROM SALES | Q81: 1 | R81: 2 | S81: 3 | T81: 4 | U81: 5 | V81: 6 | W81: 7 | X81: 8 | Y81: 9 | Z81: 10 | AC81: 1 | AD81: 2 | AE81: 3 | AF81: 4 | AG81: 5 | AH81: 6 | AI81: 7 | AJ81: 8 | AK81: 9 | AL81: 10 | AP81: REVENUE FROM SALES | AQ81: 1 | AR81: 2 | AS81: 3 | AT81: 4 | AU81: 5 | AV81: 6 | AW81: 7 | AX81: 8 | AY81: 9 | AZ81: 10
B82: Drone | C82: 0.05 | D82: =C82+_xlfn.NORM.DIST(RAND(), 0, 1, FALSE)% -> 0.053329574 | E82: =D82+_xlfn.NORM.DIST(RAND(), 0, 1, FALSE)% -> 0.057309526 | F82: =E82+_xlfn.NORM.DIST(RAND(), 0, 1, FALSE)% -> 0.060785643 | G82: =F82+_xlfn.NORM.DIST(RAND(), 0, 1, FALSE)% -> 0.064283552 | H82: =G82+_xlfn.NORM.DIST(RAND(), 0, 1, FALSE)% -> 0.068271426 | I82: =H82+_xlfn.NORM.DIST(RAND(), 0, 1, FALSE)% -> 0.070932129 | J82: =I82+_xlfn.NORM.DIST(RAND(), 0, 1, FALSE)% -> 0.07348457 | K82: =J82+_xlfn.NORM.DIST(RAND(), 0, 1, FALSE)% -> 0.076762917 | L82: =K82+_xlfn.NORM.DIST(RAND(), 0, 1, FALSE)% -> 0.080219451 | P82: Drone | Q82: =C68*Q68 -> 0 | R82: =D68*R68 -> 0 | S82: =E68*S68 -> 0 | T82: =F68*T68 -> 7700000 | U82: =G68*U68 -> 8425343 | V82: =H68*V68 -> 9249413 | W82: =I68*W68 -> 10192131 | X82: =J68*X68 -> 11258906 | ... Z82: =L68*Z68 -> 13846836 | AB82: Drone | AC82: 0.02 | AD82: =AC82+_xlfn.NORM.DIST(RAND(), 0, 1, FALSE)% -> 0.023522638 | AE82: =AD82+_xlfn.NORM.DIST(RAND(), 0, 1, FALSE)% -> 0.026853788 | AF82: =AE82+_xlfn.NORM.DIST(RAND(), 0, 1, FALSE)% -> 0.030746737 | AG82: =AF82+_xlfn.NORM.DIST(RAND(), 0, 1, FALSE)% -> 0.034626054 | AH82: =AG82+_xlfn.NORM.DIST(RAND(), 0, 1, FALSE)% -> 0.038604603 | AI82: =AH82+_xlfn.NORM.DIST(RAND(), 0, 1, FALSE)% -> 0.042554451 | AJ82: =AI82+_xlfn.NORM.DIST(RAND(), 0, 1, FALSE)% -> 0.046480539 | AK82: =AJ82+_xlfn.NORM.DIST(RAND(), 0, 1, FALSE)% -> 0.049185229 | AL82: =AK82+_xlfn.NORM.DIST(RAND(), 0, 1, FALSE)% -> 0.052417446 | AP82: Drone | AQ82: =AC68*AQ68 -> 0 | AR82: =AD68*AR68 -> 0 | AS82: =AE68*AS68 -> 0 | AT82: =AF68*AT68 -> 7700000 | AU82: =AG68*AU68 -> 8730424.9 | AV82: =AH68*AV68 -> 9935997.5 | AW82: =AI68*AW68 -> 11351530 | AX82: =AJ68*AX68 -> 13018047 | ... AZ82: =AL68*AZ68 -> 17294760
B83: Rover | C83: 0.09 | D83: =C83+_xlfn.NORM.DIST(RAND(), 0, 1, FALSE)% -> 0.093949057 | E83: =D83+_xlfn.NORM.DIST(RAND(), 0, 1, FALSE)% -> 0.09718572 | F83: =E83+_xlfn.NORM.DIST(RAND(), 0, 1, FALSE)% -> 0.10082292 | G83: =F83+_xlfn.NORM.DIST(RAND(), 0, 1, FALSE)% -> 0.10377523 | H83: =G83+_xlfn.NORM.DIST(RAND(), 0, 1, FALSE)% -> 0.10744647 | I83: =H83+_xlfn.NORM.DIST(RAND(), 0, 1, FALSE)% -> 0.11081908 | J83: =I83+_xlfn.NORM.DIST(RAND(), 0, 1, FALSE)% -> 0.11468948 | K83: =J83+_xlfn.NORM.DIST(RAND(), 0, 1, FALSE)% -> 0.11750006 | L83: =K83+_xlfn.NORM.DIST(RAND(), 0, 1, FALSE)% -> 0.12062775 | P83: Rover | Q83: =C69*Q69 -> 0 | R83: =D69*R69 -> 0 | S83: =E69*S69 -> 0 | T83: =F69*T69 -> 7000000 | U83: =G69*U69 -> 7948491.9 | V83: =H69*V69 -> 9049708.9 | W83: =I69*W69 -> 10337763 | X83: =J69*X69 -> 11845111 | ... Z83: =L69*Z69 -> 15699256 | AB83: Rover | AC83: 0.04 | AD83: =AC83+_xlfn.NORM.DIST(RAND(), 0, 1, FALSE)% -> 0.04398936 | AE83: =AD83+_xlfn.NORM.DIST(RAND(), 0, 1, FALSE)% -> 0.047766754 | AF83: =AE83+_xlfn.NORM.DIST(RAND(), 0, 1, FALSE)% -> 0.050219952 | AG83: =AF83+_xlfn.NORM.DIST(RAND(), 0, 1, FALSE)% -> 0.054208206 | AH83: =AG83+_xlfn.NORM.DIST(RAND(), 0, 1, FALSE)% -> 0.057246516 | AI83: =AH83+_xlfn.NORM.DIST(RAND(), 0, 1, FALSE)% -> 0.061235926 | AJ83: =AI83+_xlfn.NORM.DIST(RAND(), 0, 1, FALSE)% -> 0.065155238 | AK83: =AJ83+_xlfn.NORM.DIST(RAND(), 0, 1, FALSE)% -> 0.069114388 | AL83: =AK83+_xlfn.NORM.DIST(RAND(), 0, 1, FALSE)% -> 0.07233461 | AP83: Rover | AQ83: =AC69*AQ69 -> 0 | AR83: =AD69*AR69 -> 0 | AS83: =AE69*AS69 -> 0 | AT83: =AF69*AT69 -> 7000000 | AU83: =AG69*AU69 -> 8086693.6 | AV83: =AH69*AV69 -> 9377564.7 | AW83: =AI69*AW69 -> 10905837 | AX83: =AJ69*AX69 -> 12731033 | ... AZ83: =AL69*AZ69 -> 17542282
B84: Edge | C84: 0.02 | D84: =C84+_xlfn.NORM.DIST(RAND(), 0, 1, FALSE)% -> 0.023974818 | E84: =D84+_xlfn.NORM.DIST(RAND(), 0, 1, FALSE)% -> 0.027740679 | F84: =E84+_xlfn.NORM.DIST(RAND(), 0, 1, FALSE)% -> 0.03157889 | G84: =F84+_xlfn.NORM.DIST(RAND(), 0, 1, FALSE)% -> 0.035151741 | H84: =G84+_xlfn.NORM.DIST(RAND(), 0, 1, FALSE)% -> 0.03912287 | I84: =H84+_xlfn.NORM.DIST(RAND(), 0, 1, FALSE)% -> 0.043080507 | J84: =I84+_xlfn.NORM.DIST(RAND(), 0, 1, FALSE)% -> 0.046459919 | K84: =J84+_xlfn.NORM.DIST(RAND(), 0, 1, FALSE)% -> 0.050425776 | L84: =K84+_xlfn.NORM.DIST(RAND(), 0, 1, FALSE)% -> 0.054161616 | P84: Edge | Q84: =C70*Q70 -> 0 | R84: =D70*R70 -> 0 | S84: =E70*S70 -> 0 | T84: =F70*T70 -> 6350000 | U84: =G70*U70 -> 6756867.5 | V84: =H70*V70 -> 7214706.2 | W84: =I70*W70 -> 7733120.7 | X84: =J70*X70 -> 8320354.9 | ... Z84: =L70*Z70 -> 9731242.3 | AB84: Edge | AC84: 0.03 | AD84: =AC84+_xlfn.NORM.DIST(RAND(), 0, 1, FALSE)% -> 0.032533487 | AE84: =AD84+_xlfn.NORM.DIST(RAND(), 0, 1, FALSE)% -> 0.035390423 | AF84: =AE84+_xlfn.NORM.DIST(RAND(), 0, 1, FALSE)% -> 0.038965989 | AG84: =AF84+_xlfn.NORM.DIST(RAND(), 0, 1, FALSE)% -> 0.041410022 | AH84: =AG84+_xlfn.NORM.DIST(RAND(), 0, 1, FALSE)% -> 0.044350181 | AI84: =AH84+_xlfn.NORM.DIST(RAND(), 0, 1, FALSE)% -> 0.048290988 | AJ84: =AI84+_xlfn.NORM.DIST(RAND(), 0, 1, FALSE)% -> 0.052280209 | AK84: =AJ84+_xlfn.NORM.DIST(RAND(), 0, 1, FALSE)% -> 0.055847247 | AL84: =AK84+_xlfn.NORM.DIST(RAND(), 0, 1, FALSE)% -> 0.05846796 | AP84: Edge | AQ84: =AC70*AQ70 -> 0 | AR84: =AD70*AR70 -> 0 | AS84: =AE70*AS70 -> 0 | AT84: =AF70*AT70 -> 6350000 | AU84: =AG70*AU70 -> 7257177.4 | AV84: =AH70*AV70 -> 8313467 | AW84: =AI70*AW70 -> 9550387.9 | AX84: =AJ70*AX70 -> 11012744 | ... AZ84: =AL70*AZ70 -> 14805170
B85: Fog | C85: 0.04 | D85: =C85+_xlfn.NORM.DIST(RAND(), 0, 1, FALSE)% -> 0.042523877 | E85: =D85+_xlfn.NORM.DIST(RAND(), 0, 1, FALSE)% -> 0.045379546 | F85: =E85+_xlfn.NORM.DIST(RAND(), 0, 1, FALSE)% -> 0.048955336 | G85: =F85+_xlfn.NORM.DIST(RAND(), 0, 1, FALSE)% -> 0.051978713 | H85: =G85+_xlfn.NORM.DIST(RAND(), 0, 1, FALSE)% -> 0.054767515 | I85: =H85+_xlfn.NORM.DIST(RAND(), 0, 1, FALSE)% -> 0.057849365 | J85: =I85+_xlfn.NORM.DIST(RAND(), 0, 1, FALSE)% -> 0.061064592 | K85: =J85+_xlfn.NORM.DIST(RAND(), 0, 1, FALSE)% -> 0.064797174 | L85: =K85+_xlfn.NORM.DIST(RAND(), 0, 1, FALSE)% -> 0.068473978 | P85: Fog | R85: =D71*R71 -> 0 | S85: =E71*S71 -> 0 | T85: =F71*T71 -> 0 | U85: =G71*U71 -> 6032500 | V85: =H71*V71 -> 6545962.5 | W85: =I71*W71 -> 7121959.4 | X85: =J71*X71 -> 7771280 | Y85: =K71*Y71 -> 8505573.7 | Z85: =L71*Z71 -> 9341997.2 | AB85: Fog | AC85: 0.04 | AD85: =AC85+_xlfn.NORM.DIST(RAND(), 0, 1, FALSE)% -> 0.043776396 | AE85: =AD85+_xlfn.NORM.DIST(RAND(), 0, 1, FALSE)% -> 0.047421688 | AF85: =AE85+_xlfn.NORM.DIST(RAND(), 0, 1, FALSE)% -> 0.050172956 | AG85: =AF85+_xlfn.NORM.DIST(RAND(), 0, 1, FALSE)% -> 0.05265202 | AH85: =AG85+_xlfn.NORM.DIST(RAND(), 0, 1, FALSE)% -> 0.0562124 | AI85: =AH85+_xlfn.NORM.DIST(RAND(), 0, 1, FALSE)% -> 0.059858606 | AJ85: =AI85+_xlfn.NORM.DIST(RAND(), 0, 1, FALSE)% -> 0.062881629 | AK85: =AJ85+_xlfn.NORM.DIST(RAND(), 0, 1, FALSE)% -> 0.066665453 | AL85: =AK85+_xlfn.NORM.DIST(RAND(), 0, 1, FALSE)% -> 0.070387982 | AP85: Fog | AR85: =AD71*AR71 -> 0 | AS85: =AE71*AS71 -> 0 | AT85: =AF71*AT71 -> 0 | AU85: =AG71*AU71 -> 6032500 | AV85: =AH71*AV71 -> 6985135.6 | AW85: =AI71*AW71 -> 8115565.6 | AX85: =AJ71*AX71 -> 9461487.2 | AY85: =AK71*AY71 -> 11062085 | AZ85: =AL71*AZ71 -> 12979498
B86: Enterprise | C86: 0.04 | D86: =C86+_xlfn.NORM.DIST(RAND(), 0, 1, FALSE)% -> 0.043402098 | E86: =D86+_xlfn.NORM.DIST(RAND(), 0, 1, FALSE)% -> 0.047355224 | F86: =E86+_xlfn.NORM.DIST(RAND(), 0, 1, FALSE)% -> 0.05134241 | G86: =F86+_xlfn.NORM.DIST(RAND(), 0, 1, FALSE)% -> 0.054127743 | H86: =G86+_xlfn.NORM.DIST(RAND(), 0, 1, FALSE)% -> 0.057473197 | I86: =H86+_xlfn.NORM.DIST(RAND(), 0, 1, FALSE)% -> 0.061085964 | J86: =I86+_xlfn.NORM.DIST(RAND(), 0, 1, FALSE)% -> 0.063780286 | K86: =J86+_xlfn.NORM.DIST(RAND(), 0, 1, FALSE)% -> 0.066979502 | L86: =K86+_xlfn.NORM.DIST(RAND(), 0, 1, FALSE)% -> 0.070147918 | P86: Enterprise | S86: =E72*S72 -> 0 | T86: =F72*T72 -> 0 | U86: =G72*U72 -> 0 | V86: =H72*V72 -> 3180000 | W86: =I72*W72 -> 3468691.9 | X86: =J72*X72 -> 3796518.5 | Y86: =K72*Y72 -> 4165879.4 | Z86: =L72*Z72 -> 4584922.5 | AB86: Enterprise | AC86: 0.01 | AD86: =AC86+_xlfn.NORM.DIST(RAND(), 0, 1, FALSE)% -> 0.013427971 | AE86: =AD86+_xlfn.NORM.DIST(RAND(), 0, 1, FALSE)% -> 0.016453977 | AF86: =AE86+_xlfn.NORM.DIST(RAND(), 0, 1, FALSE)% -> 0.019589677 | AG86: =AF86+_xlfn.NORM.DIST(RAND(), 0, 1, FALSE)% -> 0.022528645 | AH86: =AG86+_xlfn.NORM.DIST(RAND(), 0, 1, FALSE)% -> 0.025981118 | AI86: =AH86+_xlfn.NORM.DIST(RAND(), 0, 1, FALSE)% -> 0.028755373 | AJ86: =AI86+_xlfn.NORM.DIST(RAND(), 0, 1, FALSE)% -> 0.032736735 | AK86: =AJ86+_xlfn.NORM.DIST(RAND(), 0, 1, FALSE)% -> 0.03569042 | AL86: =AK86+_xlfn.NORM.DIST(RAND(), 0, 1, FALSE)% -> 0.039667423 | AP86: Enterprise | AS86: =AE72*AS72 -> 0 | AT86: =AF72*AT72 -> 0 | AU86: =AG72*AU72 -> 0 | AV86: =AH72*AV72 -> 3180000 | AW86: =AI72*AW72 -> 3588881.9 | AX86: =AJ72*AX72 -> 4061289.7 | AY86: =AK72*AY72 -> 4613667.4 | AZ86: =AL72*AZ72 -> 5256164.3
B87: software stacks | C87: 0 | D87: =C87+_xlfn.NORM.DIST(RAND(), 0, 1, FALSE)% -> 0.0037944881 | E87: =D87+_xlfn.NORM.DIST(RAND(), 0, 1, FALSE)% -> 0.0077034466 | F87: =E87+_xlfn.NORM.DIST(RAND(), 0, 1, FALSE)% -> 0.011349364 | G87: =F87+_xlfn.NORM.DIST(RAND(), 0, 1, FALSE)% -> 0.015285881 | H87: =G87+_xlfn.NORM.DIST(RAND(), 0, 1, FALSE)% -> 0.018831766 | I87: =H87+_xlfn.NORM.DIST(RAND(), 0, 1, FALSE)% -> 0.021756198 | J87: =I87+_xlfn.NORM.DIST(RAND(), 0, 1, FALSE)% -> 0.024283478 | K87: =J87+_xlfn.NORM.DIST(RAND(), 0, 1, FALSE)% -> 0.027928385 | L87: =K87+_xlfn.NORM.DIST(RAND(), 0, 1, FALSE)% -> 0.031363574 | P87: software stacks | Q87: =C73*Q73 + C74*Q74 -> 0 | R87: =D73*R73 + D74*R74 -> 0 | S87: =E73*S73 + E74*S74 -> 0 | T87: =F73*T73 + F74*T74 -> 3610000 | U87: =G73*U73 + G74*U74 -> 4142246.7 | V87: =H73*V73 + H74*V74 -> 4474396.6 | W87: =I73*W73 + I74*W74 -> 4810056.7 | X87: =J73*X73 + J74*X74 -> 5151507.3 | ... Z87: =L73*Z73 + L74*Z74 -> 5870322.5 | AB87: software stacks | AC87: 0 | AD87: =AC87+_xlfn.NORM.DIST(RAND(), 0, 1, FALSE)% -> 0.0038807091 | AE87: =AD87+_xlfn.NORM.DIST(RAND(), 0, 1, FALSE)% -> 0.0063216928 | AF87: =AE87+_xlfn.NORM.DIST(RAND(), 0, 1, FALSE)% -> 0.0097646402 | AG87: =AF87+_xlfn.NORM.DIST(RAND(), 0, 1, FALSE)% -> 0.013329659 | AH87: =AG87+_xlfn.NORM.DIST(RAND(), 0, 1, FALSE)% -> 0.016741907 | AI87: =AH87+_xlfn.NORM.DIST(RAND(), 0, 1, FALSE)% -> 0.020728247 | AJ87: =AI87+_xlfn.NORM.DIST(RAND(), 0, 1, FALSE)% -> 0.02471254 | AK87: =AJ87+_xlfn.NORM.DIST(RAND(), 0, 1, FALSE)% -> 0.028283073 | AL87: =AK87+_xlfn.NORM.DIST(RAND(), 0, 1, FALSE)% -> 0.0322463 | AP87: software stacks | AQ87: =AC73*AQ73 + AC74*AQ74 -> 0 | AR87: =AD73*AR73 + AD74*AR74 -> 0 | AS87: =AE73*AS73 + AE74*AS74 -> 0 | AT87: =AF73*AT73 + AF74*AT74 -> 3610000 | AU87: =AG73*AU73 + AG74*AU74 -> 4209775.4 | AV87: =AH73*AV73 + AH74*AV74 -> 4850212.7 | AW87: =AI73*AW73 + AI74*AW74 -> 5540954.1 | AX87: =AJ73*AX73 + AJ74*AX74 -> 6299323.8 | ... AZ87: =AL73*AZ73 + AL74*AZ74 -> 8087943.4
B88: system integration | C88: 0 | D88: =C88+_xlfn.NORM.DIST(RAND(), 0, 1, FALSE)% -> 0.0038643518 | E88: =D88+_xlfn.NORM.DIST(RAND(), 0, 1, FALSE)% -> 0.0072433462 | F88: =E88+_xlfn.NORM.DIST(RAND(), 0, 1, FALSE)% -> 0.010396524 | G88: =F88+_xlfn.NORM.DIST(RAND(), 0, 1, FALSE)% -> 0.014384441 | H88: =G88+_xlfn.NORM.DIST(RAND(), 0, 1, FALSE)% -> 0.018328142 | I88: =H88+_xlfn.NORM.DIST(RAND(), 0, 1, FALSE)% -> 0.022097648 | J88: =I88+_xlfn.NORM.DIST(RAND(), 0, 1, FALSE)% -> 0.025117138 | K88: =J88+_xlfn.NORM.DIST(RAND(), 0, 1, FALSE)% -> 0.029081995 | L88: =K88+_xlfn.NORM.DIST(RAND(), 0, 1, FALSE)% -> 0.032082798 | P88: system integration | Q88: =C75*Q75 -> 0 | R88: =D75*R75 -> 0 | S88: =E75*S75 -> 0 | T88: =F75*T75 -> 0 | U88: =G75*U75 -> 150000 | V88: =H75*V75 -> 156950.63 | W88: =I75*W75 -> 164861.8 | X88: =J75*X75 -> 173812.77 | ... Z88: =L75*Z75 -> 195093.86 | AB88: system integration | AC88: 0 | AD88: =AC88+_xlfn.NORM.DIST(RAND(), 0, 1, FALSE)% -> 0.002798714 | AE88: =AD88+_xlfn.NORM.DIST(RAND(), 0, 1, FALSE)% -> 0.0063214686 | AF88: =AE88+_xlfn.NORM.DIST(RAND(), 0, 1, FALSE)% -> 0.0088174371 | AG88: =AF88+_xlfn.NORM.DIST(RAND(), 0, 1, FALSE)% -> 0.012563297 | AH88: =AG88+_xlfn.NORM.DIST(RAND(), 0, 1, FALSE)% -> 0.015377477 | AI88: =AH88+_xlfn.NORM.DIST(RAND(), 0, 1, FALSE)% -> 0.019349771 | AJ88: =AI88+_xlfn.NORM.DIST(RAND(), 0, 1, FALSE)% -> 0.023337433 | AK88: =AJ88+_xlfn.NORM.DIST(RAND(), 0, 1, FALSE)% -> 0.026874603 | AL88: =AK88+_xlfn.NORM.DIST(RAND(), 0, 1, FALSE)% -> 0.030311302 | AP88: system integration | AQ88: =AC75*AQ75 -> 0 | AR88: =AD75*AR75 -> 0 | AS88: =AE75*AS75 -> 0 | AT88: =AF75*AT75 -> 0 | AU88: =AG75*AU75 -> 150000 | AV88: =AH75*AV75 -> 167072.94 | AW88: =AI75*AW75 -> 186606.31 | AX88: =AJ75*AX75 -> 209238.81 | ... AZ88: =AL75*AZ75 -> 266050.39
